Workbook

Sheet Dashboard
B1: SMR vs alternatives — digital-twin financial model (Stalowa Wola, BWRX-300)
B2: AM R&D / EnergyScope · real PLN 2026 · hourly dispatch from the Python twin (smrtwin) · all formulas live
B3: Assumption case | C3: CENTRAL | D3: LOW = every parameter at its low value (cheap SMR AND low prices); use Input to mix cases.
B4: Case index (1 = LOW, 2 = CENTRAL, 3 = HIGH) | C4: =MATCH(C3,{"LOW","CENTRAL","HIGH"},0) -> 2
B6: Key results by scenario (selected case)
B7: Scenario | C7: NPV post-tax (m PLN) | D7: IRR post-tax | E7: LCOE (PLN/MWh) | F7: Levelised revenue (PLN/MWh) | G7: Avg capacity factor | H7: Local gov. revenue (m PLN/op-yr) | I7: CfD/support PV (m PLN) | J7: Break-even strike / premium (PLN/MWh)
B8: SMR · CfD (two-way, PEJ template) | C8: =Model_SMR_CfD!$D$105 -> 501.54656 | D8: =Model_SMR_CfD!$D$107 -> 0.052593 | E8: =Model_SMR_CfD!$D$119 -> 487.94313 | F8: =Model_SMR_CfD!$D$120 -> 533.57714 | G8: =Model_SMR_CfD!$D$121 -> 0.91178077 | H8: =Model_SMR_CfD!$D$140 -> 78.399928 | I8: =Model_SMR_CfD!$D$122 -> 5501.49 | J8: =Model_SMR_CfD!$D$123 -> 120.84834
B9: SMR · fixed price = last-12-month average spot | C9: =Model_SMR_Fixed!$D$102 -> -821.15934 | D9: =Model_SMR_Fixed!$D$104 -> 0.045942837 | E9: =Model_SMR_Fixed!$D$116 -> 479.35669 | F9: =Model_SMR_Fixed!$D$117 -> 483.39 | G9: =Model_SMR_Fixed!$D$118 -> 0.93709361 | H9: =Model_SMR_Fixed!$D$137 -> 78.094634 | I9: =Model_SMR_Fixed!$D$119 -> 0 | J9: =Model_SMR_Fixed!$D$120 -> 26.474515
B10: SMR · merchant, dynamic 50–100 % dispatch | C10: =Model_SMR_Dynamic!$D$101 -> -5904.5069 | D10: =Model_SMR_Dynamic!$D$103 -> 0.028078146 | E10: =Model_SMR_Dynamic!$D$115 -> 629.40754 | F10: =Model_SMR_Dynamic!$D$116 -> 401.9501 | G10: =Model_SMR_Dynamic!$D$117 -> 0.88969251 | H10: =Model_SMR_Dynamic!$D$136 -> 63.914606 | I10: =Model_SMR_Dynamic!$D$118 -> 0 | J10: =Model_SMR_Dynamic!$D$119 -> 291.51366
B11: CCGT 1+1 ~300 MW · merchant dynamic | C11: =Model_CCGT!$D$100 -> -1718.6727 | D11: =Model_CCGT!$D$102 -> n/a | E11: =Model_CCGT!$D$114 -> 958.88997 | F11: =Model_CCGT!$D$115 -> 633.17192 | G11: =Model_CCGT!$D$116 -> 0.17191977 | H11: =Model_CCGT!$D$135 -> 6.0621583 | I11: =Model_CCGT!$D$117 -> 0 | J11: =Model_CCGT!$D$118 -> 402.12105
B12: OCGT 2×150 MW · merchant dynamic | C12: =Model_OCGT!$D$100 -> -998.17669 | D12: =Model_OCGT!$D$102 -> n/a | E12: =Model_OCGT!$D$114 -> 1857.9693 | F12: =Model_OCGT!$D$115 -> 1060.5848 | G12: =Model_OCGT!$D$116 -> 0.037266172 | H12: =Model_OCGT!$D$135 -> 2.5685396 | I12: =Model_OCGT!$D$117 -> 0 | J12: =Model_OCGT!$D$118 -> 984.42538
B13: Gas engines 4×76.5 MW · merchant dynamic | C13: =Model_Engines!$D$100 -> -221.94746 | D13: =Model_Engines!$D$102 -> -0.26465621 | E13: =Model_Engines!$D$114 -> 1098.9469 | F13: =Model_Engines!$D$115 -> 797.03141 | G13: =Model_Engines!$D$116 -> 0.096557306 | H13: =Model_Engines!$D$135 -> 0.79741117 | I13: =Model_Engines!$D$117 -> 0 | J13: =Model_Engines!$D$118 -> 373.42931
B15: Break-even column: for the CfD sheet = strike (EUR/MWh) at which NPV = 0 (pre-tax exact / post-tax approximated as linear in strike); for other sheets = constant PLN/MWh premium on all output needed for NPV = 0.
B16: 'Alternative cost' reading: NPV of a merchant asset = value of its output at market prices − its full cost, i.e. minus the net cost to the system of building it instead of buying from the market.
B18: Key figures by year — selected case (m PLN)
B19: Year | C19: 2030 | D19: 2035 | E19: 2040 | F19: 2045 | G19: 2050 | H19: 2055 | I19: 2060 | J19: 2065 | K19: 2070
B20: SMR · CfD (two-way, PEJ template) — post-tax FCF | C20: =Model_SMR_CfD!J102 -> -1948.2073 | D20: =Model_SMR_CfD!O102 -> 818.75689 | E20: =Model_SMR_CfD!T102 -> 885.35843 | F20: =Model_SMR_CfD!Y102 -> 840.37602 | G20: =Model_SMR_CfD!AD102 -> 785.01443 | H20: =Model_SMR_CfD!AI102 -> 745.27054 | I20: =Model_SMR_CfD!AN102 -> 729.197 | J20: =Model_SMR_CfD!AS102 -> 769.00426 | K20: =Model_SMR_CfD!AX102 -> 729.2079
B21: SMR · CfD (two-way, PEJ template) — revenue | C21: =Model_SMR_CfD!J69 -> 0 | D21: =Model_SMR_CfD!O69 -> 1331.9653 | E21: =Model_SMR_CfD!T69 -> 1317.9867 | F21: =Model_SMR_CfD!Y69 -> 1317.9955 | G21: =Model_SMR_CfD!AD69 -> 1374.4562 | H21: =Model_SMR_CfD!AI69 -> 1318.0599 | I21: =Model_SMR_CfD!AN69 -> 1318.1157 | J21: =Model_SMR_CfD!AS69 -> 1374.5809 | K21: =Model_SMR_CfD!AX69 -> 1318.1292
B22: SMR · CfD (two-way, PEJ template) — local gov. revenue | C22: =Model_SMR_CfD!J138 -> 1.3540221 | D22: =Model_SMR_CfD!O138 -> 47.697388 | E22: =Model_SMR_CfD!T138 -> 47.697388 | F22: =Model_SMR_CfD!Y138 -> 60.956232 | G22: =Model_SMR_CfD!AD138 -> 91.754744 | H22: =Model_SMR_CfD!AI138 -> 89.007018 | I22: =Model_SMR_CfD!AN138 -> 93.764095 | J22: =Model_SMR_CfD!AS138 -> 96.516202 | K22: =Model_SMR_CfD!AX138 -> 93.764848
B24: SMR · fixed price = last-12-month average spot — post-tax FCF | C24: =Model_SMR_Fixed!J99 -> -1948.2073 | D24: =Model_SMR_Fixed!O99 -> 681.44558 | E24: =Model_SMR_Fixed!T99 -> 748.74132 | F24: =Model_SMR_Fixed!Y99 -> 716.73487 | G24: =Model_SMR_Fixed!AD99 -> 730.80081 | H24: =Model_SMR_Fixed!AI99 -> 634.55416 | I24: =Model_SMR_Fixed!AN99 -> 618.42672 | J24: =Model_SMR_Fixed!AS99 -> 653.4698 | K24: =Model_SMR_Fixed!AX99 -> 618.42672
B25: SMR · fixed price = last-12-month average spot — revenue | C25: =Model_SMR_Fixed!J66 -> 0 | D25: =Model_SMR_Fixed!O66 -> 1194.128 | E25: =Model_SMR_Fixed!T66 -> 1181.5985 | F25: =Model_SMR_Fixed!Y66 -> 1181.5985 | G25: =Model_SMR_Fixed!AD66 -> 1232.2385 | H25: =Model_SMR_Fixed!AI66 -> 1181.5985 | I25: =Model_SMR_Fixed!AN66 -> 1181.5985 | J25: =Model_SMR_Fixed!AS66 -> 1232.2385 | K25: =Model_SMR_Fixed!AX66 -> 1181.5985
B26: SMR · fixed price = last-12-month average spot — local gov. revenue | C26: =Model_SMR_Fixed!J135 -> 1.3540221 | D26: =Model_SMR_Fixed!O135 -> 47.697388 | E26: =Model_SMR_Fixed!T135 -> 47.697388 | F26: =Model_SMR_Fixed!Y135 -> 57.130871 | G26: =Model_SMR_Fixed!AD135 -> 65.736336 | H26: =Model_SMR_Fixed!AI135 -> 81.352553 | I26: =Model_SMR_Fixed!AN135 -> 86.105903 | J26: =Model_SMR_Fixed!AS135 -> 88.528634 | K26: =Model_SMR_Fixed!AX135 -> 86.105903
B28: SMR · merchant, dynamic 50–100 % dispatch — post-tax FCF | C28: =Model_SMR_Dynamic!J98 -> -1948.2073 | D28: =Model_SMR_Dynamic!O98 -> 473.065 | E28: =Model_SMR_Dynamic!T98 -> 514.53907 | F28: =Model_SMR_Dynamic!Y98 -> 493.88482 | G28: =Model_SMR_Dynamic!AD98 -> 491.78984 | H28: =Model_SMR_Dynamic!AI98 -> 457.86659 | I28: =Model_SMR_Dynamic!AN98 -> 449.7651 | J28: =Model_SMR_Dynamic!AS98 -> 483.99276 | K28: =Model_SMR_Dynamic!AX98 -> 409.14574
B29: SMR · merchant, dynamic 50–100 % dispatch — revenue | C29: =Model_SMR_Dynamic!J65 -> 0 | D29: =Model_SMR_Dynamic!O65 -> 979.13023 | E29: =Model_SMR_Dynamic!T65 -> 939.64688 | F29: =Model_SMR_Dynamic!Y65 -> 927.49534 | G29: =Model_SMR_Dynamic!AD65 -> 960.02762 | H29: =Model_SMR_Dynamic!AI65 -> 915.19418 | I29: =Model_SMR_Dynamic!AN65 -> 915.05353 | J29: =Model_SMR_Dynamic!AS65 -> 960.13668 | K29: =Model_SMR_Dynamic!AX65 -> 915.04427
B30: SMR · merchant, dynamic 50–100 % dispatch — local gov. revenue | C30: =Model_SMR_Dynamic!J134 -> 1.3540221 | D30: =Model_SMR_Dynamic!O134 -> 47.697388 | E30: =Model_SMR_Dynamic!T134 -> 47.697388 | F30: =Model_SMR_Dynamic!Y134 -> 50.236063 | G30: =Model_SMR_Dynamic!AD134 -> 58.341521 | H30: =Model_SMR_Dynamic!AI134 -> 57.291963 | I30: =Model_SMR_Dynamic!AN134 -> 59.667469 | J30: =Model_SMR_Dynamic!AS134 -> 60.726446 | K30: =Model_SMR_Dynamic!AX134 -> 71.637094
B32: CCGT 1+1 ~300 MW · merchant dynamic — post-tax FCF | C32: =Model_CCGT!J97 -> -245.625 | D32: =Model_CCGT!O97 -> 17.263541 | E32: =Model_CCGT!T97 -> 1.8122454 | F32: =Model_CCGT!Y97 -> -1.3408349 | G32: =Model_CCGT!AD97 -> -4.1867527 | H32: =Model_CCGT!AI97 -> -3.7376429 | I32: =Model_CCGT!AN97 -> -96.212029 | J32: =Model_CCGT!AS97 -> 0 | K32: =Model_CCGT!AX97 -> 0
B33: CCGT 1+1 ~300 MW · merchant dynamic — revenue | C33: =Model_CCGT!J63 -> 0 | D33: =Model_CCGT!O63 -> 359.67566 | E33: =Model_CCGT!T63 -> 273.23157 | F33: =Model_CCGT!Y63 -> 255.78964 | G33: =Model_CCGT!AD63 -> 246.78946 | H33: =Model_CCGT!AI63 -> 249.22923 | I33: =Model_CCGT!AN63 -> 256.74324 | J33: =Model_CCGT!AS63 -> 0 | K33: =Model_CCGT!AX63 -> 0
B34: CCGT 1+1 ~300 MW · merchant dynamic — local gov. revenue | C34: =Model_CCGT!J133 -> 0.17473725 | D34: =Model_CCGT!O133 -> 6.0621583 | E34: =Model_CCGT!T133 -> 6.0621583 | F34: =Model_CCGT!Y133 -> 6.0621583 | G34: =Model_CCGT!AD133 -> 6.0621583 | H34: =Model_CCGT!AI133 -> 6.0621583 | I34: =Model_CCGT!AN133 -> 6.0621583 | J34: =Model_CCGT!AS133 -> 0 | K34: =Model_CCGT!AX133 -> 0
B36: OCGT 2×150 MW · merchant dynamic — post-tax FCF | C36: =Model_OCGT!J97 -> -675 | D36: =Model_OCGT!O97 -> 9.6453976 | E36: =Model_OCGT!T97 -> 4.9058037 | F36: =Model_OCGT!Y97 -> 3.6831206 | G36: =Model_OCGT!AD97 -> 2.5664885 | H36: =Model_OCGT!AI97 -> 2.5690681 | I36: =Model_OCGT!AN97 -> -48.41191 | J36: =Model_OCGT!AS97 -> 0 | K36: =Model_OCGT!AX97 -> 0
B37: OCGT 2×150 MW · merchant dynamic — revenue | C37: =Model_OCGT!J63 -> 0 | D37: =Model_OCGT!O63 -> 121.15856 | E37: =Model_OCGT!T63 -> 103.19991 | F37: =Model_OCGT!Y63 -> 99.267437 | G37: =Model_OCGT!AD63 -> 95.58837 | H37: =Model_OCGT!AI63 -> 95.571413 | I37: =Model_OCGT!AN63 -> 95.782062 | J37: =Model_OCGT!AS63 -> 0 | K37: =Model_OCGT!AX63 -> 0
B38: OCGT 2×150 MW · merchant dynamic — local gov. revenue | C38: =Model_OCGT!J133 -> 0.6290541 | D38: =Model_OCGT!O133 -> 2.5685396 | E38: =Model_OCGT!T133 -> 2.5685396 | F38: =Model_OCGT!Y133 -> 2.5685396 | G38: =Model_OCGT!AD133 -> 2.5685396 | H38: =Model_OCGT!AI133 -> 2.5685396 | I38: =Model_OCGT!AN133 -> 2.5685396 | J38: =Model_OCGT!AS133 -> 0 | K38: =Model_OCGT!AX133 -> 0
B40: Gas engines 4×76.5 MW · merchant dynamic — post-tax FCF | C40: =Model_Engines!J97 -> -179.28 | D40: =Model_Engines!O97 -> 6.9243515 | E40: =Model_Engines!T97 -> 4.6756388 | F40: =Model_Engines!Y97 -> 4.1875726 | G40: =Model_Engines!AD97 -> 3.5670596 | H40: =Model_Engines!AI97 -> -9.9261317 | I40: =Model_Engines!AN97 -> 0 | J40: =Model_Engines!AS97 -> 0 | K40: =Model_Engines!AX97 -> 0
B41: Gas engines 4×76.5 MW · merchant dynamic — revenue | C41: =Model_Engines!J63 -> 0 | D41: =Model_Engines!O63 -> 56.539946 | E41: =Model_Engines!T63 -> 46.002682 | F41: =Model_Engines!Y63 -> 44.468138 | G41: =Model_Engines!AD63 -> 42.613899 | H41: =Model_Engines!AI63 -> 43.059604 | I41: =Model_Engines!AN63 -> 0 | J41: =Model_Engines!AS63 -> 0 | K41: =Model_Engines!AX63 -> 0
B42: Gas engines 4×76.5 MW · merchant dynamic — local gov. revenue | C42: =Model_Engines!J133 -> 0.15097298 | D42: =Model_Engines!O133 -> 0.77717957 | E42: =Model_Engines!T133 -> 0.77717957 | F42: =Model_Engines!Y133 -> 0.77717957 | G42: =Model_Engines!AD133 -> 0.82282914 | H42: =Model_Engines!AI133 -> 0.77717957 | I42: =Model_Engines!AN133 -> 0 | J42: =Model_Engines!AS133 -> 0 | K42: =Model_Engines!AX133 -> 0

Sheet Input
B2: Input
B3: Blue = hard-coded assumption (edit LOW / CENTRAL / HIGH); green-shaded column H = value selected by the case switch on Dashboard!C4. Money in real PLN, 2026 price level.
B5: # | C5: Parameter | D5: Unit | E5: LOW | F5: CENTRAL | G5: HIGH | H5: Selected | I5: Source / note
B8: 1. Model set-up
C9: Price base year (real terms) | D9: year | E9: 2026 | F9: 2026 | G9: 2026 | H9: =INDEX(E9:G9,1,Dashboard!$C$4) -> 2026 | I9: All money real PLN at 2026 level
C10: EUR/PLN | D10: PLN | E10: 4.3633 | F10: 4.3633 | G10: 4.3633 | H10: =INDEX(E10:G10,1,Dashboard!$C$4) -> 4.3633 | I10: NBP table A mid, 18 Sep 2026 (4.3633)
C11: USD/PLN | D11: PLN | E11: 3.7998 | F11: 3.7998 | G11: 3.7998 | H11: =INDEX(E11:G11,1,Dashboard!$C$4) -> 3.7998 | I11: NBP table A mid, 18 Sep 2026
C12: Hours per year | D12: h | E12: 8760 | F12: 8760 | G12: 8760 | H12: =INDEX(E12:G12,1,Dashboard!$C$4) -> 8760
B14: 2. Macro and cost of capital
C15: Real post-tax WACC — SMR with CfD | D15: % | E15: 0.04 | F15: 0.05 | G15: 0.065 | H15: =INDEX(E15:G15,1,Dashboard!$C$4) -> 0.05 | I15: PEJ EC decision (OJ C 2025/1389) Table 1: nominal 6–8 % with aid; deflated at 2.5 % CPI
C16: Real post-tax WACC — SMR merchant | D16: % | E16: 0.06 | F16: 0.07 | G16: 0.085 | H16: =INDEX(E16:G16,1,Dashboard!$C$4) -> 0.07 | I16: PEJ Table 1 without aid: 8.5–10.5 % nominal
C17: Real post-tax WACC — gas | D17: % | E17: 0.06 | F17: 0.07 | G17: 0.085 | H17: =INDEX(E17:G17,1,Dashboard!$C$4) -> 0.07 | I17: Ministry of Climate LCOE note 7 % real (70 % debt @6 %, 30 % equity @9.5 %)
C18: CPI long run (memo, for nominal conversions) | D18: % | E18: 0.025 | F18: 0.025 | G18: 0.025 | H18: =INDEX(E18:G18,1,Dashboard!$C$4) -> 0.025 | I18: NBP target 2.5 %
B20: 3. Market — Polish day-ahead market (TGE RDN / SDAC), gas, CO2, capacity
C21: Reference year mean day-ahead price (Sep 2025–Aug 2026, hourly PSE/TGE data) | D21: PLN/MWh | E21: 483.39 | F21: 483.39 | G21: 483.39 | H21: =INDEX(E21:G21,1,Dashboard!$C$4) -> 483.39 | I21: PSE csdac-pln API, 8,760 hourly values; TGE 2025 vol.-weighted 446.30
C22: Fixed price for SMR-fixed scenario (= reference mean unless overridden) | D22: PLN/MWh | E22: 483.39 | F22: 483.39 | G22: 483.39 | H22: =INDEX(E22:G22,1,Dashboard!$C$4) -> 483.39 | I22: Scenario S1b: 'average spot over the last year'
C23: Capacity-market price (successor mechanism, if any) | D23: PLN/kW-yr | E23: 0 | F23: 0 | G23: 400 | H23: =INDEX(E23:G23,1,Dashboard!$C$4) -> 0 | I23: 2030 main auction cleared 465.02 PLN/kW-yr (URE, 11 Dec 2025); no auction exists for delivery ≥2031 → 0 in base
C24: Capacity contract length | D24: years | E24: 17 | F24: 17 | G24: 17 | H24: =INDEX(E24:G24,1,Dashboard!$C$4) -> 17 | I24: 17 y new low-emission; 15 y new gas
C25: De-rating factor nuclear (KWD) | D25: # | E25: 0.9383 | F25: 0.9383 | G25: 0.9383 | H25: =INDEX(E25:G25,1,Dashboard!$C$4) -> 0.9383 | I25: Dz.U. 2025 poz. 1066 (2030 auction parameters)
C26: De-rating factor CCGT | D26: # | E26: 0.9315 | F26: 0.9315 | G26: 0.9315 | H26: =INDEX(E26:G26,1,Dashboard!$C$4) -> 0.9315 | I26: same
C27: De-rating factor OCGT / engines | D27: # | E27: 0.9328 | F27: 0.9328 | G27: 0.9328 | H27: =INDEX(E27:G27,1,Dashboard!$C$4) -> 0.9328 | I27: same
C28: Balancing-capacity revenue CCGT | D28: PLN/kW-yr | E28: 0 | F28: 15 | G28: 40 | H28: =INDEX(E28:G28,1,Dashboard!$C$4) -> 15 | I28: aFRR/mFRR 2025 ~180 PLN/MW/h falling to 50–90 by 2027; low contracted share
C29: Balancing-capacity revenue OCGT / engines | D29: PLN/kW-yr | E29: 10 | F29: 40 | G29: 120 | H29: =INDEX(E29:G29,1,Dashboard!$C$4) -> 40 | I29: mFRR/RR from standstill
C30: CO2 emission factor natural gas | D30: t/MWh_th | E30: 0.2006 | F30: 0.2006 | G30: 0.2006 | H30: =INDEX(E30:G30,1,Dashboard!$C$4) -> 0.2006 | I30: KOBiZE 2025 ETS factor 55.73 kg/GJ
C31: URE licence fee (share of revenue) | D31: % | E31: 0.005 | F31: 0.005 | G31: 0.005 | H31: =INDEX(E31:G31,1,Dashboard!$C$4) -> 0.005 | I31: Proposal from 2027: 0.5 % uncapped (current 0.05 %, cap 2.5 m PLN)
C32: Annual mean day-ahead price path (real 2026) | D32: PLN/MWh | I32: 2027–29 TGE BASE_Y forwards (Aug-2026 VWAP 495.5/444.5/420.1); 2030+ judgement bridging TGE 2029 and PEJ counterfactual; hourly shape from the twin | J32: 2027 | K32: 2028 | L32: 2029 | M32: 2030 | N32: 2031 | O32: 2032 | P32: 2033 | Q32: 2034 | R32: 2035 | S32: 2036 | T32: 2037 | U32: 2038 | V32: 2039 | W32: 2040 | X32: 2041 | Y32: 2042 | Z32: 2043 | AA32: 2044 | AB32: 2045 | AC32: 2046 | AD32: 2047 | AE32: 2048 | AF32: 2049 | AG32: 2050 | AH32: 2051 | AI32: 2052 | AJ32: 2053 | AK32: 2054 | AL32: 2055 | AM32: 2056 | AN32: 2057 | AO32: 2058 | AP32: 2059 | AQ32: 2060 | AR32: 2061 | AS32: 2062 | AT32: 2063 | AU32: 2064 | AV32: 2065 | AW32: 2066 | AX32: 2067 | AY32: 2068 | AZ32: 2069 | BA32: 2070 | BB32: 2071 | BC32: 2072 | BD32: 2073 | BE32: 2074 | BF32: 2075 | BG32: 2076 | BH32: 2077 | BI32: 2078 | BJ32: 2079 | BK32: 2080 | BL32: 2081 | BM32: 2082 | BN32: 2083 | BO32: 2084 | BP32: 2085 | BQ32: 2086 | BR32: 2087 | BS32: 2088 | BT32: 2089 | BU32: 2090 | BV32: 2091 | BW32: 2092 | BX32: 2093 | BY32: 2094 | BZ32: 2095 | CA32: 2096
C33: LOW | J33: 440 | K33: 380 | L33: 350 | M33: 320 | N33: 316 | O33: 312 | P33: 308 | Q33: 304 | R33: 300 | S33: 298 | T33: 296 | U33: 294 | V33: 292 | W33: 290 | X33: 289 | Y33: 288 | Z33: 287 | AA33: 286 | AB33: 285 | AC33: 284 | AD33: 283 | AE33: 282 | AF33: 281 | AG33: 280 | AH33: 280 | AI33: 280 | AJ33: 280 | AK33: 280 | AL33: 280 | AM33: 280 | AN33: 280 | AO33: 280 | AP33: 280 | AQ33: 280 | AR33: 280 | AS33: 280 | AT33: 280 | AU33: 280 | AV33: 280 | AW33: 280 | AX33: 280 | AY33: 280 | AZ33: 280 | BA33: 280 | BB33: 280 | BC33: 280 | BD33: 280 | BE33: 280 | BF33: 280 | BG33: 280 | BH33: 280 | BI33: 280 | BJ33: 280 | BK33: 280 | BL33: 280 | BM33: 280 | BN33: 280 | BO33: 280 | BP33: 280 | BQ33: 280 | BR33: 280 | BS33: 280 | BT33: 280 | BU33: 280 | BV33: 280 | BW33: 280 | BX33: 280 | BY33: 280 | BZ33: 280 | CA33: 280
C34: CENTRAL | J34: 496 | K34: 445 | L34: 420 | M34: 410 | N34: 408 | O34: 406 | P34: 404 | Q34: 402 | R34: 400 | S34: 398 | T34: 396 | U34: 394 | V34: 392 | W34: 390 | X34: 389 | Y34: 388 | Z34: 387 | AA34: 386 | AB34: 385 | AC34: 384 | AD34: 383 | AE34: 382 | AF34: 381 | AG34: 380 | AH34: 380 | AI34: 380 | AJ34: 380 | AK34: 380 | AL34: 380 | AM34: 380 | AN34: 380 | AO34: 380 | AP34: 380 | AQ34: 380 | AR34: 380 | AS34: 380 | AT34: 380 | AU34: 380 | AV34: 380 | AW34: 380 | AX34: 380 | AY34: 380 | AZ34: 380 | BA34: 380 | BB34: 380 | BC34: 380 | BD34: 380 | BE34: 380 | BF34: 380 | BG34: 380 | BH34: 380 | BI34: 380 | BJ34: 380 | BK34: 380 | BL34: 380 | BM34: 380 | BN34: 380 | BO34: 380 | BP34: 380 | BQ34: 380 | BR34: 380 | BS34: 380 | BT34: 380 | BU34: 380 | BV34: 380 | BW34: 380 | BX34: 380 | BY34: 380 | BZ34: 380 | CA34: 380
C35: HIGH | J35: 590 | K35: 520 | L35: 480 | M35: 470 | N35: 472 | O35: 474 | P35: 476 | Q35: 478 | R35: 480 | S35: 484 | T35: 488 | U35: 492 | V35: 496 | W35: 500 | X35: 502 | Y35: 504 | Z35: 506 | AA35: 508 | AB35: 510 | AC35: 512 | AD35: 514 | AE35: 516 | AF35: 518 | AG35: 520 | AH35: 520 | AI35: 520 | AJ35: 520 | AK35: 520 | AL35: 520 | AM35: 520 | AN35: 520 | AO35: 520 | AP35: 520 | AQ35: 520 | AR35: 520 | AS35: 520 | AT35: 520 | AU35: 520 | AV35: 520 | AW35: 520 | AX35: 520 | AY35: 520 | AZ35: 520 | BA35: 520 | BB35: 520 | BC35: 520 | BD35: 520 | BE35: 520 | BF35: 520 | BG35: 520 | BH35: 520 | BI35: 520 | BJ35: 520 | BK35: 520 | BL35: 520 | BM35: 520 | BN35: 520 | BO35: 520 | BP35: 520 | BQ35: 520 | BR35: 520 | BS35: 520 | BT35: 520 | BU35: 520 | BV35: 520 | BW35: 520 | BX35: 520 | BY35: 520 | BZ35: 520 | CA35: 520
C36: Selected | J36: =CHOOSE(Dashboard!$C$4,J33,J34,J35) -> 496 | K36: =CHOOSE(Dashboard!$C$4,K33,K34,K35) -> 445 | L36: =CHOOSE(Dashboard!$C$4,L33,L34,L35) -> 420 | M36: =CHOOSE(Dashboard!$C$4,M33,M34,M35) -> 410 | N36: =CHOOSE(Dashboard!$C$4,N33,N34,N35) -> 408 | O36: =CHOOSE(Dashboard!$C$4,O33,O34,O35) -> 406 | P36: =CHOOSE(Dashboard!$C$4,P33,P34,P35) -> 404 | Q36: =CHOOSE(Dashboard!$C$4,Q33,Q34,Q35) -> 402 | ... CA36: =CHOOSE(Dashboard!$C$4,CA33,CA34,CA35) -> 380
C38: Gas price at PL virtual point (real 2026) | D38: PLN/MWh_th | I38: TGE GAS_BASE_Y-27 Aug-2026 214.20; TTF forward proxy 38/33/31 EUR + 4 EUR PL premium | J38: 2027 | K38: 2028 | L38: 2029 | M38: 2030 | N38: 2031 | O38: 2032 | P38: 2033 | Q38: 2034 | R38: 2035 | S38: 2036 | T38: 2037 | U38: 2038 | V38: 2039 | W38: 2040 | X38: 2041 | Y38: 2042 | Z38: 2043 | AA38: 2044 | AB38: 2045 | AC38: 2046 | AD38: 2047 | AE38: 2048 | AF38: 2049 | AG38: 2050 | AH38: 2051 | AI38: 2052 | AJ38: 2053 | AK38: 2054 | AL38: 2055 | AM38: 2056 | AN38: 2057 | AO38: 2058 | AP38: 2059 | AQ38: 2060 | AR38: 2061 | AS38: 2062 | AT38: 2063 | AU38: 2064 | AV38: 2065 | AW38: 2066 | AX38: 2067 | AY38: 2068 | AZ38: 2069 | BA38: 2070 | BB38: 2071 | BC38: 2072 | BD38: 2073 | BE38: 2074 | BF38: 2075 | BG38: 2076 | BH38: 2077 | BI38: 2078 | BJ38: 2079 | BK38: 2080 | BL38: 2081 | BM38: 2082 | BN38: 2083 | BO38: 2084 | BP38: 2085 | BQ38: 2086 | BR38: 2087 | BS38: 2088 | BT38: 2089 | BU38: 2090 | BV38: 2091 | BW38: 2092 | BX38: 2093 | BY38: 2094 | BZ38: 2095 | CA38: 2096
C39: LOW | J39: 180 | K39: 130 | L39: 115 | M39: 110 | N39: 110 | O39: 110 | P39: 110 | Q39: 110 | R39: 110 | S39: 110 | T39: 110 | U39: 110 | V39: 110 | W39: 110 | X39: 110 | Y39: 110 | Z39: 110 | AA39: 110 | AB39: 110 | AC39: 110 | AD39: 110 | AE39: 110 | AF39: 110 | AG39: 110 | AH39: 110 | AI39: 110 | AJ39: 110 | AK39: 110 | AL39: 110 | AM39: 110 | AN39: 110 | AO39: 110 | AP39: 110 | AQ39: 110 | AR39: 110 | AS39: 110 | AT39: 110 | AU39: 110 | AV39: 110 | AW39: 110 | AX39: 110 | AY39: 110 | AZ39: 110 | BA39: 110 | BB39: 110 | BC39: 110 | BD39: 110 | BE39: 110 | BF39: 110 | BG39: 110 | BH39: 110 | BI39: 110 | BJ39: 110 | BK39: 110 | BL39: 110 | BM39: 110 | BN39: 110 | BO39: 110 | BP39: 110 | BQ39: 110 | BR39: 110 | BS39: 110 | BT39: 110 | BU39: 110 | BV39: 110 | BW39: 110 | BX39: 110 | BY39: 110 | BZ39: 110 | CA39: 110
C40: CENTRAL | J40: 214 | K40: 165 | L40: 145 | M40: 135 | N40: 135 | O40: 135 | P40: 135 | Q40: 135 | R40: 135 | S40: 135 | T40: 135 | U40: 135 | V40: 135 | W40: 135 | X40: 135 | Y40: 135 | Z40: 135 | AA40: 135 | AB40: 135 | AC40: 135 | AD40: 135 | AE40: 135 | AF40: 135 | AG40: 135 | AH40: 135 | AI40: 135 | AJ40: 135 | AK40: 135 | AL40: 135 | AM40: 135 | AN40: 135 | AO40: 135 | AP40: 135 | AQ40: 135 | AR40: 135 | AS40: 135 | AT40: 135 | AU40: 135 | AV40: 135 | AW40: 135 | AX40: 135 | AY40: 135 | AZ40: 135 | BA40: 135 | BB40: 135 | BC40: 135 | BD40: 135 | BE40: 135 | BF40: 135 | BG40: 135 | BH40: 135 | BI40: 135 | BJ40: 135 | BK40: 135 | BL40: 135 | BM40: 135 | BN40: 135 | BO40: 135 | BP40: 135 | BQ40: 135 | BR40: 135 | BS40: 135 | BT40: 135 | BU40: 135 | BV40: 135 | BW40: 135 | BX40: 135 | BY40: 135 | BZ40: 135 | CA40: 135
C41: HIGH | J41: 290 | K41: 200 | L41: 185 | M41: 175 | N41: 175 | O41: 175 | P41: 175 | Q41: 175 | R41: 175 | S41: 175 | T41: 175 | U41: 175 | V41: 175 | W41: 175 | X41: 175 | Y41: 175 | Z41: 175 | AA41: 175 | AB41: 175 | AC41: 175 | AD41: 175 | AE41: 175 | AF41: 175 | AG41: 175 | AH41: 175 | AI41: 175 | AJ41: 175 | AK41: 175 | AL41: 175 | AM41: 175 | AN41: 175 | AO41: 175 | AP41: 175 | AQ41: 175 | AR41: 175 | AS41: 175 | AT41: 175 | AU41: 175 | AV41: 175 | AW41: 175 | AX41: 175 | AY41: 175 | AZ41: 175 | BA41: 175 | BB41: 175 | BC41: 175 | BD41: 175 | BE41: 175 | BF41: 175 | BG41: 175 | BH41: 175 | BI41: 175 | BJ41: 175 | BK41: 175 | BL41: 175 | BM41: 175 | BN41: 175 | BO41: 175 | BP41: 175 | BQ41: 175 | BR41: 175 | BS41: 175 | BT41: 175 | BU41: 175 | BV41: 175 | BW41: 175 | BX41: 175 | BY41: 175 | BZ41: 175 | CA41: 175
C42: Selected | J42: =CHOOSE(Dashboard!$C$4,J39,J40,J41) -> 214 | K42: =CHOOSE(Dashboard!$C$4,K39,K40,K41) -> 165 | L42: =CHOOSE(Dashboard!$C$4,L39,L40,L41) -> 145 | M42: =CHOOSE(Dashboard!$C$4,M39,M40,M41) -> 135 | N42: =CHOOSE(Dashboard!$C$4,N39,N40,N41) -> 135 | O42: =CHOOSE(Dashboard!$C$4,O39,O40,O41) -> 135 | P42: =CHOOSE(Dashboard!$C$4,P39,P40,P41) -> 135 | Q42: =CHOOSE(Dashboard!$C$4,Q39,Q40,Q41) -> 135 | ... CA42: =CHOOSE(Dashboard!$C$4,CA39,CA40,CA41) -> 135
C44: EUA price (real 2026) | D44: EUR/t | I44: Spot 86.9 EUR/t (18 Sep 2026); Reuters poll 2027 93; consensus 2030 126 (80–147) | J44: 2027 | K44: 2028 | L44: 2029 | M44: 2030 | N44: 2031 | O44: 2032 | P44: 2033 | Q44: 2034 | R44: 2035 | S44: 2036 | T44: 2037 | U44: 2038 | V44: 2039 | W44: 2040 | X44: 2041 | Y44: 2042 | Z44: 2043 | AA44: 2044 | AB44: 2045 | AC44: 2046 | AD44: 2047 | AE44: 2048 | AF44: 2049 | AG44: 2050 | AH44: 2051 | AI44: 2052 | AJ44: 2053 | AK44: 2054 | AL44: 2055 | AM44: 2056 | AN44: 2057 | AO44: 2058 | AP44: 2059 | AQ44: 2060 | AR44: 2061 | AS44: 2062 | AT44: 2063 | AU44: 2064 | AV44: 2065 | AW44: 2066 | AX44: 2067 | AY44: 2068 | AZ44: 2069 | BA44: 2070 | BB44: 2071 | BC44: 2072 | BD44: 2073 | BE44: 2074 | BF44: 2075 | BG44: 2076 | BH44: 2077 | BI44: 2078 | BJ44: 2079 | BK44: 2080 | BL44: 2081 | BM44: 2082 | BN44: 2083 | BO44: 2084 | BP44: 2085 | BQ44: 2086 | BR44: 2087 | BS44: 2088 | BT44: 2089 | BU44: 2090 | BV44: 2091 | BW44: 2092 | BX44: 2093 | BY44: 2094 | BZ44: 2095 | CA44: 2096
C45: LOW | J45: 70 | K45: 73.333333 | L45: 76.666667 | M45: 80 | N45: 82 | O45: 84 | P45: 86 | Q45: 88 | R45: 90 | S45: 90 | T45: 90 | U45: 90 | V45: 90 | W45: 90 | X45: 90 | Y45: 90 | Z45: 90 | AA45: 90 | AB45: 90 | AC45: 90 | AD45: 90 | AE45: 90 | AF45: 90 | AG45: 90 | AH45: 90 | AI45: 90 | AJ45: 90 | AK45: 90 | AL45: 90 | AM45: 90 | AN45: 90 | AO45: 90 | AP45: 90 | AQ45: 90 | AR45: 90 | AS45: 90 | AT45: 90 | AU45: 90 | AV45: 90 | AW45: 90 | AX45: 90 | AY45: 90 | AZ45: 90 | BA45: 90 | BB45: 90 | BC45: 90 | BD45: 90 | BE45: 90 | BF45: 90 | BG45: 90 | BH45: 90 | BI45: 90 | BJ45: 90 | BK45: 90 | BL45: 90 | BM45: 90 | BN45: 90 | BO45: 90 | BP45: 90 | BQ45: 90 | BR45: 90 | BS45: 90 | BT45: 90 | BU45: 90 | BV45: 90 | BW45: 90 | BX45: 90 | BY45: 90 | BZ45: 90 | CA45: 90
C46: CENTRAL | J46: 90 | K46: 98.333333 | L46: 106.66667 | M46: 115 | N46: 120 | O46: 125 | P46: 130 | Q46: 135 | R46: 140 | S46: 142 | T46: 144 | U46: 146 | V46: 148 | W46: 150 | X46: 150 | Y46: 150 | Z46: 150 | AA46: 150 | AB46: 150 | AC46: 150 | AD46: 150 | AE46: 150 | AF46: 150 | AG46: 150 | AH46: 150 | AI46: 150 | AJ46: 150 | AK46: 150 | AL46: 150 | AM46: 150 | AN46: 150 | AO46: 150 | AP46: 150 | AQ46: 150 | AR46: 150 | AS46: 150 | AT46: 150 | AU46: 150 | AV46: 150 | AW46: 150 | AX46: 150 | AY46: 150 | AZ46: 150 | BA46: 150 | BB46: 150 | BC46: 150 | BD46: 150 | BE46: 150 | BF46: 150 | BG46: 150 | BH46: 150 | BI46: 150 | BJ46: 150 | BK46: 150 | BL46: 150 | BM46: 150 | BN46: 150 | BO46: 150 | BP46: 150 | BQ46: 150 | BR46: 150 | BS46: 150 | BT46: 150 | BU46: 150 | BV46: 150 | BW46: 150 | BX46: 150 | BY46: 150 | BZ46: 150 | CA46: 150
C47: HIGH | J47: 105 | K47: 118.33333 | L47: 131.66667 | M47: 145 | N47: 156 | O47: 167 | P47: 178 | Q47: 189 | R47: 200 | S47: 204 | T47: 208 | U47: 212 | V47: 216 | W47: 220 | X47: 220 | Y47: 220 | Z47: 220 | AA47: 220 | AB47: 220 | AC47: 220 | AD47: 220 | AE47: 220 | AF47: 220 | AG47: 220 | AH47: 220 | AI47: 220 | AJ47: 220 | AK47: 220 | AL47: 220 | AM47: 220 | AN47: 220 | AO47: 220 | AP47: 220 | AQ47: 220 | AR47: 220 | AS47: 220 | AT47: 220 | AU47: 220 | AV47: 220 | AW47: 220 | AX47: 220 | AY47: 220 | AZ47: 220 | BA47: 220 | BB47: 220 | BC47: 220 | BD47: 220 | BE47: 220 | BF47: 220 | BG47: 220 | BH47: 220 | BI47: 220 | BJ47: 220 | BK47: 220 | BL47: 220 | BM47: 220 | BN47: 220 | BO47: 220 | BP47: 220 | BQ47: 220 | BR47: 220 | BS47: 220 | BT47: 220 | BU47: 220 | BV47: 220 | BW47: 220 | BX47: 220 | BY47: 220 | BZ47: 220 | CA47: 220
C48: Selected | J48: =CHOOSE(Dashboard!$C$4,J45,J46,J47) -> 90 | K48: =CHOOSE(Dashboard!$C$4,K45,K46,K47) -> 98.333333 | L48: =CHOOSE(Dashboard!$C$4,L45,L46,L47) -> 106.66667 | M48: =CHOOSE(Dashboard!$C$4,M45,M46,M47) -> 115 | N48: =CHOOSE(Dashboard!$C$4,N45,N46,N47) -> 120 | O48: =CHOOSE(Dashboard!$C$4,O45,O46,O47) -> 125 | P48: =CHOOSE(Dashboard!$C$4,P45,P46,P47) -> 130 | Q48: =CHOOSE(Dashboard!$C$4,Q45,Q46,Q47) -> 135 | ... CA48: =CHOOSE(Dashboard!$C$4,CA45,CA46,CA47) -> 150
B51: 4. SMR — GE Vernova Hitachi BWRX-300 (one 300 MWe unit at a 4-unit site)
C52: Net capacity | D52: MW | E52: 285 | F52: 300 | G52: 300 | H52: =INDEX(E52:G52,1,Dashboard!$C$4) -> 300 | I52: GE 'up to 300 MWe'; IAEA ARIS 270–290 net; closed-loop cooling penalty in low
C53: Overnight cost, all-in (EPC + owner's + contingency + site share), excl. IDC | D53: PLN/kW | E53: 28000 | F53: 38000 | G53: 55000 | H53: =INDEX(E53:G53,1,Dashboard!$C$4) -> 38000 | I53: Darlington unit-1 core excl. common/IDC ≈36,200 PLN/kW (OEB EB-2025-0297); MIT ANP-201 FOAK 14,000 $/kW; INL 2024 SMR 5,500–10,000 $/kW; OSGE ~2 bn EUR/unit; central = mid-fleet unit with 9.5 % learning
C54: Construction duration (first structural concrete → COD) | D54: years | E54: 4 | F54: 5 | G54: 6 | H54: =INDEX(E54:G54,1,Dashboard!$C$4) -> 5 | I54: Darlington ~53–66 months; NREL ATB 2025 43/55/71 months
C55: Commercial operation date | D55: year | E55: 2035 | F55: 2035 | G55: 2035 | H55: =INDEX(E55:G55,1,Dashboard!$C$4) -> 2035 | I55: Stalowa Wola = OSGE site 3/4; fleet first unit Włocławek 2032; transboundary EIA started Jun 2026
C56: Operating life | D56: years | E56: 60 | F56: 60 | G56: 60 | H56: =INDEX(E56:G56,1,Dashboard!$C$4) -> 60 | I56: GE design life 60 y
C57: Pre-development (licensing, EIA, FEED, PAA fees) | D57: m PLN | E57: 300 | F57: 500 | G57: 900 | H57: =INDEX(E57:G57,1,Dashboard!$C$4) -> 500 | I57: OPG 105 m CAD preliminary + 521 m CAD definition phase; PAA fees 6.9 m PLN
C58: First core (capitalised) | D58: m PLN | E58: 450 | F58: 550 | G58: 700 | H58: =INDEX(E58:G58,1,Dashboard!$C$4) -> 550 | I58: 44 tU × ~3,300 USD/kgU (U3O8 96.5 $/lb LT, SWU 183 $, conv 55.5 $, fab 350 $)
C59: Grid connection (unit share) | D59: m PLN | E59: 60 | F59: 125 | G59: 200 | H59: =INDEX(E59:G59,1,Dashboard!$C$4) -> 125 | I59: Proxy 150–400 m PLN for 4-unit site; PSE conditions exist for Stawy Monowskie only
C60: Fixed O&M (staff, insurance, materials, contractors, regulatory) | D60: PLN/kW-yr | E60: 400 | F60: 520 | G60: 820 | H60: =INDEX(E60:G60,1,Dashboard!$C$4) -> 520 | I60: INL 2024 Adv/Mod/Cons 118/136/216 $/kW-yr; EIA AEO2025 124; Lazard 136–158
C61: Single-unit-phase FOM multiplier (first years before units 2–4) | D61: × | E61: 1.3 | F61: 1.5 | G61: 1.8 | H61: =INDEX(E61:G61,1,Dashboard!$C$4) -> 1.5 | I61: INL multi-unit O&M multiplier 0.5–0.7; MIT 38.7 vs 28.2 $/MWh
C62: Years operated as single unit | D62: years | E62: 3 | F62: 3 | G62: 3 | H62: =INDEX(E62:G62,1,Dashboard!$C$4) -> 3 | I62: assumption
C63: Staff | D63: FTE | E63: 120 | F63: 180 | G63: 250 | H63: =INDEX(E63:G63,1,Dashboard!$C$4) -> 180 | I63: GEH claim ~75; NRC-style ~0.3 FTE/MW; PEJ 860 for 3.75 GW
... C80: Tax depreciation split — devices 10 % | D80: % | E80: 0.1 | F80: 0.1 | G80: 0.1 | H80: =INDEX(E80:G80,1,Dashboard!$C$4) -> 0.1 | I80: KŚT group 4/6
B82: 5. Gas — common
C83: Gas plant COD | D83: year | E83: 2031 | F83: 2031 | G83: 2031 | H83: =INDEX(E83:G83,1,Dashboard!$C$4) -> 2031 | I83: Turbine lead times 3–5 y; order 2027 → COD 2031
C84: Property tax rate on budowle | D84: % | E84: 0.02 | F84: 0.02 | G84: 0.02 | H84: =INDEX(E84:G84,1,Dashboard!$C$4) -> 0.02 | I84: 2 % of initial value
C85: Grid connection proxy | D85: PLN/kW | E85: 350 | F85: 350 | G85: 350 | H85: =INDEX(E85:G85,1,Dashboard!$C$4) -> 350 | I85: 400 kV bay/line share 50–150 m PLN per 300 MW
C86: End-of-life demolition provision (share of overnight) | D86: % | E86: 0.05 | F86: 0.05 | G86: 0.05 | H86: =INDEX(E86:G86,1,Dashboard!$C$4) -> 0.05 | I86: assumption
C87: Peak construction workforce per 300 MW | D87: FTE | E87: 300 | F87: 300 | G87: 300 | H87: =INDEX(E87:G87,1,Dashboard!$C$4) -> 300 | I87: assumption
B89: 6. Gas — CCGT 1+1 F-class, ~300 MW
C90: Net capacity (portfolio) | D90: MW | E90: 300 | F90: 300 | G90: 300 | H90: =INDEX(E90:G90,1,Dashboard!$C$4) -> 300
C91: All-in capex (EPC + owner's costs) | D91: PLN/kW | E91: 4800 | F91: 6200 | G91: 8500 | H91: =INDEX(E91:G91,1,Dashboard!$C$4) -> 6200 | I91: Polish 2025 EPC 4,800–5,500 PLN/kW for 560–1,340 MW (Kozienice, Gdańsk, Grudziądz II) +15–20 % scale penalty; Lazard-high/GridLab $2,000–2,600/kW
C92: Construction duration | D92: years | E92: 3 | F92: 4 | G92: 5 | H92: =INDEX(E92:G92,1,Dashboard!$C$4) -> 4 | I92: DESNZ 2.2/3.0/3.2; Polish reality 4–5 y
C93: Operating life | D93: years | E93: 30 | F93: 30 | G93: 30 | H93: =INDEX(E93:G93,1,Dashboard!$C$4) -> 30 | I93: DESNZ 20/25/30; Lazard 30
C94: Net efficiency at full load (LHV) | D94: % | E94: 0.55 | F94: 0.57 | G94: 0.6 | H94: =INDEX(E94:G94,1,Dashboard!$C$4) -> 0.57 | I94: 300 MW-class scale penalty vs 63–64 % H-class; Grudziądz >61 %; EC Stalowa Wola 57.4–60 %
C95: Fixed O&M incl. LTSA fixed fee | D95: PLN/kW-yr | E95: 70 | F95: 100 | G95: 130 | H95: =INDEX(E95:G95,1,Dashboard!$C$4) -> 100 | I95: EIA/Lazard/DESNZ; Dolna Odra LTSA ≈61 PLN/kW-yr
C96: Variable O&M incl. hours-based LTSA | D96: PLN/MWh | E96: 12 | F96: 16 | G96: 22 | H96: =INDEX(E96:G96,1,Dashboard!$C$4) -> 16 | I96: Lazard 2.75–5 $/MWh; DESNZ £4.44
C97: Gas transmission exit-capacity booking (Gaz-System) | D97: PLN/kW-yr | E97: 58 | F97: 58 | G97: 58 | H97: =INDEX(E97:G97,1,Dashboard!$C$4) -> 58 | I97: Tariff 19 exit ≈0.381 gr/(kWh/h)/h annual firm; peakers book monthly/daily products
C98: Staff | D98: FTE | E98: 45 | F98: 60 | G98: 80 | H98: =INDEX(E98:G98,1,Dashboard!$C$4) -> 60 | I98: EC Stalowa Wola ~60 FTE for 450 MW CHP
C99: Loaded cost per FTE | D99: k PLN/yr | E99: 150 | F99: 200 | G99: 260 | H99: =INDEX(E99:G99,1,Dashboard!$C$4) -> 200 | I99: GUS energy sector
C100: Share of capex taxable as budowle | D100: % | E100: 0.15 | F100: 0.15 | G100: 0.15 | H100: =INDEX(E100:G100,1,Dashboard!$C$4) -> 0.15 | I100: structures, foundations, stacks, pipelines
C101: Tax depreciation split — buildings 2.5 % | D101: % | E101: 0.15 | F101: 0.15 | G101: 0.15 | H101: =INDEX(E101:G101,1,Dashboard!$C$4) -> 0.15
C102: Tax depreciation split — structures 4.5 % | D102: % | E102: 0.1 | F102: 0.1 | G102: 0.1 | H102: =INDEX(E102:G102,1,Dashboard!$C$4) -> 0.1
C103: Tax depreciation split — turbines/boilers 7 % | D103: % | E103: 0.6 | F103: 0.6 | G103: 0.6 | H103: =INDEX(E103:G103,1,Dashboard!$C$4) -> 0.6 | I103: KŚT group 3 (engines 14 % — conservatively 7 %)
C104: Tax depreciation split — devices 10 % | D104: % | E104: 0.15 | F104: 0.15 | G104: 0.15 | H104: =INDEX(E104:G104,1,Dashboard!$C$4) -> 0.15
B106: 7. Gas — OCGT frame peakers, 2 × 150 MW
C107: Net capacity (portfolio) | D107: MW | E107: 300 | F107: 300 | G107: 300 | H107: =INDEX(E107:G107,1,Dashboard!$C$4) -> 300
C108: All-in capex (EPC + owner's costs) | D108: PLN/kW | E108: 2000 | F108: 3400 | G108: 5800 | H108: =INDEX(E108:G108,1,Dashboard!$C$4) -> 3400 | I108: DESNZ 2025 £361/kW; EIA $791/kW; PGE HL-class OCGT ~5,900 PLN/kW incl. 12-y LTSA
C109: Construction duration | D109: years | E109: 2 | F109: 2 | G109: 3 | H109: =INDEX(E109:G109,1,Dashboard!$C$4) -> 2 | I109: DESNZ 2.2/3.0/3.2; Polish reality 4–5 y
C110: Operating life | D110: years | E110: 30 | F110: 30 | G110: 30 | H110: =INDEX(E110:G110,1,Dashboard!$C$4) -> 30 | I110: DESNZ 20/25/30; Lazard 30
C111: Net efficiency at full load (LHV) | D111: % | E111: 0.36 | F111: 0.39 | G111: 0.43 | H111: =INDEX(E111:G111,1,Dashboard!$C$4) -> 0.39 | I111: DESNZ 38.9 %; EIA 41.3 %; GE 9HA SC 44 %
C112: Fixed O&M incl. LTSA fixed fee | D112: PLN/kW-yr | E112: 30 | F112: 55 | G112: 85 | H112: =INDEX(E112:G112,1,Dashboard!$C$4) -> 55 | I112: EIA/Lazard/DESNZ; Dolna Odra LTSA ≈61 PLN/kW-yr
C113: Variable O&M incl. hours-based LTSA | D113: PLN/MWh | E113: 15 | F113: 20 | G113: 30 | H113: =INDEX(E113:G113,1,Dashboard!$C$4) -> 20 | I113: Lazard 2.75–5 $/MWh; DESNZ £4.44
C114: Gas transmission exit-capacity booking (Gaz-System) | D114: PLN/kW-yr | E114: 35 | F114: 35 | G114: 35 | H114: =INDEX(E114:G114,1,Dashboard!$C$4) -> 35 | I114: Tariff 19 exit ≈0.381 gr/(kWh/h)/h annual firm; peakers book monthly/daily products
C115: Staff | D115: FTE | E115: 10 | F115: 15 | G115: 20 | H115: =INDEX(E115:G115,1,Dashboard!$C$4) -> 15 | I115: EC Stalowa Wola ~60 FTE for 450 MW CHP | J115: 20
C116: Loaded cost per FTE | D116: k PLN/yr | E116: 150 | F116: 200 | G116: 260 | H116: =INDEX(E116:G116,1,Dashboard!$C$4) -> 200 | I116: GUS energy sector
C117: Share of capex taxable as budowle | D117: % | E117: 0.12 | F117: 0.12 | G117: 0.12 | H117: =INDEX(E117:G117,1,Dashboard!$C$4) -> 0.12 | I117: structures, foundations, stacks, pipelines
C118: Tax depreciation split — buildings 2.5 % | D118: % | E118: 0.1 | F118: 0.1 | G118: 0.1 | H118: =INDEX(E118:G118,1,Dashboard!$C$4) -> 0.1
C119: Tax depreciation split — structures 4.5 % | D119: % | E119: 0.1 | F119: 0.1 | G119: 0.1 | H119: =INDEX(E119:G119,1,Dashboard!$C$4) -> 0.1
C120: Tax depreciation split — turbines/boilers 7 % | D120: % | E120: 0.65 | F120: 0.65 | G120: 0.65 | H120: =INDEX(E120:G120,1,Dashboard!$C$4) -> 0.65 | I120: KŚT group 3 (engines 14 % — conservatively 7 %)
C121: Tax depreciation split — devices 10 % | D121: % | E121: 0.15 | F121: 0.15 | G121: 0.15 | H121: =INDEX(E121:G121,1,Dashboard!$C$4) -> 0.15
B123: 8. Gas — Gas engines, 4 blocks × 76.5 MW (≈17 × 18 MW)
C124: Net capacity (portfolio) | D124: MW | E124: 72 | F124: 72 | G124: 72 | H124: =INDEX(E124:G124,1,Dashboard!$C$4) -> 72
C125: All-in capex (EPC + owner's costs) | D125: PLN/kW | E125: 2700 | F125: 3800 | G125: 5000 | H125: =INDEX(E125:G125,1,Dashboard!$C$4) -> 3800 | I125: DESNZ £529/kW; PGE Kraków/Gdynia CHP engines 7,600–8,900 PLN/kWe (upper bound)
C126: Construction duration | D126: years | E126: 1 | F126: 2 | G126: 2 | H126: =INDEX(E126:G126,1,Dashboard!$C$4) -> 2 | I126: DESNZ 2.2/3.0/3.2; Polish reality 4–5 y
C127: Operating life | D127: years | E127: 25 | F127: 25 | G127: 25 | H127: =INDEX(E127:G127,1,Dashboard!$C$4) -> 25 | I127: DESNZ 20/25/30; Lazard 30
C128: Net efficiency at full load (LHV) | D128: % | E128: 0.45 | F128: 0.48 | G128: 0.5 | H128: =INDEX(E128:G128,1,Dashboard!$C$4) -> 0.48 | I128: Wärtsilä 50DF 49.4 %, 31SG >50 %; DESNZ 44.6 %
C129: Fixed O&M incl. LTSA fixed fee | D129: PLN/kW-yr | E129: 55 | F129: 75 | G129: 95 | H129: =INDEX(E129:G129,1,Dashboard!$C$4) -> 75 | I129: EIA/Lazard/DESNZ; Dolna Odra LTSA ≈61 PLN/kW-yr
C130: Variable O&M incl. hours-based LTSA | D130: PLN/MWh | E130: 25 | F130: 32 | G130: 40 | H130: =INDEX(E130:G130,1,Dashboard!$C$4) -> 32 | I130: Lazard 2.75–5 $/MWh; DESNZ £4.44
...

Sheet Twin
B1: Twin — outputs of the hourly digital-twin dispatch (Python: smrtwin), per operating year k
B2: cf = capacity factor; capture = generation-weighted price ÷ annual mean price; cfd_ref = generation-weighted CfD reference (daily TGeBase) ÷ annual mean; heat = MWh_th per MWh_e incl. no-load & start fuel; start = start costs (wear) PLN/MWh_e; fuel_ratio = SMR fuel cost ÷ (energy × fuel price). Re-generate with `python build_excel.py` after `python run_all.py`.
C4: operating year k → | G4: 1 | H4: 2 | I4: 3 | J4: 4 | K4: 5 | L4: 6 | M4: 7 | N4: 8 | O4: 9 | P4: 10 | Q4: 11 | R4: 12 | S4: 13 | T4: 14 | U4: 15 | V4: 16 | W4: 17 | X4: 18 | Y4: 19 | Z4: 20 | AA4: 21 | AB4: 22 | AC4: 23 | AD4: 24 | AE4: 25 | AF4: 26 | AG4: 27 | AH4: 28 | AI4: 29 | AJ4: 30 | AK4: 31 | AL4: 32 | AM4: 33 | AN4: 34 | AO4: 35 | AP4: 36 | AQ4: 37 | AR4: 38 | AS4: 39 | AT4: 40 | AU4: 41 | AV4: 42 | AW4: 43 | AX4: 44 | AY4: 45 | AZ4: 46 | BA4: 47 | BB4: 48 | BC4: 49 | BD4: 50 | BE4: 51 | BF4: 52 | BG4: 53 | BH4: 54 | BI4: 55 | BJ4: 56 | BK4: 57 | BL4: 58 | BM4: 59 | BN4: 60
B5: SMR · CfD (two-way, PEJ template)
B6: cf · low | G6: 0.94933505 | H6: 0.91810217 | I6: 0.91810217 | J6: 0.97931279 | K6: 0.94709361 | L6: 0.94709361 | M6: 0.97931279 | N6: 0.94709361 | O6: 0.94709361 | P6: 0.9121895 | Q6: 0.94709361 | R6: 0.94709361 | S6: 0.97931279 | T6: 0.94709361 | U6: 0.94709361 | V6: 0.97931279 | W6: 0.94709361 | X6: 0.94709361 | Y6: 0.97931279 | Z6: 0.89876484 | AA6: 0.94709361 | AB6: 0.97931279 | AC6: 0.94709361 | AD6: 0.94709361 | AE6: 0.97931279 | AF6: 0.94709361 | AG6: 0.94709361 | AH6: 0.97931279 | AI6: 0.94709361 | AJ6: 0.89876484 | AK6: 0.97931279 | AL6: 0.94709361 | AM6: 0.94709361 | AN6: 0.97931279 | AO6: 0.94709361 | AP6: 0.94709361 | AQ6: 0.97931279 | AR6: 0.94706164 | AS6: 0.94706164 | AT6: 0.91215753 | AU6: 0.91140639 | AV6: 0.9113984 | AW6: 0.94352169 | AX6: 0.91130251 | AY6: 0.91119863 | AZ6: 0.94341781 | BA6: 0.91110274 | BB6: 0.91107078 | BC6: 0.94326598 | BD6: 0.86268607 | BE6: 0.91093493 | BF6: 0.94315411 | BG6: 0.91088699 | BH6: 0.910871 | BI6: 0.94309018 | BJ6: 0.91084703 | BK6: 0.91078311 | BL6: 0.94300228 | BM6: 0.91074315 | BN6: 0.86238242
B7: cf · central | G7: 0.92592856 | H7: 0.88778905 | I7: 0.88778905 | J7: 0.95559225 | K7: 0.91623184 | L7: 0.91624706 | M7: 0.95563172 | N7: 0.91623184 | O7: 0.91625609 | P7: 0.88999965 | Q7: 0.91628034 | R7: 0.91628034 | S7: 0.95564074 | T7: 0.91629556 | U7: 0.91635026 | V7: 0.95570447 | W7: 0.91626511 | X7: 0.91626511 | Y7: 0.95562552 | Z7: 0.8768562 | AA7: 0.91626511 | AB7: 0.95561029 | AC7: 0.91622563 | AD7: 0.91620139 | AE7: 0.95558604 | AF7: 0.91620139 | AG7: 0.91620139 | AH7: 0.95558604 | AI7: 0.91620139 | AJ7: 0.87681673 | AK7: 0.95558604 | AL7: 0.91620139 | AM7: 0.91620139 | AN7: 0.95558604 | AO7: 0.91620139 | AP7: 0.91620139 | AQ7: 0.95558604 | AR7: 0.91620139 | AS7: 0.91620139 | AT7: 0.88994495 | AU7: 0.88226201 | AV7: 0.88226201 | AW7: 0.92164666 | AX7: 0.88226201 | AY7: 0.88226201 | AZ7: 0.92164666 | BA7: 0.88226201 | BB7: 0.88226201 | BC7: 0.92164666 | BD7: 0.84287735 | BE7: 0.88226201 | BF7: 0.92164666 | BG7: 0.88226201 | BH7: 0.88226201 | BI7: 0.92164666 | BJ7: 0.88226201 | BK7: 0.88226201 | BL7: 0.92164666 | BM7: 0.88226201 | BN7: 0.84287735
B8: cf · high | G8: 0.89770461 | H8: 0.84808148 | I8: 0.84783872 | J8: 0.92633493 | K8: 0.875173 | L8: 0.87489612 | M8: 0.92573642 | N8: 0.87452414 | O8: 0.87425006 | P8: 0.86139315 | Q8: 0.87362917 | R8: 0.87332991 | S8: 0.92418139 | T8: 0.8730726 | U8: 0.87299429 | V8: 0.92392968 | W8: 0.87291598 | X8: 0.87291598 | Y8: 0.92392968 | Z8: 0.84740913 | AA8: 0.87291598 | AB8: 0.92392968 | AC8: 0.87291598 | AD8: 0.87291598 | AE8: 0.92392968 | AF8: 0.87291598 | AG8: 0.87291598 | AH8: 0.92392968 | AI8: 0.87291598 | AJ8: 0.84740913 | AK8: 0.92392968 | AL8: 0.87291598 | AM8: 0.87291598 | AN8: 0.92392968 | AO8: 0.87291598 | AP8: 0.87291598 | AQ8: 0.92392968 | AR8: 0.87291598 | AS8: 0.87291598 | AT8: 0.86016256 | AU8: 0.84580097 | AV8: 0.84580097 | AW8: 0.89681467 | AX8: 0.84580097 | AY8: 0.84580097 | AZ8: 0.89681467 | BA8: 0.84580097 | BB8: 0.84580097 | BC8: 0.89681467 | BD8: 0.82029412 | BE8: 0.84580097 | BF8: 0.89681467 | BG8: 0.84580097 | BH8: 0.84580097 | BI8: 0.89681467 | BJ8: 0.84580097 | BK8: 0.84580097 | BL8: 0.89681467 | BM8: 0.84580097 | BN8: 0.82029412
B9: cf · selected | G9: =CHOOSE(Dashboard!$C$4,G6,G7,G8) -> 0.92592856 | H9: =CHOOSE(Dashboard!$C$4,H6,H7,H8) -> 0.88778905 | I9: =CHOOSE(Dashboard!$C$4,I6,I7,I8) -> 0.88778905 | J9: =CHOOSE(Dashboard!$C$4,J6,J7,J8) -> 0.95559225 | K9: =CHOOSE(Dashboard!$C$4,K6,K7,K8) -> 0.91623184 | L9: =CHOOSE(Dashboard!$C$4,L6,L7,L8) -> 0.91624706 | M9: =CHOOSE(Dashboard!$C$4,M6,M7,M8) -> 0.95563172 | N9: =CHOOSE(Dashboard!$C$4,N6,N7,N8) -> 0.91623184 | ... BN9: =CHOOSE(Dashboard!$C$4,BN6,BN7,BN8) -> 0.84287735
B10: capture · low | G10: 1.0024088 | H10: 0.99699465 | I10: 0.99698633 | J10: 1.0024283 | K10: 0.99697014 | L10: 0.99696182 | M10: 1.0024472 | N10: 0.99694518 | O10: 0.99693686 | P10: 0.9970233 | Q10: 0.99692021 | R10: 0.99691189 | S10: 1.0024852 | T10: 0.99689525 | U10: 0.99688692 | V10: 1.0025042 | W10: 0.99687028 | X10: 0.99686196 | Y10: 1.0025232 | Z10: 0.99886423 | AA10: 0.99683699 | AB10: 1.0025422 | AC10: 0.99682035 | AD10: 0.99681203 | AE10: 1.0025612 | AF10: 0.99679538 | AG10: 0.99678706 | AH10: 1.0025802 | AI10: 0.99677042 | AJ10: 0.99850523 | AK10: 1.0025992 | AL10: 0.99674545 | AM10: 0.99673713 | AN10: 1.0026181 | AO10: 0.99672049 | AP10: 0.99671217 | AQ10: 1.0026371 | AR10: 0.99678527 | AS10: 0.99677713 | AT10: 0.9962905 | AU10: 1.0369517 | AV10: 1.0369582 | AW10: 1.0419184 | AX10: 1.0370473 | AY10: 1.037145 | AZ10: 1.0420564 | BA10: 1.0372343 | BB10: 1.0372639 | BC10: 1.042239 | BD10: 1.0408382 | BE10: 1.0373909 | BF10: 1.0423851 | BG10: 1.0374353 | BH10: 1.0374499 | BI10: 1.0424873 | BJ10: 1.0374717 | BK10: 1.037532 | BL10: 1.042612 | BM10: 1.0375692 | BN10: 1.0408562
B11: capture · central | G11: 1.004328 | H11: 0.99915641 | I11: 0.99913388 | J11: 1.0043053 | K11: 0.999041 | L11: 0.99899338 | M11: 1.0043079 | N11: 0.99897341 | O11: 0.99893284 | P11: 0.99842585 | Q11: 0.99888776 | R11: 0.99886518 | S11: 1.0044656 | T11: 0.99887961 | U11: 0.9987474 | V11: 1.0044792 | W11: 0.99887485 | X11: 0.99890302 | Y11: 1.0046999 | Z11: 1.0000376 | AA11: 0.99887169 | AB11: 1.0048173 | AC11: 0.9988998 | AD11: 0.99893464 | AE11: 1.0049212 | AF11: 0.99889208 | AG11: 0.9988708 | AH11: 1.0049546 | AI11: 0.9988708 | AJ11: 0.99969665 | AK11: 1.0049546 | AL11: 0.9988708 | AM11: 0.9988708 | AN11: 1.0049546 | AO11: 0.9988708 | AP11: 0.9988708 | AQ11: 1.0049546 | AR11: 0.9988708 | AS11: 0.9988708 | AT11: 0.9978925 | AU11: 1.0385695 | AV11: 1.0385695 | AW11: 1.043181 | AX11: 1.0385695 | AY11: 1.0385695 | AZ11: 1.043181 | BA11: 1.0385695 | BB11: 1.0385695 | BC11: 1.043181 | BD11: 1.0412836 | BE11: 1.0385695 | BF11: 1.043181 | BG11: 1.0385695 | BH11: 1.0385695 | BI11: 1.043181 | BJ11: 1.0385695 | BK11: 1.0385695 | BL11: 1.043181 | BM11: 1.0385695 | BN11: 1.0412836
B12: capture · high | G12: 1.0058105 | H12: 1.0002075 | I12: 1.0004661 | J12: 1.0067031 | K12: 1.0007996 | L12: 1.0010516 | M12: 1.0074073 | N12: 1.0013918 | O12: 1.0016354 | P12: 1.001818 | Q12: 1.0021608 | R12: 1.0024804 | S12: 1.0092088 | T12: 1.0026763 | U12: 1.0026872 | V12: 1.0095124 | W12: 1.0027429 | X12: 1.0027429 | Y12: 1.0095124 | Z12: 1.0046388 | AA12: 1.0027429 | AB12: 1.0095124 | AC12: 1.0027429 | AD12: 1.0027429 | AE12: 1.0095124 | AF12: 1.0027429 | AG12: 1.0027429 | AH12: 1.0095124 | AI12: 1.0027429 | AJ12: 1.0046388 | AK12: 1.0095124 | AL12: 1.0027429 | AM12: 1.0027429 | AN12: 1.0095124 | AO12: 1.0027429 | AP12: 1.0027429 | AQ12: 1.0095124 | AR12: 1.0027429 | AS12: 1.0027429 | AT12: 1.0027522 | AU12: 1.0366849 | AV12: 1.0366849 | AW12: 1.0417284 | AX12: 1.0366849 | AY12: 1.0366849 | AZ12: 1.0417284 | BA12: 1.0366849 | BB12: 1.0366849 | BC12: 1.0417284 | BD12: 1.0396989 | BE12: 1.0366849 | BF12: 1.0417284 | BG12: 1.0366849 | BH12: 1.0366849 | BI12: 1.0417284 | BJ12: 1.0366849 | BK12: 1.0366849 | BL12: 1.0417284 | BM12: 1.0366849 | BN12: 1.0396989
B13: capture · selected | G13: =CHOOSE(Dashboard!$C$4,G10,G11,G12) -> 1.004328 | H13: =CHOOSE(Dashboard!$C$4,H10,H11,H12) -> 0.99915641 | I13: =CHOOSE(Dashboard!$C$4,I10,I11,I12) -> 0.99913388 | J13: =CHOOSE(Dashboard!$C$4,J10,J11,J12) -> 1.0043053 | K13: =CHOOSE(Dashboard!$C$4,K10,K11,K12) -> 0.999041 | L13: =CHOOSE(Dashboard!$C$4,L10,L11,L12) -> 0.99899338 | M13: =CHOOSE(Dashboard!$C$4,M10,M11,M12) -> 1.0043079 | N13: =CHOOSE(Dashboard!$C$4,N10,N11,N12) -> 0.99897341 | ... BN13: =CHOOSE(Dashboard!$C$4,BN10,BN11,BN12) -> 1.0412836
B14: cfd_ref · low | G14: 1.0006452 | H14: 0.99516523 | I14: 0.99515113 | J14: 1.0006492 | K14: 0.99512474 | L14: 0.99511064 | M14: 1.0006514 | N14: 0.99508245 | O14: 0.99506835 | P14: 0.99507729 | Q14: 0.99504015 | R14: 0.99502605 | S14: 1.0006558 | T14: 0.99499785 | U14: 0.99498375 | V14: 1.0006581 | W14: 0.99495555 | X14: 0.99494145 | Y14: 1.0006603 | Z14: 0.99682827 | AA14: 0.99489916 | AB14: 1.0006625 | AC14: 0.99487096 | AD14: 0.99485686 | AE14: 1.0006647 | AF14: 0.99482866 | AG14: 0.99481456 | AH14: 1.000667 | AI14: 0.99478636 | AJ14: 0.9964084 | AK14: 1.0006692 | AL14: 0.99474407 | AM14: 0.99472997 | AN14: 1.0006714 | AO14: 0.99470177 | AP14: 0.99468767 | AQ14: 1.0006737 | AR14: 0.99469445 | AS14: 0.99468037 | AT14: 0.99410733 | AU14: 1 | AV14: 1 | AW14: 1 | AX14: 1 | AY14: 1 | AZ14: 1 | BA14: 1 | BB14: 1 | BC14: 1 | BD14: 1 | BE14: 1 | BF14: 1 | BG14: 1 | BH14: 1 | BI14: 1 | BJ14: 1 | BK14: 1 | BL14: 1 | BM14: 1 | BN14: 1
B15: cfd_ref · central | G15: 0.99940571 | H15: 0.99404549 | I15: 0.99400945 | J15: 0.99949249 | K15: 0.99404005 | L15: 0.99399973 | M15: 0.9995071 | N15: 0.99393184 | O15: 0.99391051 | P15: 0.99324149 | Q15: 0.99387142 | R15: 0.9938353 | S15: 0.99959832 | T15: 0.99384431 | U15: 0.99377337 | V15: 0.99965641 | W15: 0.99375544 | X15: 0.99376941 | Y15: 0.99973209 | Z15: 0.99460852 | AA15: 0.99369497 | AB15: 0.99978789 | AC15: 0.99363961 | AD15: 0.99362639 | AE15: 0.99981758 | AF15: 0.99355428 | AG15: 0.99351823 | AH15: 0.99982268 | AI15: 0.99351823 | AJ15: 0.99410365 | AK15: 0.99982268 | AL15: 0.99351823 | AM15: 0.99351823 | AN15: 0.99982268 | AO15: 0.99351823 | AP15: 0.99351823 | AQ15: 0.99982268 | AR15: 0.99351823 | AS15: 0.99351823 | AT15: 0.99238201 | AU15: 1 | AV15: 1 | AW15: 1 | AX15: 1 | AY15: 1 | AZ15: 1 | BA15: 1 | BB15: 1 | BC15: 1 | BD15: 1 | BE15: 1 | BF15: 1 | BG15: 1 | BH15: 1 | BI15: 1 | BJ15: 1 | BK15: 1 | BL15: 1 | BM15: 1 | BN15: 1
B16: cfd_ref · high | G16: 0.99934274 | H16: 0.99306444 | I16: 0.9929917 | J16: 0.999442 | K16: 0.99291006 | L16: 0.99281041 | M16: 0.99940405 | N16: 0.99265976 | O16: 0.99255769 | P16: 0.99245309 | Q16: 0.99230311 | R16: 0.99223957 | S16: 0.99932962 | T16: 0.99208177 | U16: 0.99197303 | V16: 0.99929603 | W16: 0.99192947 | X16: 0.99192947 | Y16: 0.99929603 | Z16: 0.99349992 | AA16: 0.99192947 | AB16: 0.99929603 | AC16: 0.99192947 | AD16: 0.99192947 | AE16: 0.99929603 | AF16: 0.99192947 | AG16: 0.99192947 | AH16: 0.99929603 | AI16: 0.99192947 | AJ16: 0.99349992 | AK16: 0.99929603 | AL16: 0.99192947 | AM16: 0.99192947 | AN16: 0.99929603 | AO16: 0.99192947 | AP16: 0.99192947 | AQ16: 0.99929603 | AR16: 0.99192947 | AS16: 0.99192947 | AT16: 0.99177847 | AU16: 1 | AV16: 1 | AW16: 1 | AX16: 1 | AY16: 1 | AZ16: 1 | BA16: 1 | BB16: 1 | BC16: 1 | BD16: 1 | BE16: 1 | BF16: 1 | BG16: 1 | BH16: 1 | BI16: 1 | BJ16: 1 | BK16: 1 | BL16: 1 | BM16: 1 | BN16: 1
B17: cfd_ref · selected | G17: =CHOOSE(Dashboard!$C$4,G14,G15,G16) -> 0.99940571 | H17: =CHOOSE(Dashboard!$C$4,H14,H15,H16) -> 0.99404549 | I17: =CHOOSE(Dashboard!$C$4,I14,I15,I16) -> 0.99400945 | J17: =CHOOSE(Dashboard!$C$4,J14,J15,J16) -> 0.99949249 | K17: =CHOOSE(Dashboard!$C$4,K14,K15,K16) -> 0.99404005 | L17: =CHOOSE(Dashboard!$C$4,L14,L15,L16) -> 0.99399973 | M17: =CHOOSE(Dashboard!$C$4,M14,M15,M16) -> 0.9995071 | N17: =CHOOSE(Dashboard!$C$4,N14,N15,N16) -> 0.99393184 | ... BN17: =CHOOSE(Dashboard!$C$4,BN14,BN15,BN16) -> 1
B18: fuel_ratio · low | G18: 1.0000381 | H18: 1.0000393 | I18: 1.0000393 | J18: 1.0000383 | K18: 1.0000397 | L18: 1.0000397 | M18: 1.0000383 | N18: 1.0000397 | O18: 1.0000397 | P18: 1.0000412 | Q18: 1.0000397 | R18: 1.0000397 | S18: 1.0000383 | T18: 1.0000397 | U18: 1.0000397 | V18: 1.0000383 | W18: 1.0000397 | X18: 1.0000397 | Y18: 1.0000383 | Z18: 1.0000418 | AA18: 1.0000397 | AB18: 1.0000383 | AC18: 1.0000397 | AD18: 1.0000397 | AE18: 1.0000383 | AF18: 1.0000397 | AG18: 1.0000397 | AH18: 1.0000383 | AI18: 1.0000397 | AJ18: 1.0000418 | AK18: 1.0000383 | AL18: 1.0000397 | AM18: 1.0000397 | AN18: 1.0000383 | AO18: 1.0000397 | AP18: 1.0000397 | AQ18: 1.0000383 | AR18: 1.0000413 | AS18: 1.0000413 | AT18: 1.0000428 | AU18: 1.0020515 | AV18: 1.0020519 | AW18: 1.0019875 | AX18: 1.0020578 | AY18: 1.002064 | AZ18: 1.0019935 | BA18: 1.0020698 | BB18: 1.0020716 | BC18: 1.0020021 | BD18: 1.0021909 | BE18: 1.0020802 | BF18: 1.0020091 | BG18: 1.0020828 | BH18: 1.0020843 | BI18: 1.0020131 | BJ18: 1.0020856 | BK18: 1.0020897 | BL18: 1.0020183 | BM18: 1.0020924 | BN18: 1.0022116
B19: fuel_ratio · central | G19: 1.0001515 | H19: 1.0001566 | I19: 1.0001566 | J19: 1.000147 | K19: 1.0001521 | L19: 1.0001518 | M19: 1.0001456 | N19: 1.0001521 | O19: 1.0001508 | P19: 1.0001553 | Q19: 1.0001496 | R19: 1.0001496 | S19: 1.0001446 | T19: 1.0001484 | U19: 1.0001456 | V19: 1.0001411 | W19: 1.0001499 | X19: 1.0001499 | Y19: 1.0001449 | Z19: 1.0001579 | AA19: 1.0001499 | AB19: 1.0001461 | AC19: 1.0001524 | AD19: 1.0001536 | AE19: 1.0001472 | AF19: 1.0001536 | AG19: 1.0001536 | AH19: 1.0001472 | AI19: 1.0001536 | AJ19: 1.0001605 | AK19: 1.0001472 | AL19: 1.0001536 | AM19: 1.0001536 | AN19: 1.0001472 | AO19: 1.0001536 | AP19: 1.0001536 | AQ19: 1.0001472 | AR19: 1.0001536 | AS19: 1.0001536 | AT19: 1.0001581 | AU19: 1.0020252 | AV19: 1.0020252 | AW19: 1.0019386 | AX19: 1.0020252 | AY19: 1.0020252 | AZ19: 1.0019386 | BA19: 1.0020252 | BB19: 1.0020252 | BC19: 1.0019386 | BD19: 1.0021198 | BE19: 1.0020252 | BF19: 1.0019386 | BG19: 1.0020252 | BH19: 1.0020252 | BI19: 1.0019386 | BJ19: 1.0020252 | BK19: 1.0020252 | BL19: 1.0019386 | BM19: 1.0020252 | BN19: 1.0021198
B20: fuel_ratio · high | G20: 1.0002178 | H20: 1.0002447 | I20: 1.0002564 | J20: 1.0002527 | K20: 1.0002767 | L20: 1.0002937 | M20: 1.0002846 | N20: 1.0003131 | O20: 1.000329 | P20: 1.0003405 | Q20: 1.0003671 | R20: 1.0003864 | S20: 1.0003721 | T20: 1.0003994 | U20: 1.0004035 | V20: 1.0003851 | W20: 1.0004076 | X20: 1.0004076 | Y20: 1.0003851 | Z20: 1.0004199 | AA20: 1.0004076 | AB20: 1.0003851 | AC20: 1.0004076 | AD20: 1.0004076 | AE20: 1.0003851 | AF20: 1.0004076 | AG20: 1.0004076 | AH20: 1.0003851 | AI20: 1.0004076 | AJ20: 1.0004199 | AK20: 1.0003851 | AL20: 1.0004076 | AM20: 1.0004076 | AN20: 1.0003851 | AO20: 1.0004076 | AP20: 1.0004076 | AQ20: 1.0003851 | AR20: 1.0004076 | AS20: 1.0004076 | AT20: 1.0004137 | AU20: 1.0019555 | AV20: 1.0019555 | AW20: 1.0018443 | AX20: 1.0019555 | AY20: 1.0019555 | AZ20: 1.0018443 | BA20: 1.0019555 | BB20: 1.0019555 | BC20: 1.0018443 | BD20: 1.0020163 | BE20: 1.0019555 | BF20: 1.0018443 | BG20: 1.0019555 | BH20: 1.0019555 | BI20: 1.0018443 | BJ20: 1.0019555 | BK20: 1.0019555 | BL20: 1.0018443 | BM20: 1.0019555 | BN20: 1.0020163
B21: fuel_ratio · selected | G21: =CHOOSE(Dashboard!$C$4,G18,G19,G20) -> 1.0001515 | H21: =CHOOSE(Dashboard!$C$4,H18,H19,H20) -> 1.0001566 | I21: =CHOOSE(Dashboard!$C$4,I18,I19,I20) -> 1.0001566 | J21: =CHOOSE(Dashboard!$C$4,J18,J19,J20) -> 1.000147 | K21: =CHOOSE(Dashboard!$C$4,K18,K19,K20) -> 1.0001521 | L21: =CHOOSE(Dashboard!$C$4,L18,L19,L20) -> 1.0001518 | M21: =CHOOSE(Dashboard!$C$4,M18,M19,M20) -> 1.0001456 | N21: =CHOOSE(Dashboard!$C$4,N18,N19,N20) -> 1.0001521 | ... BN21: =CHOOSE(Dashboard!$C$4,BN18,BN19,BN20) -> 1.0021198
B23: SMR · fixed price = last-12-month average spot
B24: cf · low | G24: 0.95 | H24: 0.91876712 | I24: 0.91876712 | J24: 0.98 | K24: 0.94778082 | L24: 0.94778082 | M24: 0.98 | N24: 0.94778082 | O24: 0.94778082 | P24: 0.91287671 | Q24: 0.94778082 | R24: 0.94778082 | S24: 0.98 | T24: 0.94778082 | U24: 0.94778082 | V24: 0.98 | W24: 0.94778082 | X24: 0.94778082 | Y24: 0.98 | Z24: 0.89945205 | AA24: 0.94778082 | AB24: 0.98 | AC24: 0.94778082 | AD24: 0.94778082 | AE24: 0.98 | AF24: 0.94778082 | AG24: 0.94778082 | AH24: 0.98 | AI24: 0.94778082 | AJ24: 0.89945205 | AK24: 0.98 | AL24: 0.94778082 | AM24: 0.94778082 | AN24: 0.98 | AO24: 0.94778082 | AP24: 0.94778082 | AQ24: 0.98 | AR24: 0.94778082 | AS24: 0.94778082 | AT24: 0.91287671 | AU24: 0.94778082 | AV24: 0.94778082 | AW24: 0.98 | AX24: 0.94778082 | AY24: 0.94778082 | AZ24: 0.98 | BA24: 0.94778082 | BB24: 0.94778082 | BC24: 0.98 | BD24: 0.89945205 | BE24: 0.94778082 | BF24: 0.98 | BG24: 0.94778082 | BH24: 0.94778082 | BI24: 0.98 | BJ24: 0.94778082 | BK24: 0.94778082 | BL24: 0.98 | BM24: 0.94778082 | BN24: 0.89945205
B25: cf · central | G25: 0.94 | H25: 0.90136986 | I25: 0.90136986 | J25: 0.97 | K25: 0.93013699 | L25: 0.93013699 | M25: 0.97 | N25: 0.93013699 | O25: 0.93013699 | P25: 0.90356164 | Q25: 0.93013699 | R25: 0.93013699 | S25: 0.97 | T25: 0.93013699 | U25: 0.93013699 | V25: 0.97 | W25: 0.93013699 | X25: 0.93013699 | Y25: 0.97 | Z25: 0.89027397 | AA25: 0.93013699 | AB25: 0.97 | AC25: 0.93013699 | AD25: 0.93013699 | AE25: 0.97 | AF25: 0.93013699 | AG25: 0.93013699 | AH25: 0.97 | AI25: 0.93013699 | AJ25: 0.89027397 | AK25: 0.97 | AL25: 0.93013699 | AM25: 0.93013699 | AN25: 0.97 | AO25: 0.93013699 | AP25: 0.93013699 | AQ25: 0.97 | AR25: 0.93013699 | AS25: 0.93013699 | AT25: 0.90356164 | AU25: 0.93013699 | AV25: 0.93013699 | AW25: 0.97 | AX25: 0.93013699 | AY25: 0.93013699 | AZ25: 0.97 | BA25: 0.93013699 | BB25: 0.93013699 | BC25: 0.97 | BD25: 0.89027397 | BE25: 0.93013699 | BF25: 0.97 | BG25: 0.93013699 | BH25: 0.93013699 | BI25: 0.97 | BJ25: 0.93013699 | BK25: 0.93013699 | BL25: 0.97 | BM25: 0.93013699 | BN25: 0.89027397
B26: cf · high | G26: 0.92 | H26: 0.86958904 | I26: 0.86958904 | J26: 0.95 | K26: 0.89794521 | L26: 0.89794521 | M26: 0.95 | N26: 0.89794521 | O26: 0.89794521 | P26: 0.88493151 | Q26: 0.89794521 | R26: 0.89794521 | S26: 0.95 | T26: 0.89794521 | U26: 0.89794521 | V26: 0.95 | W26: 0.89794521 | X26: 0.89794521 | Y26: 0.95 | Z26: 0.87191781 | AA26: 0.89794521 | AB26: 0.95 | AC26: 0.89794521 | AD26: 0.89794521 | AE26: 0.95 | AF26: 0.89794521 | AG26: 0.89794521 | AH26: 0.95 | AI26: 0.89794521 | AJ26: 0.87191781 | AK26: 0.95 | AL26: 0.89794521 | AM26: 0.89794521 | AN26: 0.95 | AO26: 0.89794521 | AP26: 0.89794521 | AQ26: 0.95 | AR26: 0.89794521 | AS26: 0.89794521 | AT26: 0.88493151 | AU26: 0.89794521 | AV26: 0.89794521 | AW26: 0.95 | AX26: 0.89794521 | AY26: 0.89794521 | AZ26: 0.95 | BA26: 0.89794521 | BB26: 0.89794521 | BC26: 0.95 | BD26: 0.87191781 | BE26: 0.89794521 | BF26: 0.95 | BG26: 0.89794521 | BH26: 0.89794521 | BI26: 0.95 | BJ26: 0.89794521 | BK26: 0.89794521 | BL26: 0.95 | BM26: 0.89794521 | BN26: 0.87191781
B27: cf · selected | G27: =CHOOSE(Dashboard!$C$4,G24,G25,G26) -> 0.94 | H27: =CHOOSE(Dashboard!$C$4,H24,H25,H26) -> 0.90136986 | I27: =CHOOSE(Dashboard!$C$4,I24,I25,I26) -> 0.90136986 | J27: =CHOOSE(Dashboard!$C$4,J24,J25,J26) -> 0.97 | K27: =CHOOSE(Dashboard!$C$4,K24,K25,K26) -> 0.93013699 | L27: =CHOOSE(Dashboard!$C$4,L24,L25,L26) -> 0.93013699 | M27: =CHOOSE(Dashboard!$C$4,M24,M25,M26) -> 0.97 | N27: =CHOOSE(Dashboard!$C$4,N24,N25,N26) -> 0.93013699 | ... BN27: =CHOOSE(Dashboard!$C$4,BN24,BN25,BN26) -> 0.89027397
B28: fuel_ratio · low | G28: 1 | H28: 1 | I28: 1 | J28: 1 | K28: 1 | L28: 1 | M28: 1 | N28: 1 | O28: 1 | P28: 1 | Q28: 1 | R28: 1 | S28: 1 | T28: 1 | U28: 1 | V28: 1 | W28: 1 | X28: 1 | Y28: 1 | Z28: 1 | AA28: 1 | AB28: 1 | AC28: 1 | AD28: 1 | AE28: 1 | AF28: 1 | AG28: 1 | AH28: 1 | AI28: 1 | AJ28: 1 | AK28: 1 | AL28: 1 | AM28: 1 | AN28: 1 | AO28: 1 | AP28: 1 | AQ28: 1 | AR28: 1 | AS28: 1 | AT28: 1 | AU28: 1 | AV28: 1 | AW28: 1 | AX28: 1 | AY28: 1 | AZ28: 1 | BA28: 1 | BB28: 1 | BC28: 1 | BD28: 1 | BE28: 1 | BF28: 1 | BG28: 1 | BH28: 1 | BI28: 1 | BJ28: 1 | BK28: 1 | BL28: 1 | BM28: 1 | BN28: 1
B29: fuel_ratio · central | G29: 1 | H29: 1 | I29: 1 | J29: 1 | K29: 1 | L29: 1 | M29: 1 | N29: 1 | O29: 1 | P29: 1 | Q29: 1 | R29: 1 | S29: 1 | T29: 1 | U29: 1 | V29: 1 | W29: 1 | X29: 1 | Y29: 1 | Z29: 1 | AA29: 1 | AB29: 1 | AC29: 1 | AD29: 1 | AE29: 1 | AF29: 1 | AG29: 1 | AH29: 1 | AI29: 1 | AJ29: 1 | AK29: 1 | AL29: 1 | AM29: 1 | AN29: 1 | AO29: 1 | AP29: 1 | AQ29: 1 | AR29: 1 | AS29: 1 | AT29: 1 | AU29: 1 | AV29: 1 | AW29: 1 | AX29: 1 | AY29: 1 | AZ29: 1 | BA29: 1 | BB29: 1 | BC29: 1 | BD29: 1 | BE29: 1 | BF29: 1 | BG29: 1 | BH29: 1 | BI29: 1 | BJ29: 1 | BK29: 1 | BL29: 1 | BM29: 1 | BN29: 1
B30: fuel_ratio · high | G30: 1 | H30: 1 | I30: 1 | J30: 1 | K30: 1 | L30: 1 | M30: 1 | N30: 1 | O30: 1 | P30: 1 | Q30: 1 | R30: 1 | S30: 1 | T30: 1 | U30: 1 | V30: 1 | W30: 1 | X30: 1 | Y30: 1 | Z30: 1 | AA30: 1 | AB30: 1 | AC30: 1 | AD30: 1 | AE30: 1 | AF30: 1 | AG30: 1 | AH30: 1 | AI30: 1 | AJ30: 1 | AK30: 1 | AL30: 1 | AM30: 1 | AN30: 1 | AO30: 1 | AP30: 1 | AQ30: 1 | AR30: 1 | AS30: 1 | AT30: 1 | AU30: 1 | AV30: 1 | AW30: 1 | AX30: 1 | AY30: 1 | AZ30: 1 | BA30: 1 | BB30: 1 | BC30: 1 | BD30: 1 | BE30: 1 | BF30: 1 | BG30: 1 | BH30: 1 | BI30: 1 | BJ30: 1 | BK30: 1 | BL30: 1 | BM30: 1 | BN30: 1
B31: fuel_ratio · selected | G31: =CHOOSE(Dashboard!$C$4,G28,G29,G30) -> 1 | H31: =CHOOSE(Dashboard!$C$4,H28,H29,H30) -> 1 | I31: =CHOOSE(Dashboard!$C$4,I28,I29,I30) -> 1 | J31: =CHOOSE(Dashboard!$C$4,J28,J29,J30) -> 1 | K31: =CHOOSE(Dashboard!$C$4,K28,K29,K30) -> 1 | L31: =CHOOSE(Dashboard!$C$4,L28,L29,L30) -> 1 | M31: =CHOOSE(Dashboard!$C$4,M28,M29,M30) -> 1 | N31: =CHOOSE(Dashboard!$C$4,N28,N29,N30) -> 1 | ... BN31: =CHOOSE(Dashboard!$C$4,BN28,BN29,BN30) -> 1
B33: SMR · merchant, dynamic 50–100 % dispatch
B34: cf · low | G34: 0.91619578 | H34: 0.88492295 | I34: 0.88477169 | J34: 0.94493607 | K34: 0.91265297 | L34: 0.912621 | M34: 0.94484018 | N34: 0.91254909 | O34: 0.91251712 | P34: 0.87751712 | Q34: 0.91234932 | R34: 0.91226142 | S34: 0.94444863 | T34: 0.91214155 | U34: 0.91208562 | V34: 0.9442089 | W34: 0.91198973 | X34: 0.91198973 | Y34: 0.94416096 | Z34: 0.86351712 | AA34: 0.91184589 | AB34: 0.94406507 | AC34: 0.91181393 | AD34: 0.91181393 | AE34: 0.9440411 | AF34: 0.91175799 | AG34: 0.91168607 | AH34: 0.94387329 | AI34: 0.91165411 | AJ34: 0.86332534 | AK34: 0.94384132 | AL34: 0.91162215 | AM34: 0.91162215 | AN34: 0.94384132 | AO34: 0.91162215 | AP34: 0.91159018 | AQ34: 0.94372945 | AR34: 0.91151027 | AS34: 0.9114863 | AT34: 0.87655023 | AU34: 0.91140639 | AV34: 0.9113984 | AW34: 0.94352169 | AX34: 0.91130251 | AY34: 0.91119863 | AZ34: 0.94341781 | BA34: 0.91110274 | BB34: 0.91107078 | BC34: 0.94326598 | BD34: 0.86268607 | BE34: 0.91093493 | BF34: 0.94315411 | BG34: 0.91088699 | BH34: 0.910871 | BI34: 0.94309018 | BJ34: 0.91084703 | BK34: 0.91078311 | BL34: 0.94300228 | BM34: 0.91074315 | BN34: 0.86238242
B35: cf · central | G35: 0.89515168 | H35: 0.85687909 | I35: 0.85677195 | J35: 0.92355781 | K35: 0.8841427 | L35: 0.8840395 | M35: 0.92342416 | N35: 0.88396337 | O35: 0.88393292 | P35: 0.85756708 | Q35: 0.88375359 | R35: 0.88367464 | S35: 0.92298035 | T35: 0.88359569 | U35: 0.88335884 | V35: 0.92271305 | W35: 0.88309154 | X35: 0.88298834 | Y35: 0.92233973 | Z35: 0.84347624 | AA35: 0.88283045 | AB35: 0.92200532 | AC35: 0.88245656 | AD35: 0.88245656 | AE35: 0.92178652 | AF35: 0.88226821 | AG35: 0.88226201 | AH35: 0.92164666 | AI35: 0.88226201 | AJ35: 0.84287735 | AK35: 0.92164666 | AL35: 0.88226201 | AM35: 0.88226201 | AN35: 0.92164666 | AO35: 0.88226201 | AP35: 0.88226201 | AQ35: 0.92164666 | AR35: 0.88226201 | AS35: 0.88226201 | AT35: 0.85600557 | AU35: 0.88226201 | AV35: 0.88226201 | AW35: 0.92164666 | AX35: 0.88226201 | AY35: 0.88226201 | AZ35: 0.92164666 | BA35: 0.88226201 | BB35: 0.88226201 | BC35: 0.92164666 | BD35: 0.84287735 | BE35: 0.88226201 | BF35: 0.92164666 | BG35: 0.88226201 | BH35: 0.88226201 | BI35: 0.92164666 | BJ35: 0.88226201 | BK35: 0.88226201 | BL35: 0.92164666 | BM35: 0.88226201 | BN35: 0.84287735
B36: cf · high | G36: 0.86843326 | H36: 0.81905514 | I36: 0.81910436 | J36: 0.89706638 | K36: 0.8459492 | L36: 0.84597717 | M36: 0.89693213 | N36: 0.84589047 | O36: 0.84583453 | P36: 0.83305873 | Q36: 0.84581495 | R36: 0.84581495 | S36: 0.89681747 | T36: 0.8457758 | U36: 0.84574783 | V36: 0.89681467 | W36: 0.84580097 | X36: 0.84580097 | Y36: 0.89681467 | Z36: 0.82029412 | AA36: 0.84580097 | AB36: 0.89681467 | AC36: 0.84580097 | AD36: 0.84580097 | AE36: 0.89681467 | AF36: 0.84580097 | AG36: 0.84580097 | AH36: 0.89681467 | AI36: 0.84580097 | AJ36: 0.82029412 | AK36: 0.89681467 | AL36: 0.84580097 | AM36: 0.84580097 | AN36: 0.89681467 | AO36: 0.84580097 | AP36: 0.84580097 | AQ36: 0.89681467 | AR36: 0.84580097 | AS36: 0.84580097 | AT36: 0.83304755 | AU36: 0.84580097 | AV36: 0.84580097 | AW36: 0.89681467 | AX36: 0.84580097 | AY36: 0.84580097 | AZ36: 0.89681467 | BA36: 0.84580097 | BB36: 0.84580097 | BC36: 0.89681467 | BD36: 0.82029412 | BE36: 0.84580097 | BF36: 0.89681467 | BG36: 0.84580097 | BH36: 0.84580097 | BI36: 0.89681467 | BJ36: 0.84580097 | BK36: 0.84580097 | BL36: 0.89681467 | BM36: 0.84580097 | BN36: 0.82029412
B37: cf · selected | G37: =CHOOSE(Dashboard!$C$4,G34,G35,G36) -> 0.89515168 | H37: =CHOOSE(Dashboard!$C$4,H34,H35,H36) -> 0.85687909 | I37: =CHOOSE(Dashboard!$C$4,I34,I35,I36) -> 0.85677195 | J37: =CHOOSE(Dashboard!$C$4,J34,J35,J36) -> 0.92355781 | K37: =CHOOSE(Dashboard!$C$4,K34,K35,K36) -> 0.8841427 | L37: =CHOOSE(Dashboard!$C$4,L34,L35,L36) -> 0.8840395 | M37: =CHOOSE(Dashboard!$C$4,M34,M35,M36) -> 0.92342416 | N37: =CHOOSE(Dashboard!$C$4,N34,N35,N36) -> 0.88396337 | ... BN37: =CHOOSE(Dashboard!$C$4,BN34,BN35,BN36) -> 0.84287735
B38: capture · low | G38: 1.039907 | H38: 1.0356591 | I38: 1.0358059 | J38: 1.0400951 | K38: 1.0358284 | L38: 1.0358565 | M38: 1.0402219 | N38: 1.0359205 | O38: 1.0359487 | P38: 1.0376919 | Q38: 1.036104 | R38: 1.0361855 | S38: 1.0406605 | T38: 1.0362954 | U38: 1.0363465 | V38: 1.0409206 | W38: 1.0364338 | X38: 1.036432 | Y38: 1.0410042 | Z38: 1.0408891 | AA38: 1.0365631 | AB38: 1.0411323 | AC38: 1.0365901 | AD38: 1.0365884 | AE38: 1.0411943 | AF38: 1.0366383 | AG38: 1.036705 | AH38: 1.0413893 | AI38: 1.0367325 | AJ38: 1.0407833 | AK38: 1.0414594 | AL38: 1.0367587 | AM38: 1.0367573 | AN38: 1.0415002 | AO38: 1.0367545 | AP38: 1.0367835 | AQ38: 1.0416441 | AR38: 1.0368567 | AS38: 1.0368782 | AT38: 1.0380077 | AU38: 1.0369517 | AV38: 1.0369582 | AW38: 1.0419184 | AX38: 1.0370473 | AY38: 1.037145 | AZ38: 1.0420564 | BA38: 1.0372343 | BB38: 1.0372639 | BC38: 1.042239 | BD38: 1.0408382 | BE38: 1.0373909 | BF38: 1.0423851 | BG38: 1.0374353 | BH38: 1.0374499 | BI38: 1.0424873 | BJ38: 1.0374717 | BK38: 1.037532 | BL38: 1.042612 | BM38: 1.0375692 | BN38: 1.0408562
B39: capture · central | G39: 1.0405393 | H39: 1.0369578 | I39: 1.0370533 | J39: 1.0407408 | K39: 1.0369701 | L39: 1.037058 | M39: 1.0409445 | N39: 1.0371071 | O39: 1.0371242 | P39: 1.0378909 | Q39: 1.0372763 | R39: 1.037341 | S39: 1.0415226 | T39: 1.0373942 | U39: 1.0376157 | V39: 1.041857 | W39: 1.0378564 | X39: 1.0379458 | Y39: 1.0422946 | Z39: 1.0410687 | AA39: 1.0380708 | AB39: 1.0426967 | AC39: 1.0384175 | AD39: 1.0384078 | AE39: 1.0429902 | AF39: 1.0385727 | AG39: 1.0385695 | AH39: 1.043181 | AI39: 1.0385695 | AJ39: 1.0412836 | AK39: 1.043181 | AL39: 1.0385695 | AM39: 1.0385695 | AN39: 1.043181 | AO39: 1.0385695 | AP39: 1.0385695 | AQ39: 1.043181 | AR39: 1.0385695 | AS39: 1.0385695 | AT39: 1.0387701 | AU39: 1.0385695 | AV39: 1.0385695 | AW39: 1.043181 | AX39: 1.0385695 | AY39: 1.0385695 | AZ39: 1.043181 | BA39: 1.0385695 | BB39: 1.0385695 | BC39: 1.043181 | BD39: 1.0412836 | BE39: 1.0385695 | BF39: 1.043181 | BG39: 1.0385695 | BH39: 1.0385695 | BI39: 1.043181 | BJ39: 1.0385695 | BK39: 1.0385695 | BL39: 1.043181 | BM39: 1.0385695 | BN39: 1.0412836
B40: capture · high | G40: 1.0412437 | H40: 1.0372934 | I40: 1.0372007 | J40: 1.0410253 | K40: 1.0369485 | L40: 1.0368791 | M40: 1.0412764 | N40: 1.0368858 | O40: 1.0369036 | P40: 1.0375407 | Q40: 1.0368436 | R40: 1.0368038 | S40: 1.0416299 | T40: 1.0367631 | U40: 1.0367523 | V40: 1.0417284 | W40: 1.0366849 | X40: 1.0366849 | Y40: 1.0417284 | Z40: 1.0396989 | AA40: 1.0366849 | AB40: 1.0417284 | AC40: 1.0366849 | AD40: 1.0366849 | AE40: 1.0417284 | AF40: 1.0366849 | AG40: 1.0366849 | AH40: 1.0417284 | AI40: 1.0366849 | AJ40: 1.0396989 | AK40: 1.0417284 | AL40: 1.0366849 | AM40: 1.0366849 | AN40: 1.0417284 | AO40: 1.0366849 | AP40: 1.0366849 | AQ40: 1.0417284 | AR40: 1.0366849 | AS40: 1.0366849 | AT40: 1.0372142 | AU40: 1.0366849 | AV40: 1.0366849 | AW40: 1.0417284 | AX40: 1.0366849 | AY40: 1.0366849 | AZ40: 1.0417284 | BA40: 1.0366849 | BB40: 1.0366849 | BC40: 1.0417284 | BD40: 1.0396989 | BE40: 1.0366849 | BF40: 1.0417284 | BG40: 1.0366849 | BH40: 1.0366849 | BI40: 1.0417284 | BJ40: 1.0366849 | BK40: 1.0366849 | BL40: 1.0417284 | BM40: 1.0366849 | BN40: 1.0396989
B41: capture · selected | G41: =CHOOSE(Dashboard!$C$4,G38,G39,G40) -> 1.0405393 | H41: =CHOOSE(Dashboard!$C$4,H38,H39,H40) -> 1.0369578 | I41: =CHOOSE(Dashboard!$C$4,I38,I39,I40) -> 1.0370533 | J41: =CHOOSE(Dashboard!$C$4,J38,J39,J40) -> 1.0407408 | K41: =CHOOSE(Dashboard!$C$4,K38,K39,K40) -> 1.0369701 | L41: =CHOOSE(Dashboard!$C$4,L38,L39,L40) -> 1.037058 | M41: =CHOOSE(Dashboard!$C$4,M38,M39,M40) -> 1.0409445 | N41: =CHOOSE(Dashboard!$C$4,N38,N39,N40) -> 1.0371071 | ... BN41: =CHOOSE(Dashboard!$C$4,BN38,BN39,BN40) -> 1.0412836
B42: fuel_ratio · low | G42: 1.0018884 | H42: 1.0019578 | I42: 1.0019669 | J42: 1.0019073 | K42: 1.0019781 | L42: 1.0019799 | M42: 1.0019124 | N42: 1.0019833 | O42: 1.001985 | P42: 1.00207 | Q42: 1.0019942 | R42: 1.0019996 | S42: 1.0019331 | T42: 1.0020061 | U42: 1.0020092 | V42: 1.0019463 | W42: 1.002015 | X42: 1.002015 | Y42: 1.0019493 | Z42: 1.0021373 | AA42: 1.002024 | AB42: 1.0019549 | AC42: 1.0020258 | AD42: 1.0020258 | AE42: 1.0019562 | AF42: 1.0020294 | AG42: 1.0020339 | AH42: 1.0019662 | AI42: 1.0020357 | AJ42: 1.0021496 | AK42: 1.0019679 | AL42: 1.0020374 | AM42: 1.0020374 | AN42: 1.0019679 | AO42: 1.0020374 | AP42: 1.0020391 | AQ42: 1.0019749 | AR42: 1.0020447 | AS42: 1.002046 | AT42: 1.0021293 | AU42: 1.0020515 | AV42: 1.0020519 | AW42: 1.0019875 | AX42: 1.0020578 | AY42: 1.002064 | AZ42: 1.0019935 | BA42: 1.0020698 | BB42: 1.0020716 | BC42: 1.0020021 | BD42: 1.0021909 | BE42: 1.0020802 | BF42: 1.0020091 | BG42: 1.0020828 | BH42: 1.0020843 | BI42: 1.0020131 | BJ42: 1.0020856 | BK42: 1.0020897 | BL42: 1.0020183 | BM42: 1.0020924 | BN42: 1.0022116
B43: fuel_ratio · central | G43: 1.0018154 | H43: 1.0019021 | I43: 1.001908 | J43: 1.0018298 | K43: 1.001913 | L43: 1.0019185 | M43: 1.0018367 | N43: 1.0019231 | O43: 1.0019247 | P43: 1.0019908 | Q43: 1.0019359 | R43: 1.0019412 | S43: 1.0018625 | T43: 1.0019455 | U43: 1.0019593 | V43: 1.0018772 | W43: 1.0019758 | X43: 1.0019824 | Y43: 1.0019 | Z43: 1.0020833 | AA43: 1.001992 | AB43: 1.0019192 | AC43: 1.0020147 | AD43: 1.0020147 | AE43: 1.0019314 | AF43: 1.0020249 | AG43: 1.0020252 | AH43: 1.0019386 | AI43: 1.0020252 | AJ43: 1.0021198 | AK43: 1.0019386 | AL43: 1.0020252 | AM43: 1.0020252 | AN43: 1.0019386 | AO43: 1.0020252 | AP43: 1.0020252 | AQ43: 1.0019386 | AR43: 1.0020252 | AS43: 1.0020252 | AT43: 1.0020873 | AU43: 1.0020252 | AV43: 1.0020252 | AW43: 1.0019386 | AX43: 1.0020252 | AY43: 1.0020252 | AZ43: 1.0019386 | BA43: 1.0020252 | BB43: 1.0020252 | BC43: 1.0019386 | BD43: 1.0021198 | BE43: 1.0020252 | BF43: 1.0019386 | BG43: 1.0020252 | BH43: 1.0020252 | BI43: 1.0019386 | BJ43: 1.0020252 | BK43: 1.0020252 | BL43: 1.0019386 | BM43: 1.0020252 | BN43: 1.0021198
B44: fuel_ratio · high | G44: 1.0018402 | H44: 1.0019498 | I44: 1.001947 | J44: 1.0018289 | K44: 1.0019461 | L44: 1.0019445 | M44: 1.0018376 | N44: 1.0019499 | O44: 1.001953 | P44: 1.0019843 | Q44: 1.0019542 | R44: 1.0019542 | S44: 1.0018441 | T44: 1.0019569 | U44: 1.0019585 | V44: 1.0018443 | W44: 1.0019555 | X44: 1.0019555 | Y44: 1.0018443 | Z44: 1.0020163 | AA44: 1.0019555 | AB44: 1.0018443 | AC44: 1.0019555 | AD44: 1.0019555 | AE44: 1.0018443 | AF44: 1.0019555 | AG44: 1.0019555 | AH44: 1.0018443 | AI44: 1.0019555 | AJ44: 1.0020163 | AK44: 1.0018443 | AL44: 1.0019555 | AM44: 1.0019555 | AN44: 1.0018443 | AO44: 1.0019555 | AP44: 1.0019555 | AQ44: 1.0018443 | AR44: 1.0019555 | AS44: 1.0019555 | AT44: 1.0019854 | AU44: 1.0019555 | AV44: 1.0019555 | AW44: 1.0018443 | AX44: 1.0019555 | AY44: 1.0019555 | AZ44: 1.0018443 | BA44: 1.0019555 | BB44: 1.0019555 | BC44: 1.0018443 | BD44: 1.0020163 | BE44: 1.0019555 | BF44: 1.0018443 | BG44: 1.0019555 | BH44: 1.0019555 | BI44: 1.0018443 | BJ44: 1.0019555 | BK44: 1.0019555 | BL44: 1.0018443 | BM44: 1.0019555 | BN44: 1.0020163
B45: fuel_ratio · selected | G45: =CHOOSE(Dashboard!$C$4,G42,G43,G44) -> 1.0018154 | H45: =CHOOSE(Dashboard!$C$4,H42,H43,H44) -> 1.0019021 | I45: =CHOOSE(Dashboard!$C$4,I42,I43,I44) -> 1.001908 | J45: =CHOOSE(Dashboard!$C$4,J42,J43,J44) -> 1.0018298 | K45: =CHOOSE(Dashboard!$C$4,K42,K43,K44) -> 1.001913 | L45: =CHOOSE(Dashboard!$C$4,L42,L43,L44) -> 1.0019185 | M45: =CHOOSE(Dashboard!$C$4,M42,M43,M44) -> 1.0018367 | N45: =CHOOSE(Dashboard!$C$4,N42,N43,N44) -> 1.0019231 | ... BN45: =CHOOSE(Dashboard!$C$4,BN42,BN43,BN44) -> 1.0021198
B47: CCGT 1+1 ~300 MW · merchant dynamic
B48: cf · low | G48: 0.30558904 | H48: 0.28592466 | I48: 0.24844521 | J48: 0.21133562 | K48: 0.18978082 | L48: 0.18260959 | M48: 0.1785411 | N48: 0.16832877 | O48: 0.16294521 | P48: 0.15589726 | Q48: 0.15258904 | R48: 0.14938356 | S48: 0.1424589 | T48: 0.1399726 | U48: 0.13456849 | V48: 0.13136301 | W48: 0.12828082 | X48: 0.12452055 | Y48: 0.12076027 | Z48: 0.11981507 | AA48: 0.12012329 | AB48: 0.12022603 | AC48: 0.12022603 | AD48: 0.12028767 | AE48: 0.12028767 | AF48: 0.12032877 | AG48: 0.11971233 | AH48: 0.12008219 | AI48: 0.12018493 | AJ48: 0.12115068
B49: cf · central | G49: 0.32748801 | H49: 0.30922032 | I49: 0.28138584 | J49: 0.25154509 | K49: 0.21705822 | L49: 0.20246518 | M49: 0.19158904 | N49: 0.17807306 | O49: 0.16740811 | P49: 0.1548847 | Q49: 0.15239269 | R49: 0.15154795 | S49: 0.14996404 | T49: 0.148 | U49: 0.14411416 | V49: 0.14358619 | W49: 0.14291039 | X49: 0.14126313 | Y49: 0.1406718 | Z49: 0.13957363 | AA49: 0.13946804 | AB49: 0.13961587 | AC49: 0.13965811 | AD49: 0.14065068 | AE49: 0.14096747 | AF49: 0.14107306 | AG49: 0.14297374 | AH49: 0.14571918 | AI49: 0.14593037 | AJ49: 0.14639498
B50: cf · high | G50: 0.25617466 | H50: 0.22110274 | I50: 0.19195205 | J50: 0.16681393 | K50: 0.14881164 | L50: 0.14859475 | M50: 0.14718493 | N50: 0.14946233 | O50: 0.14913699 | P50: 0.14772717 | Q50: 0.15065525 | R50: 0.15419064 | S50: 0.16069749 | T50: 0.16503539 | U50: 0.16720434 | V50: 0.17208447 | W50: 0.18021804 | X50: 0.18455594 | Y50: 0.19286301 | Z50: 0.19481507 | AA50: 0.19481507 | AB50: 0.19481507 | AC50: 0.19481507 | AD50: 0.19481507 | AE50: 0.19481507 | AF50: 0.19481507 | AG50: 0.19481507 | AH50: 0.19481507 | AI50: 0.19481507 | AJ50: 0.19481507
B51: cf · selected | G51: =CHOOSE(Dashboard!$C$4,G48,G49,G50) -> 0.32748801 | H51: =CHOOSE(Dashboard!$C$4,H48,H49,H50) -> 0.30922032 | I51: =CHOOSE(Dashboard!$C$4,I48,I49,I50) -> 0.28138584 | J51: =CHOOSE(Dashboard!$C$4,J48,J49,J50) -> 0.25154509 | K51: =CHOOSE(Dashboard!$C$4,K48,K49,K50) -> 0.21705822 | L51: =CHOOSE(Dashboard!$C$4,L48,L49,L50) -> 0.20246518 | M51: =CHOOSE(Dashboard!$C$4,M48,M49,M50) -> 0.19158904 | N51: =CHOOSE(Dashboard!$C$4,N48,N49,N50) -> 0.17807306 | ... BN51: =CHOOSE(Dashboard!$C$4,BN48,BN49,BN50) -> 0
B52: capture · low | G52: 1.4164218 | H52: 1.4375067 | I52: 1.4816846 | J52: 1.5390284 | K52: 1.5763222 | L52: 1.5891356 | M52: 1.5976279 | N52: 1.6196674 | O52: 1.6295219 | P52: 1.6474985 | Q52: 1.6545574 | R52: 1.661421 | S52: 1.6847415 | T52: 1.6920985 | U52: 1.7117328 | V52: 1.7214183 | W52: 1.7310122 | X52: 1.7423577 | Y52: 1.753238 | Z52: 1.7575322 | AA52: 1.7565496 | AB52: 1.7562956 | AC52: 1.75652 | AD52: 1.7563705 | AE52: 1.7565954 | AF52: 1.7567421 | AG52: 1.7582649 | AH52: 1.7570358 | AI52: 1.7569015 | AJ52: 1.7547239
B53: capture · central | G53: 1.4137578 | H53: 1.4330845 | I53: 1.4669623 | J53: 1.5074478 | K53: 1.5566164 | L53: 1.5824288 | M53: 1.6037993 | N53: 1.633595 | O53: 1.661636 | P53: 1.6928567 | Q53: 1.6981876 | R53: 1.701238 | S53: 1.7064107 | T53: 1.7124274 | U53: 1.7233832 | V53: 1.7255983 | W53: 1.7272088 | X53: 1.7313482 | Y53: 1.7338718 | Z53: 1.7382898 | AA53: 1.7392857 | AB53: 1.7395495 | AC53: 1.7401421 | AD53: 1.7388325 | AE53: 1.7384332 | AF53: 1.7386765 | AG53: 1.7327591 | AH53: 1.7252894 | AI53: 1.7253793 | AJ53: 1.7253786
B54: capture · high | G54: 1.5130869 | H54: 1.5636288 | I54: 1.622028 | J54: 1.6787336 | K54: 1.7274546 | L54: 1.728895 | M54: 1.7352636 | N54: 1.7307008 | O54: 1.7325784 | P54: 1.7372686 | Q54: 1.7310128 | R54: 1.7226797 | S54: 1.7062484 | T54: 1.6983478 | U54: 1.693066 | V54: 1.6832001 | W54: 1.6641912 | X54: 1.6558848 | Y54: 1.6409808 | Z54: 1.6371669 | AA54: 1.6371669 | AB54: 1.6371669 | AC54: 1.6371669 | AD54: 1.6371669 | AE54: 1.6371669 | AF54: 1.6371669 | AG54: 1.6371669 | AH54: 1.6371669 | AI54: 1.6371669 | AJ54: 1.6371669
B55: capture · selected | G55: =CHOOSE(Dashboard!$C$4,G52,G53,G54) -> 1.4137578 | H55: =CHOOSE(Dashboard!$C$4,H52,H53,H54) -> 1.4330845 | I55: =CHOOSE(Dashboard!$C$4,I52,I53,I54) -> 1.4669623 | J55: =CHOOSE(Dashboard!$C$4,J52,J53,J54) -> 1.5074478 | K55: =CHOOSE(Dashboard!$C$4,K52,K53,K54) -> 1.5566164 | L55: =CHOOSE(Dashboard!$C$4,L52,L53,L54) -> 1.5824288 | M55: =CHOOSE(Dashboard!$C$4,M52,M53,M54) -> 1.6037993 | N55: =CHOOSE(Dashboard!$C$4,N52,N53,N54) -> 1.633595 | ... BN55: =CHOOSE(Dashboard!$C$4,BN52,BN53,BN54) -> 0
B56: heat · low | G56: 1.8062781 | H56: 1.805769 | I56: 1.8090333 | J56: 1.8123181 | K56: 1.8144714 | L56: 1.8155592 | M56: 1.8175541 | N56: 1.8176388 | O56: 1.8172232 | P56: 1.820006 | Q56: 1.8194053 | R56: 1.8188576 | S56: 1.8207885 | T56: 1.8195485 | U56: 1.8193801 | V56: 1.8179171 | W56: 1.8169094 | X56: 1.8179896 | Y56: 1.8165396 | Z56: 1.8169374 | AA56: 1.8170629 | AB56: 1.8169079 | AC56: 1.8169079 | AD56: 1.8166908 | AE56: 1.8166908 | AF56: 1.8168145 | AG56: 1.8168129 | AH56: 1.8169857 | AI56: 1.8170637 | AJ56: 1.8174721
B57: heat · central | G57: 1.7380312 | H57: 1.7376207 | I57: 1.7418342 | J57: 1.7452769 | K57: 1.7460164 | L57: 1.7500286 | M57: 1.7515451 | N57: 1.7522998 | O57: 1.7550509 | P57: 1.7564416 | Q57: 1.755657 | R57: 1.7555462 | S57: 1.7571717 | T57: 1.7576018 | U57: 1.7592093 | V57: 1.7589848 | W57: 1.7582813 | X57: 1.7577934 | Y57: 1.757595 | Z57: 1.7582021 | AA57: 1.7582985 | AB57: 1.7585671 | AC57: 1.7587592 | AD57: 1.7584017 | AE57: 1.7584304 | AF57: 1.7582955 | AG57: 1.7571454 | AH57: 1.7562529 | AI57: 1.7564521 | AJ57: 1.7561674
B58: heat · high | G58: 1.6580268 | H58: 1.6591478 | I58: 1.6630563 | J58: 1.6678129 | K58: 1.6719436 | L58: 1.6718064 | M58: 1.6728201 | N58: 1.6735251 | O58: 1.6734569 | P58: 1.673761 | Q58: 1.6733811 | R58: 1.6737814 | S58: 1.6705968 | T58: 1.6705619 | U58: 1.6691945 | V58: 1.6681677 | W58: 1.6664731 | X58: 1.6655011 | Y58: 1.6652082 | Z58: 1.6652155 | AA58: 1.6652155 | AB58: 1.6652155 | AC58: 1.6652155 | AD58: 1.6652155 | AE58: 1.6652155 | AF58: 1.6652155 | AG58: 1.6652155 | AH58: 1.6652155 | AI58: 1.6652155 | AJ58: 1.6652155
B59: heat · selected | G59: =CHOOSE(Dashboard!$C$4,G56,G57,G58) -> 1.7380312 | H59: =CHOOSE(Dashboard!$C$4,H56,H57,H58) -> 1.7376207 | I59: =CHOOSE(Dashboard!$C$4,I56,I57,I58) -> 1.7418342 | J59: =CHOOSE(Dashboard!$C$4,J56,J57,J58) -> 1.7452769 | K59: =CHOOSE(Dashboard!$C$4,K56,K57,K58) -> 1.7460164 | L59: =CHOOSE(Dashboard!$C$4,L56,L57,L58) -> 1.7500286 | M59: =CHOOSE(Dashboard!$C$4,M56,M57,M58) -> 1.7515451 | N59: =CHOOSE(Dashboard!$C$4,N56,N57,N58) -> 1.7522998 | ... BN59: =CHOOSE(Dashboard!$C$4,BN56,BN57,BN58) -> 0
B60: start · low | G60: 22.9366 | H60: 24.478764 | I60: 26.910668 | J60: 31.118544 | K60: 33.256003 | L60: 33.665654 | M60: 34.093426 | N60: 35.887234 | O60: 36.305142 | P60: 37.247485 | Q60: 37.411048 | R60: 37.547241 | S60: 40.036412 | T60: 40.833888 | U60: 43.03076 | V60: 43.868189 | W60: 44.509904 | X60: 44.998533 | Y60: 45.229539 | Z60: 45.586349 | AA60: 45.469381 | AB60: 45.430525 | AC60: 45.430525 | AD60: 45.407243 | AE60: 45.407243 | AF60: 45.391735 | AG60: 45.283328 | AH60: 45.143851 | AI60: 45.10526 | AJ60: 44.995063
B61: start · central | G61: 27.486656 | H61: 28.875143 | I61: 31.75158 | J61: 35.465994 | K61: 38.573905 | L61: 39.870579 | M61: 41.526193 | N61: 44.453587 | O61: 47.377141 | P61: 49.575012 | Q61: 49.902484 | R61: 50.180647 | S61: 50.416972 | T61: 50.850379 | U61: 51.197031 | V61: 51.385283 | W61: 51.434122 | X61: 51.465213 | Y61: 51.827621 | Z61: 52.235404 | AA61: 52.274952 | AB61: 52.146014 | AC61: 52.130243 | AD61: 52.328707 | AE61: 52.211114 | AF61: 52.099207 | AG61: 51.579225 | AH61: 50.91812 | AI61: 50.844432 | AJ61: 50.991485
B62: start · high | G62: 40.255917 | H62: 43.997553 | I62: 50.34499 | J62: 55.168242 | K62: 59.12135 | L62: 59.207645 | M62: 60.044209 | N62: 59.829526 | O62: 59.960044 | P62: 60.232982 | Q62: 60.128283 | R62: 59.369517 | S62: 58.161624 | T62: 58.108749 | U62: 57.367875 | V62: 56.907182 | W62: 54.527811 | X62: 53.681056 | Y62: 52.533324 | Z62: 52.006938 | AA62: 52.006938 | AB62: 52.006938 | AC62: 52.006938 | AD62: 52.006938 | AE62: 52.006938 | AF62: 52.006938 | AG62: 52.006938 | AH62: 52.006938 | AI62: 52.006938 | AJ62: 52.006938
B63: start · selected | G63: =CHOOSE(Dashboard!$C$4,G60,G61,G62) -> 27.486656 | H63: =CHOOSE(Dashboard!$C$4,H60,H61,H62) -> 28.875143 | I63: =CHOOSE(Dashboard!$C$4,I60,I61,I62) -> 31.75158 | J63: =CHOOSE(Dashboard!$C$4,J60,J61,J62) -> 35.465994 | K63: =CHOOSE(Dashboard!$C$4,K60,K61,K62) -> 38.573905 | L63: =CHOOSE(Dashboard!$C$4,L60,L61,L62) -> 39.870579 | M63: =CHOOSE(Dashboard!$C$4,M60,M61,M62) -> 41.526193 | N63: =CHOOSE(Dashboard!$C$4,N60,N61,N62) -> 44.453587 | ... BN63: =CHOOSE(Dashboard!$C$4,BN60,BN61,BN62) -> 0
B65: OCGT 2×150 MW · merchant dynamic
B66: cf · low | G66: 0.045332192 | H66: 0.042253425 | I66: 0.038537671 | J66: 0.037157534 | K66: 0.034184932 | L66: 0.033547945 | M66: 0.032836644 | N66: 0.032443836 | O66: 0.031276027 | P66: 0.02930137 | Q66: 0.029089041 | R66: 0.029089041 | S66: 0.028770548 | T66: 0.02834589 | U66: 0.02760274 | V66: 0.026859589 | W66: 0.026541096 | X66: 0.026434932 | Y66: 0.026116438 | Z66: 0.02590411 | AA66: 0.026010274 | AB66: 0.026010274 | AC66: 0.026010274 | AD66: 0.026116438 | AE66: 0.026116438 | AF66: 0.026116438 | AG66: 0.026116438 | AH66: 0.026116438 | AI66: 0.026116438 | AJ66: 0.026116438
B67: cf · central | G67: 0.061055936 | H67: 0.055633562 | I67: 0.051729452 | J67: 0.047608447 | K67: 0.04359589 | L67: 0.042294521 | M67: 0.040559361 | N67: 0.037631279 | O67: 0.036763699 | P67: 0.035462329 | Q67: 0.035245434 | R67: 0.035028539 | S67: 0.034920091 | T67: 0.034811644 | U67: 0.033944064 | V67: 0.033510274 | W67: 0.033510274 | X67: 0.033076484 | Y67: 0.032642694 | Z67: 0.032642694 | AA67: 0.032642694 | AB67: 0.032642694 | AC67: 0.032642694 | AD67: 0.032642694 | AE67: 0.032642694 | AF67: 0.032642694 | AG67: 0.032642694 | AH67: 0.032534247 | AI67: 0.032534247 | AJ67: 0.032751142
B68: cf · high | G68: 0.057026256 | H68: 0.052375571 | I68: 0.047724886 | J68: 0.043738584 | K68: 0.040416667 | L68: 0.039973744 | M68: 0.040084475 | N68: 0.040084475 | O68: 0.039863014 | P68: 0.039752283 | Q68: 0.040416667 | R68: 0.041745434 | S68: 0.041856164 | T68: 0.042631279 | U68: 0.043295662 | V68: 0.044292237 | W68: 0.045510274 | X68: 0.04661758 | Y68: 0.047392694 | Z68: 0.047946347 | AA68: 0.047946347 | AB68: 0.047946347 | AC68: 0.047946347 | AD68: 0.047946347 | AE68: 0.047946347 | AF68: 0.047946347 | AG68: 0.047946347 | AH68: 0.047946347 | AI68: 0.047946347 | AJ68: 0.047946347
B69: cf · selected | G69: =CHOOSE(Dashboard!$C$4,G66,G67,G68) -> 0.061055936 | H69: =CHOOSE(Dashboard!$C$4,H66,H67,H68) -> 0.055633562 | I69: =CHOOSE(Dashboard!$C$4,I66,I67,I68) -> 0.051729452 | J69: =CHOOSE(Dashboard!$C$4,J66,J67,J68) -> 0.047608447 | K69: =CHOOSE(Dashboard!$C$4,K66,K67,K68) -> 0.04359589 | L69: =CHOOSE(Dashboard!$C$4,L66,L67,L68) -> 0.042294521 | M69: =CHOOSE(Dashboard!$C$4,M66,M67,M68) -> 0.040559361 | N69: =CHOOSE(Dashboard!$C$4,N66,N67,N68) -> 0.037631279 | ... BN69: =CHOOSE(Dashboard!$C$4,BN66,BN67,BN68) -> 0
B70: capture · low | G70: 2.3406987 | H70: 2.3822517 | I70: 2.435157 | J70: 2.460122 | K70: 2.5128384 | L70: 2.5241443 | M70: 2.5375061 | N70: 2.5466433 | O70: 2.5664253 | P70: 2.6152556 | Q70: 2.6205949 | R70: 2.6205173 | S70: 2.6260939 | T70: 2.6363917 | U70: 2.6527168 | V70: 2.6706129 | W70: 2.6790236 | X70: 2.6817982 | Y70: 2.6891662 | Z70: 2.6954508 | AA70: 2.6917892 | AB70: 2.691714 | AC70: 2.6916389 | AD70: 2.6888091 | AE70: 2.6887377 | AF70: 2.6886662 | AG70: 2.6885948 | AH70: 2.6885234 | AI70: 2.6884519 | AJ70: 2.6883805
B71: capture · central | G71: 2.1866286 | H71: 2.2386656 | I71: 2.2821697 | J71: 2.3309842 | K71: 2.3819185 | L71: 2.401092 | M71: 2.4256002 | N71: 2.4686108 | O71: 2.4858013 | P71: 2.5092109 | Q71: 2.513878 | R71: 2.5175947 | S71: 2.5200016 | T71: 2.5207749 | U71: 2.5409861 | V71: 2.5469604 | W71: 2.5469182 | X71: 2.5550376 | Y71: 2.5642462 | Z71: 2.5641941 | AA71: 2.5641421 | AB71: 2.56409 | AC71: 2.5637462 | AD71: 2.5637101 | AE71: 2.563674 | AF71: 2.5636379 | AG71: 2.5636018 | AH71: 2.5657684 | AI71: 2.5657421 | AJ71: 2.5616255
B72: capture · high | G72: 2.2372879 | H72: 2.2877687 | I72: 2.3447816 | J72: 2.3938657 | K72: 2.4447914 | L72: 2.4516958 | M72: 2.4506748 | N72: 2.4506715 | O72: 2.4542903 | P72: 2.4564416 | Q72: 2.4457519 | R72: 2.4255732 | S72: 2.4241217 | T72: 2.41317 | U72: 2.4048756 | V72: 2.3925365 | W72: 2.3772757 | X72: 2.3659906 | Y72: 2.3564959 | Z72: 2.3501509 | AA72: 2.3501509 | AB72: 2.3501509 | AC72: 2.3501509 | AD72: 2.3501509 | AE72: 2.3501509 | AF72: 2.3501509 | AG72: 2.3501509 | AH72: 2.3501509 | AI72: 2.3501509 | AJ72: 2.3501509
B73: capture · selected | G73: =CHOOSE(Dashboard!$C$4,G70,G71,G72) -> 2.1866286 | H73: =CHOOSE(Dashboard!$C$4,H70,H71,H72) -> 2.2386656 | I73: =CHOOSE(Dashboard!$C$4,I70,I71,I72) -> 2.2821697 | J73: =CHOOSE(Dashboard!$C$4,J70,J71,J72) -> 2.3309842 | K73: =CHOOSE(Dashboard!$C$4,K70,K71,K72) -> 2.3819185 | L73: =CHOOSE(Dashboard!$C$4,L70,L71,L72) -> 2.401092 | M73: =CHOOSE(Dashboard!$C$4,M70,M71,M72) -> 2.4256002 | N73: =CHOOSE(Dashboard!$C$4,N70,N71,N72) -> 2.4686108 | ... BN73: =CHOOSE(Dashboard!$C$4,BN70,BN71,BN72) -> 0
B74: heat · low | G74: 2.7483399 | H74: 2.7469812 | I74: 2.7410696 | J74: 2.740386 | K74: 2.7377578 | L74: 2.7393934 | M74: 2.741166 | N74: 2.7418926 | O74: 2.7412579 | P74: 2.7473866 | Q74: 2.746971 | R74: 2.746971 | S74: 2.7447993 | T74: 2.7422436 | U74: 2.7415333 | V74: 2.743198 | W74: 2.7409096 | X74: 2.7400974 | Y74: 2.7401042 | Z74: 2.740033 | AA74: 2.7390488 | AB74: 2.7390488 | AC74: 2.7390488 | AD74: 2.7401042 | AE74: 2.7401042 | AF74: 2.7401042 | AG74: 2.7401042 | AH74: 2.7401042 | AI74: 2.7401042 | AJ74: 2.7401042
B75: heat · central | G75: 2.5492309 | H75: 2.5454429 | I75: 2.541809 | J75: 2.5413193 | K75: 2.5393895 | L75: 2.5372836 | M75: 2.5387884 | N75: 2.5343948 | O75: 2.5329642 | P75: 2.5330385 | Q75: 2.5339583 | R75: 2.5353655 | S75: 2.5360757 | T75: 2.5355927 | U75: 2.53825 | V75: 2.5359392 | W75: 2.5359392 | X75: 2.5359207 | Y75: 2.5384562 | Z75: 2.5384562 | AA75: 2.5384562 | AB75: 2.5384562 | AC75: 2.5376047 | AD75: 2.5376047 | AE75: 2.5376047 | AF75: 2.5376047 | AG75: 2.5376047 | AH75: 2.5370075 | AI75: 2.5370075 | AJ75: 2.5354822
B76: heat · high | G76: 2.3076811 | H76: 2.3048061 | I76: 2.306063 | J76: 2.3029646 | K76: 2.3038006 | L76: 2.3040857 | M76: 2.3041422 | N76: 2.3041422 | O76: 2.3035122 | P76: 2.3041011 | Q76: 2.3038643 | R76: 2.3045847 | S76: 2.305437 | T76: 2.3049395 | U76: 2.3062513 | V76: 2.3075931 | W76: 2.3086694 | X76: 2.3124703 | Y76: 2.3133741 | Z76: 2.3127517 | AA76: 2.3127517 | AB76: 2.3127517 | AC76: 2.3127517 | AD76: 2.3127517 | AE76: 2.3127517 | AF76: 2.3127517 | AG76: 2.3127517 | AH76: 2.3127517 | AI76: 2.3127517 | AJ76: 2.3127517
B77: heat · selected | G77: =CHOOSE(Dashboard!$C$4,G74,G75,G76) -> 2.5492309 | H77: =CHOOSE(Dashboard!$C$4,H74,H75,H76) -> 2.5454429 | I77: =CHOOSE(Dashboard!$C$4,I74,I75,I76) -> 2.541809 | J77: =CHOOSE(Dashboard!$C$4,J74,J75,J76) -> 2.5413193 | K77: =CHOOSE(Dashboard!$C$4,K74,K75,K76) -> 2.5393895 | L77: =CHOOSE(Dashboard!$C$4,L74,L75,L76) -> 2.5372836 | M77: =CHOOSE(Dashboard!$C$4,M74,M75,M76) -> 2.5387884 | N77: =CHOOSE(Dashboard!$C$4,N74,N75,N76) -> 2.5343948 | ... BN77: =CHOOSE(Dashboard!$C$4,BN74,BN75,BN76) -> 0
B78: start · low | G78: 34.325527 | H78: 34.291754 | I78: 34.043603 | J78: 34.905561 | K78: 35.723469 | L78: 35.508983 | M78: 35.362612 | N78: 35.790759 | O78: 35.180562 | P78: 37.011415 | Q78: 37.281571 | R78: 37.281571 | S78: 37.158711 | T78: 37.715396 | U78: 37.633457 | V78: 37.551192 | W78: 38.001806 | X78: 38.154424 | Y78: 38.038377 | Z78: 38.350167 | AA78: 38.193636 | AB78: 38.193636 | AC78: 38.193636 | AD78: 38.038377 | AE78: 38.038377 | AF78: 38.038377 | AG78: 38.038377 | AH78: 38.038377 | AI78: 38.038377 | AJ78: 38.038377
B79: start · central | G79: 34.830373 | H79: 35.333898 | I79: 36.769337 | J79: 37.266695 | K79: 37.009256 | L79: 37.762227 | M79: 37.415339 | N79: 36.881314 | O79: 38.175361 | P79: 38.667826 | Q79: 38.905781 | R79: 38.702004 | S79: 38.822197 | T79: 38.475767 | U79: 39.91806 | V79: 39.460995 | W79: 39.460995 | X79: 39.495013 | Y79: 39.542682 | Z79: 39.542682 | AA79: 39.542682 | AB79: 39.542682 | AC79: 39.542682 | AD79: 39.542682 | AE79: 39.542682 | AF79: 39.542682 | AG79: 39.542682 | AH79: 39.674491 | AI79: 39.674491 | AJ79: 39.887348
B80: start · high | G80: 38.057952 | H80: 39.455603 | I80: 40.762133 | J80: 40.08528 | K80: 41.637763 | L80: 41.678613 | M80: 41.997779 | N80: 41.997779 | O80: 42.2311 | P80: 42.348735 | Q80: 42.068493 | R80: 41.563483 | S80: 41.453526 | T80: 41.505289 | U80: 41.678092 | V80: 41.927577 | W80: 41.951677 | X80: 42.487511 | Y80: 42.16248 | Z80: 42.389288 | AA80: 42.389288 | AB80: 42.389288 | AC80: 42.389288 | AD80: 42.389288 | AE80: 42.389288 | AF80: 42.389288 | AG80: 42.389288 | AH80: 42.389288 | AI80: 42.389288 | AJ80: 42.389288
B81: start · selected | G81: =CHOOSE(Dashboard!$C$4,G78,G79,G80) -> 34.830373 | H81: =CHOOSE(Dashboard!$C$4,H78,H79,H80) -> 35.333898 | I81: =CHOOSE(Dashboard!$C$4,I78,I79,I80) -> 36.769337 | J81: =CHOOSE(Dashboard!$C$4,J78,J79,J80) -> 37.266695 | K81: =CHOOSE(Dashboard!$C$4,K78,K79,K80) -> 37.009256 | L81: =CHOOSE(Dashboard!$C$4,L78,L79,L80) -> 37.762227 | M81: =CHOOSE(Dashboard!$C$4,M78,M79,M80) -> 37.415339 | N81: =CHOOSE(Dashboard!$C$4,N78,N79,N80) -> 36.881314 | ... BN81: =CHOOSE(Dashboard!$C$4,BN78,BN79,BN80) -> 0
B83: Gas engines 4×76.5 MW · merchant dynamic
B84: cf · low | G84: 0.13166507 | H84: 0.12028425 | I84: 0.10841507 | J84: 0.097596918 | K84: 0.087999658 | L84: 0.085780822 | M84: 0.083455822 | N84: 0.081757192 | O84: 0.079219863 | P84: 0.077404452 | Q84: 0.075599658 | R84: 0.074177055 | S84: 0.073104795 | T84: 0.072255479 | U84: 0.0713 | V84: 0.069665068 | W84: 0.068815753 | X84: 0.067860274 | Y84: 0.067010959 | Z84: 0.066055479 | AA84: 0.066161644 | AB84: 0.066161644 | AC84: 0.066055479 | AD84: 0.066055479 | AE84: 0.066161644
B85: cf · central | G85: 0.16886358 | H85: 0.15368094 | I85: 0.13586301 | J85: 0.12282763 | K85: 0.11224315 | L85: 0.10528082 | M85: 0.10061758 | N85: 0.096886986 | O85: 0.092006849 | P85: 0.08680137 | Q85: 0.086150685 | R85: 0.085380708 | S85: 0.085055365 | T85: 0.08440468 | U85: 0.084079338 | V85: 0.083211758 | W85: 0.082235731 | X85: 0.082018836 | Y85: 0.080717466 | Z85: 0.080500571 | AA85: 0.080500571 | AB85: 0.080609018 | AC85: 0.080934361 | AD85: 0.081476598 | AE85: 0.081585046
B86: cf · high | G86: 0.12109498 | H86: 0.10687717 | I86: 0.098251256 | J86: 0.088274429 | K86: 0.080744749 | L86: 0.080744749 | M86: 0.080634018 | N86: 0.080634018 | O86: 0.080744749 | P86: 0.08096621 | Q86: 0.082294977 | R86: 0.084520662 | S86: 0.085627968 | T86: 0.086956735 | U86: 0.089503539 | V86: 0.091718151 | W86: 0.093279452 | X86: 0.09537226 | Y86: 0.097354338 | Z86: 0.099347489 | AA86: 0.099347489 | AB86: 0.099347489 | AC86: 0.099347489 | AD86: 0.099347489 | AE86: 0.099347489
B87: cf · selected | G87: =CHOOSE(Dashboard!$C$4,G84,G85,G86) -> 0.16886358 | H87: =CHOOSE(Dashboard!$C$4,H84,H85,H86) -> 0.15368094 | I87: =CHOOSE(Dashboard!$C$4,I84,I85,I86) -> 0.13586301 | J87: =CHOOSE(Dashboard!$C$4,J84,J85,J86) -> 0.12282763 | K87: =CHOOSE(Dashboard!$C$4,K84,K85,K86) -> 0.11224315 | L87: =CHOOSE(Dashboard!$C$4,L84,L85,L86) -> 0.10528082 | M87: =CHOOSE(Dashboard!$C$4,M84,M85,M86) -> 0.10061758 | N87: =CHOOSE(Dashboard!$C$4,N84,N85,N86) -> 0.096886986 | ... BN87: =CHOOSE(Dashboard!$C$4,BN84,BN85,BN86) -> 0
B88: capture · low | G88: 1.809284 | H88: 1.8500529 | I88: 1.8979987 | J88: 1.9477414 | K88: 1.9966802 | L88: 2.0101917 | M88: 2.0242237 | N88: 2.0341824 | O88: 2.0493545 | P88: 2.0619842 | Q88: 2.0739574 | R88: 2.0837393 | S88: 2.0915868 | T88: 2.0974517 | U88: 2.104261 | V88: 2.1157689 | W88: 2.1226285 | X88: 2.1304232 | Y88: 2.1376945 | Z88: 2.1455699 | AA88: 2.1448548 | AB88: 2.1449661 | AC88: 2.1458623 | AD88: 2.145975 | AE88: 2.1454204
B89: capture · central | G89: 1.7156391 | H89: 1.7553762 | I89: 1.8082683 | J89: 1.8529043 | K89: 1.8949327 | L89: 1.9253177 | M89: 1.9467352 | N89: 1.9651123 | O89: 1.9903251 | P89: 2.0196587 | Q89: 2.0238925 | R89: 2.0287101 | S89: 2.030828 | T89: 2.0347196 | U89: 2.0369617 | V89: 2.0422201 | W89: 2.0481905 | X89: 2.0498821 | Y89: 2.0578575 | Z89: 2.0594062 | AA89: 2.0597835 | AB89: 2.0594885 | AC89: 2.0580779 | AD89: 2.0551708 | AE89: 2.0548252
B90: capture · high | G90: 1.868285 | H90: 1.9276159 | I90: 1.96776 | J90: 2.0210754 | K90: 2.0659526 | L90: 2.0662619 | M90: 2.0675672 | N90: 2.068046 | O90: 2.0679003 | P90: 2.0670954 | Q90: 2.0594257 | R90: 2.0468703 | S90: 2.0412002 | T90: 2.0345564 | U90: 2.0211259 | V90: 2.0099799 | W90: 2.002331 | X90: 1.9925523 | Y90: 1.9837443 | Z90: 1.9744187 | AA90: 1.9744187 | AB90: 1.9744187 | AC90: 1.9744187 | AD90: 1.9744187 | AE90: 1.9744187
B91: capture · selected | G91: =CHOOSE(Dashboard!$C$4,G88,G89,G90) -> 1.7156391 | H91: =CHOOSE(Dashboard!$C$4,H88,H89,H90) -> 1.7553762 | I91: =CHOOSE(Dashboard!$C$4,I88,I89,I90) -> 1.8082683 | J91: =CHOOSE(Dashboard!$C$4,J88,J89,J90) -> 1.8529043 | K91: =CHOOSE(Dashboard!$C$4,K88,K89,K90) -> 1.8949327 | L91: =CHOOSE(Dashboard!$C$4,L88,L89,L90) -> 1.9253177 | M91: =CHOOSE(Dashboard!$C$4,M88,M89,M90) -> 1.9467352 | N91: =CHOOSE(Dashboard!$C$4,N88,N89,N90) -> 1.9651123 | ... BN91: =CHOOSE(Dashboard!$C$4,BN88,BN89,BN90) -> 0
B92: heat · low | G92: 2.2187129 | H92: 2.2184765 | I92: 2.2195721 | J92: 2.219111 | K92: 2.2148516 | L92: 2.2158034 | M92: 2.215687 | N92: 2.2147062 | O92: 2.2120663 | P92: 2.2134569 | Q92: 2.2127407 | R92: 2.2114784 | S92: 2.211637 | T92: 2.2106428 | U92: 2.209773 | V92: 2.2072213 | W92: 2.2073565 | X92: 2.2074389 | Y92: 2.2084956 | Z92: 2.2088823 | AA92: 2.2090804 | AB92: 2.2090804 | AC92: 2.2087752 | AD92: 2.2087752 | AE92: 2.2089735
B93: heat · central | G93: 2.0811913 | H93: 2.0823705 | I93: 2.082704 | J93: 2.0809895 | K93: 2.0823486 | L93: 2.0817335 | M93: 2.0810161 | N93: 2.080308 | O93: 2.0801294 | P93: 2.0808171 | Q93: 2.0810409 | R93: 2.0807828 | S93: 2.0804049 | T93: 2.0794261 | U93: 2.0790654 | V93: 2.0780262 | W93: 2.0771502 | X93: 2.0769986 | Y93: 2.0764635 | Z93: 2.0761108 | AA93: 2.0761108 | AB93: 2.0761754 | AC93: 2.0767027 | AD93: 2.0768239 | AE93: 2.0766653
B94: heat · high | G94: 1.9965436 | H94: 1.9974904 | I94: 1.9965724 | J94: 1.9972692 | K94: 1.9943293 | L94: 1.9940825 | M94: 1.9943501 | N94: 1.9940481 | O94: 1.9942196 | P94: 1.9945064 | Q94: 1.9944465 | R94: 1.9956285 | S94: 1.9967078 | T94: 1.9979411 | U94: 1.9983458 | V94: 1.9983404 | W94: 1.9979382 | X94: 1.9980919 | Y94: 1.9988265 | Z94: 1.998877 | AA94: 1.998877 | AB94: 1.998877 | AC94: 1.998877 | AD94: 1.998877 | AE94: 1.998877
B95: heat · selected | G95: =CHOOSE(Dashboard!$C$4,G92,G93,G94) -> 2.0811913 | H95: =CHOOSE(Dashboard!$C$4,H92,H93,H94) -> 2.0823705 | I95: =CHOOSE(Dashboard!$C$4,I92,I93,I94) -> 2.082704 | J95: =CHOOSE(Dashboard!$C$4,J92,J93,J94) -> 2.0809895 | K95: =CHOOSE(Dashboard!$C$4,K92,K93,K94) -> 2.0823486 | L95: =CHOOSE(Dashboard!$C$4,L92,L93,L94) -> 2.0817335 | M95: =CHOOSE(Dashboard!$C$4,M92,M93,M94) -> 2.0810161 | N95: =CHOOSE(Dashboard!$C$4,N92,N93,N94) -> 2.080308 | ... BN95: =CHOOSE(Dashboard!$C$4,BN92,BN93,BN94) -> 0
B96: start · low | G96: 6.487039 | H96: 6.8098872 | I96: 7.0763523 | J96: 7.2649772 | K96: 7.3931444 | L96: 7.5162887 | M96: 7.5859388 | N96: 7.5654467 | O96: 7.6226861 | P96: 7.6895362 | Q96: 7.7193384 | R96: 7.8272937 | S96: 7.861775 | T96: 7.8726551 | U96: 7.8964133 | V96: 7.9560143 | W96: 8.012818 | X96: 8.083113 | Y96: 8.0991489 | Z96: 8.0851419 | AA96: 8.0721683 | AB96: 8.0721683 | AC96: 8.0851419 | AD96: 8.0851419 | AE96: 8.1166404
B97: start · central | G97: 6.1210922 | H97: 6.527365 | I97: 6.8908046 | J97: 7.1232516 | K97: 7.4162878 | L97: 7.6746227 | M97: 7.6674249 | N97: 7.7749814 | O97: 7.8217046 | P97: 7.9040611 | Q97: 7.9284034 | R97: 7.9635964 | S97: 7.9576122 | T97: 7.9815928 | U97: 8.0124773 | V97: 8.0591342 | W97: 8.0795824 | X97: 8.1009485 | Y97: 8.041063 | Z97: 8.0242206 | AA97: 8.0242206 | AB97: 8.0134252 | AC97: 8.0201803 | AD97: 8.0042838 | AE97: 7.9936441
B98: start · high | G98: 7.7421634 | H98: 8.2834843 | I98: 8.2782849 | J98: 8.4687353 | K98: 8.8076504 | L98: 8.7660146 | M98: 8.7780525 | N98: 8.8203649 | O98: 8.8082689 | P98: 8.7841763 | Q98: 8.7631987 | R98: 8.6118705 | S98: 8.5005053 | T98: 8.4482784 | U98: 8.3911155 | V98: 8.3676385 | W98: 8.2970936 | X98: 8.3209749 | Y98: 8.2856926 | Z98: 8.251904 | AA98: 8.251904 | AB98: 8.251904 | AC98: 8.251904 | AD98: 8.251904 | AE98: 8.251904
B99: start · selected | G99: =CHOOSE(Dashboard!$C$4,G96,G97,G98) -> 6.1210922 | H99: =CHOOSE(Dashboard!$C$4,H96,H97,H98) -> 6.527365 | I99: =CHOOSE(Dashboard!$C$4,I96,I97,I98) -> 6.8908046 | J99: =CHOOSE(Dashboard!$C$4,J96,J97,J98) -> 7.1232516 | K99: =CHOOSE(Dashboard!$C$4,K96,K97,K98) -> 7.4162878 | L99: =CHOOSE(Dashboard!$C$4,L96,L97,L98) -> 7.6746227 | M99: =CHOOSE(Dashboard!$C$4,M96,M97,M98) -> 7.6674249 | N99: =CHOOSE(Dashboard!$C$4,N96,N97,N98) -> 7.7749814 | ... BN99: =CHOOSE(Dashboard!$C$4,BN96,BN97,BN98) -> 0

Sheet Model_SMR_CfD
B1: SMR · CfD (two-way, PEJ template)
B2: Annual model, real PLN m (2026). Column D = totals / KPIs. Timeline columns G→. Dispatch quantities come from the Twin sheet (hourly digital twin).
B4: Year | G4: 2027 | H4: 2028 | I4: 2029 | J4: 2030 | K4: 2031 | L4: 2032 | M4: 2033 | N4: 2034 | O4: 2035 | P4: 2036 | Q4: 2037 | R4: 2038 | S4: 2039 | T4: 2040 | U4: 2041 | V4: 2042 | W4: 2043 | X4: 2044 | Y4: 2045 | Z4: 2046 | AA4: 2047 | AB4: 2048 | AC4: 2049 | AD4: 2050 | AE4: 2051 | AF4: 2052 | AG4: 2053 | AH4: 2054 | AI4: 2055 | AJ4: 2056 | AK4: 2057 | AL4: 2058 | AM4: 2059 | AN4: 2060 | AO4: 2061 | AP4: 2062 | AQ4: 2063 | AR4: 2064 | AS4: 2065 | AT4: 2066 | AU4: 2067 | AV4: 2068 | AW4: 2069 | AX4: 2070 | AY4: 2071 | AZ4: 2072 | BA4: 2073 | BB4: 2074 | BC4: 2075 | BD4: 2076 | BE4: 2077 | BF4: 2078 | BG4: 2079 | BH4: 2080 | BI4: 2081 | BJ4: 2082 | BK4: 2083 | BL4: 2084 | BM4: 2085 | BN4: 2086 | BO4: 2087 | BP4: 2088 | BQ4: 2089 | BR4: 2090 | BS4: 2091 | BT4: 2092 | BU4: 2093 | BV4: 2094 | BW4: 2095 | BX4: 2096
B6: 1. Parameters (links to Input, selected case)
B7: Net capacity, MW | D7: =Input!$H$52 -> 300
B8: Overnight capex, PLN/kW | D8: =Input!$H$53 -> 38000
B9: Construction years | D9: =Input!$H$54 -> 5
B10: COD year | D10: =Input!$H$55 -> 2035
B11: Life years | D11: =Input!$H$56 -> 60
B12: FID year (COD − construction) | D12: =$D$10-$D$9 -> 2030
B13: Real post-tax WACC | D13: =Input!$H$15 -> 0.05
B14: Fixed O&M, PLN/kW-yr | D14: =Input!$H$60 -> 520
B15: Variable O&M, PLN/MWh | D15: =Input!$H$66 -> 11
B16: EUR/PLN | D16: =Input!$H$10 -> 4.3633
B17: CIT rate | D17: =Input!$H$141 -> 0.19
B18: Licence fee share of revenue | D18: =Input!$H$31 -> 0.005
B19: Staff FTE | D19: =Input!$H$63 -> 180
B20: Loaded cost per FTE, k PLN | D20: =Input!$H$64 -> 290
B21: Budowle share of capex | D21: =Input!$H$69 -> 0.2
B22: Property tax rate | D22: =0.02 -> 0.02
B23: Host-gmina share of property tax | D23: =Input!$H$70 -> 0.5
B24: Overnight cost, m PLN | D24: =$D$8*$D$7*1000/1000000 -> 11400
B25: Nuclear fuel, PLN/MWh | D25: =Input!$H$65 -> 31
B26: Decommissioning fund, PLN/MWh | D26: =Input!$H$67 -> 26
B27: Sustaining capex, PLN/MWh @90 % CF | D27: =Input!$H$68 -> 25
B28: Pre-development, m PLN | D28: =Input!$H$57 -> 500
B29: First core, m PLN | D29: =Input!$H$58 -> 550
B30: Grid connection, m PLN | D30: =Input!$H$59 -> 125
B31: Single-unit FOM multiplier | D31: =Input!$H$61 -> 1.5
B32: Single-unit years | D32: =Input!$H$62 -> 3
B33: Load-following capability loss | D33: =Input!$H$71 -> 0.012
B34: Load-following FOM uplift | D34: =Input!$H$72 -> 0.01
B35: Capacity-market de-rating | D35: =Input!$H$25 -> 0.9383
B36: Peak construction workforce | D36: =Input!$H$75 -> 1500
B37: CfD strike, EUR/MWh | D37: =Input!$H$73 -> 125
B38: CfD strike, PLN/MWh | D38: =$D$37*$D$16 -> 545.4125
B39: CfD tenor, years | D39: =Input!$H$74 -> 40
B40: Capacity-market price, PLN/kW-yr | D40: =Input!$H$23 -> 0
B41: Capacity contract years | D41: =Input!$H$24 -> 17
B43: 2. Timing
B44: Construction flag | C44: 0/1 | G44: =IF(AND(G$4>=$D$12,G$4<$D$10),1,0) -> 0 | H44: =IF(AND(H$4>=$D$12,H$4<$D$10),1,0) -> 0 | I44: =IF(AND(I$4>=$D$12,I$4<$D$10),1,0) -> 0 | J44: =IF(AND(J$4>=$D$12,J$4<$D$10),1,0) -> 1 | K44: =IF(AND(K$4>=$D$12,K$4<$D$10),1,0) -> 1 | L44: =IF(AND(L$4>=$D$12,L$4<$D$10),1,0) -> 1 | M44: =IF(AND(M$4>=$D$12,M$4<$D$10),1,0) -> 1 | N44: =IF(AND(N$4>=$D$12,N$4<$D$10),1,0) -> 1 | ... BX44: =IF(AND(BX$4>=$D$12,BX$4<$D$10),1,0) -> 0
B45: Operating flag | C45: 0/1 | G45: =IF(AND(G$4>=$D$10,G$4<$D$10+$D$11),1,0) -> 0 | H45: =IF(AND(H$4>=$D$10,H$4<$D$10+$D$11),1,0) -> 0 | I45: =IF(AND(I$4>=$D$10,I$4<$D$10+$D$11),1,0) -> 0 | J45: =IF(AND(J$4>=$D$10,J$4<$D$10+$D$11),1,0) -> 0 | K45: =IF(AND(K$4>=$D$10,K$4<$D$10+$D$11),1,0) -> 0 | L45: =IF(AND(L$4>=$D$10,L$4<$D$10+$D$11),1,0) -> 0 | M45: =IF(AND(M$4>=$D$10,M$4<$D$10+$D$11),1,0) -> 0 | N45: =IF(AND(N$4>=$D$10,N$4<$D$10+$D$11),1,0) -> 0 | ... BX45: =IF(AND(BX$4>=$D$10,BX$4<$D$10+$D$11),1,0) -> 0
B46: Operating year k | C46: # | G46: =IF(G45=1,G$4-$D$10+1,0) -> 0 | H46: =IF(H45=1,H$4-$D$10+1,0) -> 0 | I46: =IF(I45=1,I$4-$D$10+1,0) -> 0 | J46: =IF(J45=1,J$4-$D$10+1,0) -> 0 | K46: =IF(K45=1,K$4-$D$10+1,0) -> 0 | L46: =IF(L45=1,L$4-$D$10+1,0) -> 0 | M46: =IF(M45=1,M$4-$D$10+1,0) -> 0 | N46: =IF(N45=1,N$4-$D$10+1,0) -> 0 | ... BX46: =IF(BX45=1,BX$4-$D$10+1,0) -> 0
B47: Discount period (years from FID) | C47: # | G47: =G$4-$D$12 -> -3 | H47: =H$4-$D$12 -> -2 | I47: =I$4-$D$12 -> -1 | J47: =J$4-$D$12 -> 0 | K47: =K$4-$D$12 -> 1 | L47: =L$4-$D$12 -> 2 | M47: =M$4-$D$12 -> 3 | N47: =N$4-$D$12 -> 4 | ... BX47: =BX$4-$D$12 -> 66
B48: Discount factor | C48: # | G48: =IF(G$4>=$D$12,1/(1+$D$13)^G47,0) -> 0 | H48: =IF(H$4>=$D$12,1/(1+$D$13)^H47,0) -> 0 | I48: =IF(I$4>=$D$12,1/(1+$D$13)^I47,0) -> 0 | J48: =IF(J$4>=$D$12,1/(1+$D$13)^J47,0) -> 1 | K48: =IF(K$4>=$D$12,1/(1+$D$13)^K47,0) -> 0.95238095 | L48: =IF(L$4>=$D$12,1/(1+$D$13)^L47,0) -> 0.90702948 | M48: =IF(M$4>=$D$12,1/(1+$D$13)^M47,0) -> 0.8638376 | N48: =IF(N$4>=$D$12,1/(1+$D$13)^N47,0) -> 0.82270247 | ... BX48: =IF(BX$4>=$D$12,1/(1+$D$13)^BX47,0) -> 0.039949032
B49: Capex spend share (S-curve, normalised) | C49: % | G49: =IF(G44=1,1+1.7*SIN(PI()*((G$4-$D$12+0.5)/$D$9))^2,0) -> 0 | H49: =IF(H44=1,1+1.7*SIN(PI()*((H$4-$D$12+0.5)/$D$9))^2,0) -> 0 | I49: =IF(I44=1,1+1.7*SIN(PI()*((I$4-$D$12+0.5)/$D$9))^2,0) -> 0 | J49: =IF(J44=1,1+1.7*SIN(PI()*((J$4-$D$12+0.5)/$D$9))^2,0) -> 1.1623356 | K49: =IF(K44=1,1+1.7*SIN(PI()*((K$4-$D$12+0.5)/$D$9))^2,0) -> 2.1126644 | L49: =IF(L44=1,1+1.7*SIN(PI()*((L$4-$D$12+0.5)/$D$9))^2,0) -> 2.7 | M49: =IF(M44=1,1+1.7*SIN(PI()*((M$4-$D$12+0.5)/$D$9))^2,0) -> 2.1126644 | N49: =IF(N44=1,1+1.7*SIN(PI()*((N$4-$D$12+0.5)/$D$9))^2,0) -> 1.1623356 | ... BX49: =IF(BX44=1,1+1.7*SIN(PI()*((BX$4-$D$12+0.5)/$D$9))^2,0) -> 0
B50: Capex spend share normalised | C50: % | G50: =IF(SUM($G49:$BX49)>0,G49/SUM($G49:$BX49),0) -> 0 | H50: =IF(SUM($G49:$BX49)>0,H49/SUM($G49:$BX49),0) -> 0 | I50: =IF(SUM($G49:$BX49)>0,I49/SUM($G49:$BX49),0) -> 0 | J50: =IF(SUM($G49:$BX49)>0,J49/SUM($G49:$BX49),0) -> 0.1256579 | K50: =IF(SUM($G49:$BX49)>0,K49/SUM($G49:$BX49),0) -> 0.22839616 | L50: =IF(SUM($G49:$BX49)>0,L49/SUM($G49:$BX49),0) -> 0.29189189 | M50: =IF(SUM($G49:$BX49)>0,M49/SUM($G49:$BX49),0) -> 0.22839616 | N50: =IF(SUM($G49:$BX49)>0,N49/SUM($G49:$BX49),0) -> 0.1256579 | ... BX50: =IF(SUM($G49:$BX49)>0,BX49/SUM($G49:$BX49),0) -> 0
B52: 3. Investment (m PLN)
B53: Overnight capex spend | C53: m PLN | D53: =SUM(G53:BX53) -> 11400 | G53: =$D$24*G50 -> 0 | H53: =$D$24*H50 -> 0 | I53: =$D$24*I50 -> 0 | J53: =$D$24*J50 -> 1432.5 | K53: =$D$24*K50 -> 2603.7162 | L53: =$D$24*L50 -> 3327.5676 | M53: =$D$24*M50 -> 2603.7162 | N53: =$D$24*N50 -> 1432.5 | ... BX53: =$D$24*BX50 -> 0
B54: Other capex (pre-development at FID, first core at COD−1, grid spread) | C54: m PLN | D54: =SUM(G54:BX54) -> 1175 | G54: =IF(G$4=$D$12,$D$28,0)+IF(G$4=$D$10-1,$D$29,0)+$D$30*G50 -> 0 | H54: =IF(H$4=$D$12,$D$28,0)+IF(H$4=$D$10-1,$D$29,0)+$D$30*H50 -> 0 | I54: =IF(I$4=$D$12,$D$28,0)+IF(I$4=$D$10-1,$D$29,0)+$D$30*I50 -> 0 | J54: =IF(J$4=$D$12,$D$28,0)+IF(J$4=$D$10-1,$D$29,0)+$D$30*J50 -> 515.70724 | K54: =IF(K$4=$D$12,$D$28,0)+IF(K$4=$D$10-1,$D$29,0)+$D$30*K50 -> 28.54952 | L54: =IF(L$4=$D$12,$D$28,0)+IF(L$4=$D$10-1,$D$29,0)+$D$30*L50 -> 36.486486 | M54: =IF(M$4=$D$12,$D$28,0)+IF(M$4=$D$10-1,$D$29,0)+$D$30*M50 -> 28.54952 | N54: =IF(N$4=$D$12,$D$28,0)+IF(N$4=$D$10-1,$D$29,0)+$D$30*N50 -> 565.70724 | ... BX54: =IF(BX$4=$D$12,$D$28,0)+IF(BX$4=$D$10-1,$D$29,0)+$D$30*BX50 -> 0
B55: Total capex | C55: m PLN | D55: =SUM(G55:BX55) -> 12575 | G55: =G53+G54 -> 0 | H55: =H53+H54 -> 0 | I55: =I53+I54 -> 0 | J55: =J53+J54 -> 1948.2073 | K55: =K53+K54 -> 2632.2657 | L55: =L53+L54 -> 3364.0541 | M55: =M53+M54 -> 2632.2657 | N55: =N53+N54 -> 1998.2073 | ... BX55: =BX53+BX54 -> 0
B57: 4. Market inputs (selected case, from Input)
B58: Annual mean day-ahead price | C58: PLN/MWh | G58: =Input!J36 -> 496 | H58: =Input!K36 -> 445 | I58: =Input!L36 -> 420 | J58: =Input!M36 -> 410 | K58: =Input!N36 -> 408 | L58: =Input!O36 -> 406 | M58: =Input!P36 -> 404 | N58: =Input!Q36 -> 402 | ... BX58: =Input!CA36 -> 380
B60: 5. Dispatch (from hourly twin) and revenue
B61: Capacity factor (twin) | C61: % | G61: =IF(G45=1,IFERROR(INDEX(Twin!$G$9:$BN$9,1,G46),0),0) -> 0 | H61: =IF(H45=1,IFERROR(INDEX(Twin!$G$9:$BN$9,1,H46),0),0) -> 0 | I61: =IF(I45=1,IFERROR(INDEX(Twin!$G$9:$BN$9,1,I46),0),0) -> 0 | J61: =IF(J45=1,IFERROR(INDEX(Twin!$G$9:$BN$9,1,J46),0),0) -> 0 | K61: =IF(K45=1,IFERROR(INDEX(Twin!$G$9:$BN$9,1,K46),0),0) -> 0 | L61: =IF(L45=1,IFERROR(INDEX(Twin!$G$9:$BN$9,1,L46),0),0) -> 0 | M61: =IF(M45=1,IFERROR(INDEX(Twin!$G$9:$BN$9,1,M46),0),0) -> 0 | N61: =IF(N45=1,IFERROR(INDEX(Twin!$G$9:$BN$9,1,N46),0),0) -> 0 | ... BX61: =IF(BX45=1,IFERROR(INDEX(Twin!$G$9:$BN$9,1,BX46),0),0) -> 0
B62: Net generation (twin CF already net of load-following capability loss) | C62: MWh | D62: =SUM(G62:BX62) -> 1.4376959e+08 | G62: =G61*$D$7*8760 -> 0 | H62: =H61*$D$7*8760 -> 0 | I62: =I61*$D$7*8760 -> 0 | J62: =J61*$D$7*8760 -> 0 | K62: =K61*$D$7*8760 -> 0 | L62: =L61*$D$7*8760 -> 0 | M62: =M61*$D$7*8760 -> 0 | N62: =N61*$D$7*8760 -> 0 | ... BX62: =BX61*$D$7*8760 -> 0
B63: Capture price = mean × capture ratio (twin) | C63: PLN/MWh | G63: =IF(G45=1,G58*IFERROR(INDEX(Twin!$G$13:$BN$13,1,G46),0),0) -> 0 | H63: =IF(H45=1,H58*IFERROR(INDEX(Twin!$G$13:$BN$13,1,H46),0),0) -> 0 | I63: =IF(I45=1,I58*IFERROR(INDEX(Twin!$G$13:$BN$13,1,I46),0),0) -> 0 | J63: =IF(J45=1,J58*IFERROR(INDEX(Twin!$G$13:$BN$13,1,J46),0),0) -> 0 | K63: =IF(K45=1,K58*IFERROR(INDEX(Twin!$G$13:$BN$13,1,K46),0),0) -> 0 | L63: =IF(L45=1,L58*IFERROR(INDEX(Twin!$G$13:$BN$13,1,L46),0),0) -> 0 | M63: =IF(M45=1,M58*IFERROR(INDEX(Twin!$G$13:$BN$13,1,M46),0),0) -> 0 | N63: =IF(N45=1,N58*IFERROR(INDEX(Twin!$G$13:$BN$13,1,N46),0),0) -> 0 | ... BX63: =IF(BX45=1,BX58*IFERROR(INDEX(Twin!$G$13:$BN$13,1,BX46),0),0) -> 0
B64: Market revenue | C64: m PLN | D64: =SUM(G64:BX64) -> 55699.941 | G64: =G62*G63/1000000 -> 0 | H64: =H62*H63/1000000 -> 0 | I64: =I62*I63/1000000 -> 0 | J64: =J62*J63/1000000 -> 0 | K64: =K62*K63/1000000 -> 0 | L64: =L62*L63/1000000 -> 0 | M64: =M62*M63/1000000 -> 0 | N64: =N62*N63/1000000 -> 0 | ... BX64: =BX62*BX63/1000000 -> 0
B65: CfD reference price (daily TGeBase, generation-weighted; twin) | C65: PLN/MWh | G65: =IF(AND(G45=1,G46<=$D$39),G58*IFERROR(INDEX(Twin!$G$17:$BN$17,1,G46),0),0) -> 0 | H65: =IF(AND(H45=1,H46<=$D$39),H58*IFERROR(INDEX(Twin!$G$17:$BN$17,1,H46),0),0) -> 0 | I65: =IF(AND(I45=1,I46<=$D$39),I58*IFERROR(INDEX(Twin!$G$17:$BN$17,1,I46),0),0) -> 0 | J65: =IF(AND(J45=1,J46<=$D$39),J58*IFERROR(INDEX(Twin!$G$17:$BN$17,1,J46),0),0) -> 0 | K65: =IF(AND(K45=1,K46<=$D$39),K58*IFERROR(INDEX(Twin!$G$17:$BN$17,1,K46),0),0) -> 0 | L65: =IF(AND(L45=1,L46<=$D$39),L58*IFERROR(INDEX(Twin!$G$17:$BN$17,1,L46),0),0) -> 0 | M65: =IF(AND(M45=1,M46<=$D$39),M58*IFERROR(INDEX(Twin!$G$17:$BN$17,1,M46),0),0) -> 0 | N65: =IF(AND(N45=1,N46<=$D$39),N58*IFERROR(INDEX(Twin!$G$17:$BN$17,1,N46),0),0) -> 0 | ... BX65: =IF(AND(BX45=1,BX46<=$D$39),BX58*IFERROR(INDEX(Twin!$G$17:$BN$17,1,BX46),0),0) -> 0
B66: CfD difference payment (+ top-up / − pay-back) | C66: m PLN | D66: =SUM(G66:BX66) -> 15881.983 | G66: =IF(AND(G45=1,G46<=$D$39),G62*($D$38-G65)/1000000,0) -> 0 | H66: =IF(AND(H45=1,H46<=$D$39),H62*($D$38-H65)/1000000,0) -> 0 | I66: =IF(AND(I45=1,I46<=$D$39),I62*($D$38-I65)/1000000,0) -> 0 | J66: =IF(AND(J45=1,J46<=$D$39),J62*($D$38-J65)/1000000,0) -> 0 | K66: =IF(AND(K45=1,K46<=$D$39),K62*($D$38-K65)/1000000,0) -> 0 | L66: =IF(AND(L45=1,L46<=$D$39),L62*($D$38-L65)/1000000,0) -> 0 | M66: =IF(AND(M45=1,M46<=$D$39),M62*($D$38-M65)/1000000,0) -> 0 | N66: =IF(AND(N45=1,N46<=$D$39),N62*($D$38-N65)/1000000,0) -> 0 | ... BX66: =IF(AND(BX45=1,BX46<=$D$39),BX62*($D$38-BX65)/1000000,0) -> 0
B67: Capacity-market revenue | C67: m PLN | D67: =SUM(G67:BX67) -> 0 | G67: =IF(AND(G45=1,G46<=$D$41),$D$40*$D$35*$D$7*1000/1000000,0) -> 0 | H67: =IF(AND(H45=1,H46<=$D$41),$D$40*$D$35*$D$7*1000/1000000,0) -> 0 | I67: =IF(AND(I45=1,I46<=$D$41),$D$40*$D$35*$D$7*1000/1000000,0) -> 0 | J67: =IF(AND(J45=1,J46<=$D$41),$D$40*$D$35*$D$7*1000/1000000,0) -> 0 | K67: =IF(AND(K45=1,K46<=$D$41),$D$40*$D$35*$D$7*1000/1000000,0) -> 0 | L67: =IF(AND(L45=1,L46<=$D$41),$D$40*$D$35*$D$7*1000/1000000,0) -> 0 | M67: =IF(AND(M45=1,M46<=$D$41),$D$40*$D$35*$D$7*1000/1000000,0) -> 0 | N67: =IF(AND(N45=1,N46<=$D$41),$D$40*$D$35*$D$7*1000/1000000,0) -> 0 | ... BX67: =IF(AND(BX45=1,BX46<=$D$41),$D$40*$D$35*$D$7*1000/1000000,0) -> 0
B68: Balancing-services revenue | C68: m PLN | D68: =SUM(G68:BX68) -> 0 | G68: =0 -> 0 | H68: =0 -> 0 | I68: =0 -> 0 | J68: =0 -> 0 | K68: =0 -> 0 | L68: =0 -> 0 | M68: =0 -> 0 | N68: =0 -> 0 | ... BX68: =0 -> 0
B69: Total revenue | C69: m PLN | D69: =SUM(G69:BX69) -> 71581.924 | G69: =G64+G66+G67+G68 -> 0 | H69: =H64+H66+H67+H68 -> 0 | I69: =I64+I66+I67+I68 -> 0 | J69: =J64+J66+J67+J68 -> 0 | K69: =K64+K66+K67+K68 -> 0 | L69: =L64+L66+L67+L68 -> 0 | M69: =M64+M66+M67+M68 -> 0 | N69: =N64+N66+N67+N68 -> 0 | ... BX69: =BX64+BX66+BX67+BX68 -> 0
B71: 6. Operating costs (m PLN)
B72: Nuclear fuel (incl. part-load efficiency effect, twin ratio) | C72: m PLN | D72: =SUM(G72:BX72) -> 4460.2223 | G72: =G62*$D$25*IF(G45=1,IFERROR(INDEX(Twin!$G$21:$BN$21,1,G46),0),0)/1000000 -> 0 | H72: =H62*$D$25*IF(H45=1,IFERROR(INDEX(Twin!$G$21:$BN$21,1,H46),0),0)/1000000 -> 0 | I72: =I62*$D$25*IF(I45=1,IFERROR(INDEX(Twin!$G$21:$BN$21,1,I46),0),0)/1000000 -> 0 | J72: =J62*$D$25*IF(J45=1,IFERROR(INDEX(Twin!$G$21:$BN$21,1,J46),0),0)/1000000 -> 0 | K72: =K62*$D$25*IF(K45=1,IFERROR(INDEX(Twin!$G$21:$BN$21,1,K46),0),0)/1000000 -> 0 | L72: =L62*$D$25*IF(L45=1,IFERROR(INDEX(Twin!$G$21:$BN$21,1,L46),0),0)/1000000 -> 0 | M72: =M62*$D$25*IF(M45=1,IFERROR(INDEX(Twin!$G$21:$BN$21,1,M46),0),0)/1000000 -> 0 | N72: =N62*$D$25*IF(N45=1,IFERROR(INDEX(Twin!$G$21:$BN$21,1,N46),0),0)/1000000 -> 0 | ... BX72: =BX62*$D$25*IF(BX45=1,IFERROR(INDEX(Twin!$G$21:$BN$21,1,BX46),0),0)/1000000 -> 0
B73: CO2 cost | C73: m PLN | D73: =SUM(G73:BX73) -> 0 | G73: =0 -> 0 | H73: =0 -> 0 | I73: =0 -> 0 | J73: =0 -> 0 | K73: =0 -> 0 | L73: =0 -> 0 | M73: =0 -> 0 | N73: =0 -> 0 | ... BX73: =0 -> 0
B74: Variable O&M | C74: m PLN | D74: =SUM(G74:BX74) -> 1581.4655 | G74: =G62*$D$15/1000000 -> 0 | H74: =H62*$D$15/1000000 -> 0 | I74: =I62*$D$15/1000000 -> 0 | J74: =J62*$D$15/1000000 -> 0 | K74: =K62*$D$15/1000000 -> 0 | L74: =L62*$D$15/1000000 -> 0 | M74: =M62*$D$15/1000000 -> 0 | N74: =N62*$D$15/1000000 -> 0 | ... BX74: =BX62*$D$15/1000000 -> 0
B75: Start-up / cycling cost | C75: m PLN | D75: =SUM(G75:BX75) -> 0 | G75: =0 -> 0 | H75: =0 -> 0 | I75: =0 -> 0 | J75: =0 -> 0 | K75: =0 -> 0 | L75: =0 -> 0 | M75: =0 -> 0 | N75: =0 -> 0 | ... BX75: =0 -> 0
B76: Decommissioning & waste fund | C76: m PLN | D76: =SUM(G76:BX76) -> 3738.0094 | G76: =G62*$D$26/1000000 -> 0 | H76: =H62*$D$26/1000000 -> 0 | I76: =I62*$D$26/1000000 -> 0 | J76: =J62*$D$26/1000000 -> 0 | K76: =K62*$D$26/1000000 -> 0 | L76: =L62*$D$26/1000000 -> 0 | M76: =M62*$D$26/1000000 -> 0 | N76: =N62*$D$26/1000000 -> 0 | ... BX76: =BX62*$D$26/1000000 -> 0
B77: Fixed O&M (× single-unit multiplier, × load-following uplift) | C77: m PLN | D77: =SUM(G77:BX77) -> 9689.94 | G77: =IF(G45=1,$D$14*$D$7*1000/1000000*IF(G46<=$D$32,$D$31,1)*(1+$D$34),0) -> 0 | H77: =IF(H45=1,$D$14*$D$7*1000/1000000*IF(H46<=$D$32,$D$31,1)*(1+$D$34),0) -> 0 | I77: =IF(I45=1,$D$14*$D$7*1000/1000000*IF(I46<=$D$32,$D$31,1)*(1+$D$34),0) -> 0 | J77: =IF(J45=1,$D$14*$D$7*1000/1000000*IF(J46<=$D$32,$D$31,1)*(1+$D$34),0) -> 0 | K77: =IF(K45=1,$D$14*$D$7*1000/1000000*IF(K46<=$D$32,$D$31,1)*(1+$D$34),0) -> 0 | L77: =IF(L45=1,$D$14*$D$7*1000/1000000*IF(L46<=$D$32,$D$31,1)*(1+$D$34),0) -> 0 | M77: =IF(M45=1,$D$14*$D$7*1000/1000000*IF(M46<=$D$32,$D$31,1)*(1+$D$34),0) -> 0 | N77: =IF(N45=1,$D$14*$D$7*1000/1000000*IF(N46<=$D$32,$D$31,1)*(1+$D$34),0) -> 0 | ... BX77: =IF(BX45=1,$D$14*$D$7*1000/1000000*IF(BX46<=$D$32,$D$31,1)*(1+$D$34),0) -> 0
B78: memo: staff cost inside fixed O&M | C78: m PLN | D78: =SUM(G78:BX78) -> 3132 | G78: =IF(G45=1,$D$19*$D$20/1000,0) -> 0 | H78: =IF(H45=1,$D$19*$D$20/1000,0) -> 0 | I78: =IF(I45=1,$D$19*$D$20/1000,0) -> 0 | J78: =IF(J45=1,$D$19*$D$20/1000,0) -> 0 | K78: =IF(K45=1,$D$19*$D$20/1000,0) -> 0 | L78: =IF(L45=1,$D$19*$D$20/1000,0) -> 0 | M78: =IF(M45=1,$D$19*$D$20/1000,0) -> 0 | N78: =IF(N45=1,$D$19*$D$20/1000,0) -> 0 | ... BX78: =IF(BX45=1,$D$19*$D$20/1000,0) -> 0
B79: Sustaining capex | C79: m PLN | D79: =SUM(G79:BX79) -> 3547.8 | G79: =IF(G45=1,$D$27*$D$7*8760*0.9/1000000,0) -> 0 | H79: =IF(H45=1,$D$27*$D$7*8760*0.9/1000000,0) -> 0 | I79: =IF(I45=1,$D$27*$D$7*8760*0.9/1000000,0) -> 0 | J79: =IF(J45=1,$D$27*$D$7*8760*0.9/1000000,0) -> 0 | K79: =IF(K45=1,$D$27*$D$7*8760*0.9/1000000,0) -> 0 | L79: =IF(L45=1,$D$27*$D$7*8760*0.9/1000000,0) -> 0 | M79: =IF(M45=1,$D$27*$D$7*8760*0.9/1000000,0) -> 0 | N79: =IF(N45=1,$D$27*$D$7*8760*0.9/1000000,0) -> 0 | ... BX79: =IF(BX45=1,$D$27*$D$7*8760*0.9/1000000,0) -> 0
B80: Gas capacity booking | C80: m PLN | D80: =SUM(G80:BX80) -> 0 | G80: =0 -> 0 | H80: =0 -> 0 | I80: =0 -> 0 | J80: =0 -> 0 | K80: =0 -> 0 | L80: =0 -> 0 | M80: =0 -> 0 | N80: =0 -> 0 | ... BX80: =0 -> 0
B81: Property tax (2 % of budowle value) | C81: m PLN | D81: =SUM(G81:BX81) -> 2736 | G81: =IF(G45=1,$D$22*$D$21*$D$24,0) -> 0 | H81: =IF(H45=1,$D$22*$D$21*$D$24,0) -> 0 | I81: =IF(I45=1,$D$22*$D$21*$D$24,0) -> 0 | J81: =IF(J45=1,$D$22*$D$21*$D$24,0) -> 0 | K81: =IF(K45=1,$D$22*$D$21*$D$24,0) -> 0 | L81: =IF(L45=1,$D$22*$D$21*$D$24,0) -> 0 | M81: =IF(M45=1,$D$22*$D$21*$D$24,0) -> 0 | N81: =IF(N45=1,$D$22*$D$21*$D$24,0) -> 0 | ... BX81: =IF(BX45=1,$D$22*$D$21*$D$24,0) -> 0
B82: URE licence fee | C82: m PLN | D82: =SUM(G82:BX82) -> 357.90962 | G82: =IF(G45=1,$D$18*MAX(G69,0),0) -> 0 | H82: =IF(H45=1,$D$18*MAX(H69,0),0) -> 0 | I82: =IF(I45=1,$D$18*MAX(I69,0),0) -> 0 | J82: =IF(J45=1,$D$18*MAX(J69,0),0) -> 0 | K82: =IF(K45=1,$D$18*MAX(K69,0),0) -> 0 | L82: =IF(L45=1,$D$18*MAX(L69,0),0) -> 0 | M82: =IF(M45=1,$D$18*MAX(M69,0),0) -> 0 | N82: =IF(N45=1,$D$18*MAX(N69,0),0) -> 0 | ... BX82: =IF(BX45=1,$D$18*MAX(BX69,0),0) -> 0
B83: Total opex | C83: m PLN | D83: =SUM(G83:BX83) -> 26111.347 | G83: =G72+G73+G74+G75+G76+G77+G79+G80+G81+G82 -> 0 | H83: =H72+H73+H74+H75+H76+H77+H79+H80+H81+H82 -> 0 | I83: =I72+I73+I74+I75+I76+I77+I79+I80+I81+I82 -> 0 | J83: =J72+J73+J74+J75+J76+J77+J79+J80+J81+J82 -> 0 | K83: =K72+K73+K74+K75+K76+K77+K79+K80+K81+K82 -> 0 | L83: =L72+L73+L74+L75+L76+L77+L79+L80+L81+L82 -> 0 | M83: =M72+M73+M74+M75+M76+M77+M79+M80+M81+M82 -> 0 | N83: =N72+N73+N74+N75+N76+N77+N79+N80+N81+N82 -> 0 | ... BX83: =BX72+BX73+BX74+BX75+BX76+BX77+BX79+BX80+BX81+BX82 -> 0
B84: EBITDA | C84: m PLN | D84: =SUM(G84:BX84) -> 45470.578 | G84: =G69-G83 -> 0 | H84: =H69-H83 -> 0 | I84: =I69-I83 -> 0 | J84: =J69-J83 -> 0 | K84: =K69-K83 -> 0 | L84: =L69-L83 -> 0 | M84: =M69-M83 -> 0 | N84: =N69-N83 -> 0 | ... BX84: =BX69-BX83 -> 0
B85: End-of-life provision (nuclear: covered by fund) | C85: m PLN | D85: =SUM(G85:BX85) -> 0 | G85: =0 -> 0 | H85: =0 -> 0 | I85: =0 -> 0 | J85: =0 -> 0 | K85: =0 -> 0 | L85: =0 -> 0 | M85: =0 -> 0 | N85: =0 -> 0 | ... BX85: =0 -> 0
B87: 7. Tax (Polish CIT, straight-line KŚT depreciation, loss carry-forward)
B88: Depreciation — KŚT group (b) | C88: m PLN | D88: =SUM(G88:BX88) -> 2515 | G88: =IF(AND(G45=1,G46<=ROUNDUP(1/Input!$H$142,0)),MIN($D$55*Input!$H$76*Input!$H$142,MAX($D$55*Input!$H$76-$D$55*Input!$H$76*Input!$H$142*(G46-1),0)),0) -> 0 | H88: =IF(AND(H45=1,H46<=ROUNDUP(1/Input!$H$142,0)),MIN($D$55*Input!$H$76*Input!$H$142,MAX($D$55*Input!$H$76-$D$55*Input!$H$76*Input!$H$142*(H46-1),0)),0) -> 0 | I88: =IF(AND(I45=1,I46<=ROUNDUP(1/Input!$H$142,0)),MIN($D$55*Input!$H$76*Input!$H$142,MAX($D$55*Input!$H$76-$D$55*Input!$H$76*Input!$H$142*(I46-1),0)),0) -> 0 | J88: =IF(AND(J45=1,J46<=ROUNDUP(1/Input!$H$142,0)),MIN($D$55*Input!$H$76*Input!$H$142,MAX($D$55*Input!$H$76-$D$55*Input!$H$76*Input!$H$142*(J46-1),0)),0) -> 0 | K88: =IF(AND(K45=1,K46<=ROUNDUP(1/Input!$H$142,0)),MIN($D$55*Input!$H$76*Input!$H$142,MAX($D$55*Input!$H$76-$D$55*Input!$H$76*Input!$H$142*(K46-1),0)),0) -> 0 | L88: =IF(AND(L45=1,L46<=ROUNDUP(1/Input!$H$142,0)),MIN($D$55*Input!$H$76*Input!$H$142,MAX($D$55*Input!$H$76-$D$55*Input!$H$76*Input!$H$142*(L46-1),0)),0) -> 0 | M88: =IF(AND(M45=1,M46<=ROUNDUP(1/Input!$H$142,0)),MIN($D$55*Input!$H$76*Input!$H$142,MAX($D$55*Input!$H$76-$D$55*Input!$H$76*Input!$H$142*(M46-1),0)),0) -> 0 | N88: =IF(AND(N45=1,N46<=ROUNDUP(1/Input!$H$142,0)),MIN($D$55*Input!$H$76*Input!$H$142,MAX($D$55*Input!$H$76-$D$55*Input!$H$76*Input!$H$142*(N46-1),0)),0) -> 0 | ... BX88: =IF(AND(BX45=1,BX46<=ROUNDUP(1/Input!$H$142,0)),MIN($D$55*Input!$H$76*Input!$H$142,MAX($D$55*Input!$H$76-$D$55*Input!$H$76*Input!$H$142*(BX46-1),0)),0) -> 0
B89: Depreciation — KŚT group (s) | C89: m PLN | D89: =SUM(G89:BX89) -> 1886.25 | G89: =IF(AND(G45=1,G46<=ROUNDUP(1/Input!$H$143,0)),MIN($D$55*Input!$H$77*Input!$H$143,MAX($D$55*Input!$H$77-$D$55*Input!$H$77*Input!$H$143*(G46-1),0)),0) -> 0 | H89: =IF(AND(H45=1,H46<=ROUNDUP(1/Input!$H$143,0)),MIN($D$55*Input!$H$77*Input!$H$143,MAX($D$55*Input!$H$77-$D$55*Input!$H$77*Input!$H$143*(H46-1),0)),0) -> 0 | I89: =IF(AND(I45=1,I46<=ROUNDUP(1/Input!$H$143,0)),MIN($D$55*Input!$H$77*Input!$H$143,MAX($D$55*Input!$H$77-$D$55*Input!$H$77*Input!$H$143*(I46-1),0)),0) -> 0 | J89: =IF(AND(J45=1,J46<=ROUNDUP(1/Input!$H$143,0)),MIN($D$55*Input!$H$77*Input!$H$143,MAX($D$55*Input!$H$77-$D$55*Input!$H$77*Input!$H$143*(J46-1),0)),0) -> 0 | K89: =IF(AND(K45=1,K46<=ROUNDUP(1/Input!$H$143,0)),MIN($D$55*Input!$H$77*Input!$H$143,MAX($D$55*Input!$H$77-$D$55*Input!$H$77*Input!$H$143*(K46-1),0)),0) -> 0 | L89: =IF(AND(L45=1,L46<=ROUNDUP(1/Input!$H$143,0)),MIN($D$55*Input!$H$77*Input!$H$143,MAX($D$55*Input!$H$77-$D$55*Input!$H$77*Input!$H$143*(L46-1),0)),0) -> 0 | M89: =IF(AND(M45=1,M46<=ROUNDUP(1/Input!$H$143,0)),MIN($D$55*Input!$H$77*Input!$H$143,MAX($D$55*Input!$H$77-$D$55*Input!$H$77*Input!$H$143*(M46-1),0)),0) -> 0 | N89: =IF(AND(N45=1,N46<=ROUNDUP(1/Input!$H$143,0)),MIN($D$55*Input!$H$77*Input!$H$143,MAX($D$55*Input!$H$77-$D$55*Input!$H$77*Input!$H$143*(N46-1),0)),0) -> 0 | ... BX89: =IF(AND(BX45=1,BX46<=ROUNDUP(1/Input!$H$143,0)),MIN($D$55*Input!$H$77*Input!$H$143,MAX($D$55*Input!$H$77-$D$55*Input!$H$77*Input!$H$143*(BX46-1),0)),0) -> 0
B90: Depreciation — KŚT group (r) | C90: m PLN | D90: =SUM(G90:BX90) -> 3143.75 | G90: =IF(AND(G45=1,G46<=ROUNDUP(1/Input!$H$144,0)),MIN($D$55*Input!$H$78*Input!$H$144,MAX($D$55*Input!$H$78-$D$55*Input!$H$78*Input!$H$144*(G46-1),0)),0) -> 0 | H90: =IF(AND(H45=1,H46<=ROUNDUP(1/Input!$H$144,0)),MIN($D$55*Input!$H$78*Input!$H$144,MAX($D$55*Input!$H$78-$D$55*Input!$H$78*Input!$H$144*(H46-1),0)),0) -> 0 | I90: =IF(AND(I45=1,I46<=ROUNDUP(1/Input!$H$144,0)),MIN($D$55*Input!$H$78*Input!$H$144,MAX($D$55*Input!$H$78-$D$55*Input!$H$78*Input!$H$144*(I46-1),0)),0) -> 0 | J90: =IF(AND(J45=1,J46<=ROUNDUP(1/Input!$H$144,0)),MIN($D$55*Input!$H$78*Input!$H$144,MAX($D$55*Input!$H$78-$D$55*Input!$H$78*Input!$H$144*(J46-1),0)),0) -> 0 | K90: =IF(AND(K45=1,K46<=ROUNDUP(1/Input!$H$144,0)),MIN($D$55*Input!$H$78*Input!$H$144,MAX($D$55*Input!$H$78-$D$55*Input!$H$78*Input!$H$144*(K46-1),0)),0) -> 0 | L90: =IF(AND(L45=1,L46<=ROUNDUP(1/Input!$H$144,0)),MIN($D$55*Input!$H$78*Input!$H$144,MAX($D$55*Input!$H$78-$D$55*Input!$H$78*Input!$H$144*(L46-1),0)),0) -> 0 | M90: =IF(AND(M45=1,M46<=ROUNDUP(1/Input!$H$144,0)),MIN($D$55*Input!$H$78*Input!$H$144,MAX($D$55*Input!$H$78-$D$55*Input!$H$78*Input!$H$144*(M46-1),0)),0) -> 0 | N90: =IF(AND(N45=1,N46<=ROUNDUP(1/Input!$H$144,0)),MIN($D$55*Input!$H$78*Input!$H$144,MAX($D$55*Input!$H$78-$D$55*Input!$H$78*Input!$H$144*(N46-1),0)),0) -> 0 | ... BX90: =IF(AND(BX45=1,BX46<=ROUNDUP(1/Input!$H$144,0)),MIN($D$55*Input!$H$78*Input!$H$144,MAX($D$55*Input!$H$78-$D$55*Input!$H$78*Input!$H$144*(BX46-1),0)),0) -> 0
B91: Depreciation — KŚT group (t) | C91: m PLN | D91: =SUM(G91:BX91) -> 3772.5 | G91: =IF(AND(G45=1,G46<=ROUNDUP(1/Input!$H$145,0)),MIN($D$55*Input!$H$79*Input!$H$145,MAX($D$55*Input!$H$79-$D$55*Input!$H$79*Input!$H$145*(G46-1),0)),0) -> 0 | H91: =IF(AND(H45=1,H46<=ROUNDUP(1/Input!$H$145,0)),MIN($D$55*Input!$H$79*Input!$H$145,MAX($D$55*Input!$H$79-$D$55*Input!$H$79*Input!$H$145*(H46-1),0)),0) -> 0 | I91: =IF(AND(I45=1,I46<=ROUNDUP(1/Input!$H$145,0)),MIN($D$55*Input!$H$79*Input!$H$145,MAX($D$55*Input!$H$79-$D$55*Input!$H$79*Input!$H$145*(I46-1),0)),0) -> 0 | J91: =IF(AND(J45=1,J46<=ROUNDUP(1/Input!$H$145,0)),MIN($D$55*Input!$H$79*Input!$H$145,MAX($D$55*Input!$H$79-$D$55*Input!$H$79*Input!$H$145*(J46-1),0)),0) -> 0 | K91: =IF(AND(K45=1,K46<=ROUNDUP(1/Input!$H$145,0)),MIN($D$55*Input!$H$79*Input!$H$145,MAX($D$55*Input!$H$79-$D$55*Input!$H$79*Input!$H$145*(K46-1),0)),0) -> 0 | L91: =IF(AND(L45=1,L46<=ROUNDUP(1/Input!$H$145,0)),MIN($D$55*Input!$H$79*Input!$H$145,MAX($D$55*Input!$H$79-$D$55*Input!$H$79*Input!$H$145*(L46-1),0)),0) -> 0 | M91: =IF(AND(M45=1,M46<=ROUNDUP(1/Input!$H$145,0)),MIN($D$55*Input!$H$79*Input!$H$145,MAX($D$55*Input!$H$79-$D$55*Input!$H$79*Input!$H$145*(M46-1),0)),0) -> 0 | N91: =IF(AND(N45=1,N46<=ROUNDUP(1/Input!$H$145,0)),MIN($D$55*Input!$H$79*Input!$H$145,MAX($D$55*Input!$H$79-$D$55*Input!$H$79*Input!$H$145*(N46-1),0)),0) -> 0 | ... BX91: =IF(AND(BX45=1,BX46<=ROUNDUP(1/Input!$H$145,0)),MIN($D$55*Input!$H$79*Input!$H$145,MAX($D$55*Input!$H$79-$D$55*Input!$H$79*Input!$H$145*(BX46-1),0)),0) -> 0
B92: Depreciation — KŚT group (d) | C92: m PLN | D92: =SUM(G92:BX92) -> 1257.5 | G92: =IF(AND(G45=1,G46<=ROUNDUP(1/Input!$H$146,0)),MIN($D$55*Input!$H$80*Input!$H$146,MAX($D$55*Input!$H$80-$D$55*Input!$H$80*Input!$H$146*(G46-1),0)),0) -> 0 | H92: =IF(AND(H45=1,H46<=ROUNDUP(1/Input!$H$146,0)),MIN($D$55*Input!$H$80*Input!$H$146,MAX($D$55*Input!$H$80-$D$55*Input!$H$80*Input!$H$146*(H46-1),0)),0) -> 0 | I92: =IF(AND(I45=1,I46<=ROUNDUP(1/Input!$H$146,0)),MIN($D$55*Input!$H$80*Input!$H$146,MAX($D$55*Input!$H$80-$D$55*Input!$H$80*Input!$H$146*(I46-1),0)),0) -> 0 | J92: =IF(AND(J45=1,J46<=ROUNDUP(1/Input!$H$146,0)),MIN($D$55*Input!$H$80*Input!$H$146,MAX($D$55*Input!$H$80-$D$55*Input!$H$80*Input!$H$146*(J46-1),0)),0) -> 0 | K92: =IF(AND(K45=1,K46<=ROUNDUP(1/Input!$H$146,0)),MIN($D$55*Input!$H$80*Input!$H$146,MAX($D$55*Input!$H$80-$D$55*Input!$H$80*Input!$H$146*(K46-1),0)),0) -> 0 | L92: =IF(AND(L45=1,L46<=ROUNDUP(1/Input!$H$146,0)),MIN($D$55*Input!$H$80*Input!$H$146,MAX($D$55*Input!$H$80-$D$55*Input!$H$80*Input!$H$146*(L46-1),0)),0) -> 0 | M92: =IF(AND(M45=1,M46<=ROUNDUP(1/Input!$H$146,0)),MIN($D$55*Input!$H$80*Input!$H$146,MAX($D$55*Input!$H$80-$D$55*Input!$H$80*Input!$H$146*(M46-1),0)),0) -> 0 | N92: =IF(AND(N45=1,N46<=ROUNDUP(1/Input!$H$146,0)),MIN($D$55*Input!$H$80*Input!$H$146,MAX($D$55*Input!$H$80-$D$55*Input!$H$80*Input!$H$146*(N46-1),0)),0) -> 0 | ... BX92: =IF(AND(BX45=1,BX46<=ROUNDUP(1/Input!$H$146,0)),MIN($D$55*Input!$H$80*Input!$H$146,MAX($D$55*Input!$H$80-$D$55*Input!$H$80*Input!$H$146*(BX46-1),0)),0) -> 0
B93: Total tax depreciation | C93: m PLN | D93: =SUM(G93:BX93) -> 12575 | G93: =G88+G89+G90+G91+G92 -> 0 | H93: =H88+H89+H90+H91+H92 -> 0 | I93: =I88+I89+I90+I91+I92 -> 0 | J93: =J88+J89+J90+J91+J92 -> 0 | K93: =K88+K89+K90+K91+K92 -> 0 | L93: =L88+L89+L90+L91+L92 -> 0 | M93: =M88+M89+M90+M91+M92 -> 0 | N93: =N88+N89+N90+N91+N92 -> 0 | ... BX93: =BX88+BX89+BX90+BX91+BX92 -> 0
B94: Taxable EBIT (EBITDA − depreciation − provisions) | C94: m PLN | D94: =SUM(G94:BX94) -> 32895.578 | G94: =G84-G93-G85 -> 0 | H94: =H84-H93-H85 -> 0 | I94: =I84-I93-I85 -> 0 | J94: =J84-J93-J85 -> 0 | K94: =K84-K93-K85 -> 0 | L94: =L84-L93-L85 -> 0 | M94: =M84-M93-M85 -> 0 | N94: =N84-N93-N85 -> 0 | ... BX94: =BX84-BX93-BX85 -> 0
B95: Loss utilisation (50 % cap per year, simplified pool) | C95: m PLN | G95: =0 -> 0 | H95: =IF(H94>0,MIN(G96,0.5*H94),0) -> 0 | I95: =IF(I94>0,MIN(H96,0.5*I94),0) -> 0 | J95: =IF(J94>0,MIN(I96,0.5*J94),0) -> 0 | K95: =IF(K94>0,MIN(J96,0.5*K94),0) -> 0 | L95: =IF(L94>0,MIN(K96,0.5*L94),0) -> 0 | M95: =IF(M94>0,MIN(L96,0.5*M94),0) -> 0 | N95: =IF(N94>0,MIN(M96,0.5*N94),0) -> 0 | O95: =IF(O94>0,MIN(N96,0.5*O94),0) -> 0 | ... BX95: =IF(BX94>0,MIN(BW96,0.5*BX94),0) -> 0
B96: Loss pool carried forward (EoY) | C96: m PLN | G96: =MAX(-G94,0) -> 0 | H96: =MAX(G96-H95+MAX(-H94,0),0) -> 0 | I96: =MAX(H96-I95+MAX(-I94,0),0) -> 0 | J96: =MAX(I96-J95+MAX(-J94,0),0) -> 0 | K96: =MAX(J96-K95+MAX(-K94,0),0) -> 0 | L96: =MAX(K96-L95+MAX(-L94,0),0) -> 0 | M96: =MAX(L96-M95+MAX(-M94,0),0) -> 0 | N96: =MAX(M96-N95+MAX(-N94,0),0) -> 0 | O96: =MAX(N96-O95+MAX(-O94,0),0) -> 158.94936 | ... BX96: =MAX(BW96-BX95+MAX(-BX94,0),0) -> 0
B97: Taxable income | C97: m PLN | D97: =SUM(G97:BX97) -> 32895.578 | G97: =MAX(G94-G95,0) -> 0 | H97: =MAX(H94-H95,0) -> 0 | I97: =MAX(I94-I95,0) -> 0 | J97: =MAX(J94-J95,0) -> 0 | K97: =MAX(K94-K95,0) -> 0 | L97: =MAX(L94-L95,0) -> 0 | M97: =MAX(M94-M95,0) -> 0 | N97: =MAX(N94-N95,0) -> 0 | ... BX97: =MAX(BX94-BX95,0) -> 0
B98: CIT | C98: m PLN | D98: =SUM(G98:BX98) -> 6250.1597 | G98: =G97*$D$17 -> 0 | H98: =H97*$D$17 -> 0 | I98: =I97*$D$17 -> 0 | J98: =J97*$D$17 -> 0 | K98: =K97*$D$17 -> 0 | L98: =L97*$D$17 -> 0 | M98: =M97*$D$17 -> 0 | N98: =N97*$D$17 -> 0 | ... BX98: =BX97*$D$17 -> 0
B100: 8. Cash flow and valuation (m PLN)
B101: Pre-tax free cash flow | C101: m PLN | D101: =SUM(G101:BX101) -> 32895.578 | G101: =G84-G55-G85 -> 0 | H101: =H84-H55-H85 -> 0 | I101: =I84-I55-I85 -> 0 | J101: =J84-J55-J85 -> -1948.2073 | K101: =K84-K55-K85 -> -2632.2657 | L101: =L84-L55-L85 -> -3364.0541 | M101: =M84-M55-M85 -> -2632.2657 | N101: =N84-N55-N85 -> -1998.2073 | ... BX101: =BX84-BX55-BX85 -> 0
B102: Post-tax free cash flow (unlevered) | C102: m PLN | D102: =SUM(G102:BX102) -> 26645.418 | G102: =G101-G98 -> 0 | H102: =H101-H98 -> 0 | I102: =I101-I98 -> 0 | J102: =J101-J98 -> -1948.2073 | K102: =K101-K98 -> -2632.2657 | L102: =L101-L98 -> -3364.0541 | M102: =M101-M98 -> -2632.2657 | N102: =N101-N98 -> -1998.2073 | ... BX102: =BX101-BX98 -> 0
B103: Cumulative post-tax FCF | C103: m PLN | G103: =G102 -> 0 | H103: =G103+H102 -> 0 | I103: =H103+I102 -> 0 | J103: =I103+J102 -> -1948.2073 | K103: =J103+K102 -> -4580.473 | L103: =K103+L102 -> -7944.527 | M103: =L103+M102 -> -10576.793 | N103: =M103+N102 -> -12575 | O103: =N103+O102 -> -11756.243 | ... BX103: =BW103+BX102 -> 26645.418
B104: Discounted post-tax FCF | C104: m PLN | D104: =SUM(G104:BX104) -> 501.54656 | G104: =G102*G48 -> 0 | H104: =H102*H48 -> 0 | I104: =I102*I48 -> 0 | J104: =J102*J48 -> -1948.2073 | K104: =K102*K48 -> -2506.9197 | L104: =L102*L48 -> -3051.2962 | M104: =M102*M48 -> -2273.8501 | N104: =N102*N48 -> -1643.9301 | ... BX104: =BX102*BX48 -> 0
B105: NPV post-tax @ WACC (m PLN) | D105: =SUMPRODUCT($G$102:$BX$102,$G$48:$BX$48) -> 501.54656
B106: NPV pre-tax @ WACC (m PLN) | D106: =SUMPRODUCT($G$101:$BX$101,$G$48:$BX$48) -> 1715.4249
B107: IRR post-tax (real) | D107: =IFERROR(IRR(OFFSET(G102,0,$D$12-2027,1,$D$11+$D$9),0.05),"n/a") -> 0.052593
B108: PV of generation (MWh) | D108: =SUMPRODUCT($G$62:$BX$62,$G$48:$BX$48) -> 37590927
B109: PV of all costs (capex + opex + provisions) | D109: =SUMPRODUCT($G$55:$BX$55,$G$48:$BX$48)+SUMPRODUCT($G$83:$BX$83,$G$48:$BX$48)+SUMPRODUCT($G$85:$BX$85,$G$48:$BX$48) -> 18342.235
...

Sheet Model_SMR_Fixed
B1: SMR · fixed price = last-12-month average spot
B2: Annual model, real PLN m (2026). Column D = totals / KPIs. Timeline columns G→. Dispatch quantities come from the Twin sheet (hourly digital twin).
B4: Year | G4: 2027 | H4: 2028 | I4: 2029 | J4: 2030 | K4: 2031 | L4: 2032 | M4: 2033 | N4: 2034 | O4: 2035 | P4: 2036 | Q4: 2037 | R4: 2038 | S4: 2039 | T4: 2040 | U4: 2041 | V4: 2042 | W4: 2043 | X4: 2044 | Y4: 2045 | Z4: 2046 | AA4: 2047 | AB4: 2048 | AC4: 2049 | AD4: 2050 | AE4: 2051 | AF4: 2052 | AG4: 2053 | AH4: 2054 | AI4: 2055 | AJ4: 2056 | AK4: 2057 | AL4: 2058 | AM4: 2059 | AN4: 2060 | AO4: 2061 | AP4: 2062 | AQ4: 2063 | AR4: 2064 | AS4: 2065 | AT4: 2066 | AU4: 2067 | AV4: 2068 | AW4: 2069 | AX4: 2070 | AY4: 2071 | AZ4: 2072 | BA4: 2073 | BB4: 2074 | BC4: 2075 | BD4: 2076 | BE4: 2077 | BF4: 2078 | BG4: 2079 | BH4: 2080 | BI4: 2081 | BJ4: 2082 | BK4: 2083 | BL4: 2084 | BM4: 2085 | BN4: 2086 | BO4: 2087 | BP4: 2088 | BQ4: 2089 | BR4: 2090 | BS4: 2091 | BT4: 2092 | BU4: 2093 | BV4: 2094 | BW4: 2095 | BX4: 2096
B6: 1. Parameters (links to Input, selected case)
B7: Net capacity, MW | D7: =Input!$H$52 -> 300
B8: Overnight capex, PLN/kW | D8: =Input!$H$53 -> 38000
B9: Construction years | D9: =Input!$H$54 -> 5
B10: COD year | D10: =Input!$H$55 -> 2035
B11: Life years | D11: =Input!$H$56 -> 60
B12: FID year (COD − construction) | D12: =$D$10-$D$9 -> 2030
B13: Real post-tax WACC | D13: =Input!$H$15 -> 0.05
B14: Fixed O&M, PLN/kW-yr | D14: =Input!$H$60 -> 520
B15: Variable O&M, PLN/MWh | D15: =Input!$H$66 -> 11
B16: EUR/PLN | D16: =Input!$H$10 -> 4.3633
B17: CIT rate | D17: =Input!$H$141 -> 0.19
B18: Licence fee share of revenue | D18: =Input!$H$31 -> 0.005
B19: Staff FTE | D19: =Input!$H$63 -> 180
B20: Loaded cost per FTE, k PLN | D20: =Input!$H$64 -> 290
B21: Budowle share of capex | D21: =Input!$H$69 -> 0.2
B22: Property tax rate | D22: =0.02 -> 0.02
B23: Host-gmina share of property tax | D23: =Input!$H$70 -> 0.5
B24: Overnight cost, m PLN | D24: =$D$8*$D$7*1000/1000000 -> 11400
B25: Nuclear fuel, PLN/MWh | D25: =Input!$H$65 -> 31
B26: Decommissioning fund, PLN/MWh | D26: =Input!$H$67 -> 26
B27: Sustaining capex, PLN/MWh @90 % CF | D27: =Input!$H$68 -> 25
B28: Pre-development, m PLN | D28: =Input!$H$57 -> 500
B29: First core, m PLN | D29: =Input!$H$58 -> 550
B30: Grid connection, m PLN | D30: =Input!$H$59 -> 125
B31: Single-unit FOM multiplier | D31: =Input!$H$61 -> 1.5
B32: Single-unit years | D32: =Input!$H$62 -> 3
B33: Load-following capability loss | D33: =Input!$H$71 -> 0.012
B34: Load-following FOM uplift | D34: =Input!$H$72 -> 0.01
B35: Capacity-market de-rating | D35: =Input!$H$25 -> 0.9383
B36: Peak construction workforce | D36: =Input!$H$75 -> 1500
B37: Fixed price, PLN/MWh | D37: =Input!$H$22 -> 483.39
B38: Capacity-market price, PLN/kW-yr | D38: =Input!$H$23 -> 0
B39: Capacity contract years | D39: =Input!$H$24 -> 17
B41: 2. Timing
B42: Construction flag | C42: 0/1 | G42: =IF(AND(G$4>=$D$12,G$4<$D$10),1,0) -> 0 | H42: =IF(AND(H$4>=$D$12,H$4<$D$10),1,0) -> 0 | I42: =IF(AND(I$4>=$D$12,I$4<$D$10),1,0) -> 0 | J42: =IF(AND(J$4>=$D$12,J$4<$D$10),1,0) -> 1 | K42: =IF(AND(K$4>=$D$12,K$4<$D$10),1,0) -> 1 | L42: =IF(AND(L$4>=$D$12,L$4<$D$10),1,0) -> 1 | M42: =IF(AND(M$4>=$D$12,M$4<$D$10),1,0) -> 1 | N42: =IF(AND(N$4>=$D$12,N$4<$D$10),1,0) -> 1 | ... BX42: =IF(AND(BX$4>=$D$12,BX$4<$D$10),1,0) -> 0
B43: Operating flag | C43: 0/1 | G43: =IF(AND(G$4>=$D$10,G$4<$D$10+$D$11),1,0) -> 0 | H43: =IF(AND(H$4>=$D$10,H$4<$D$10+$D$11),1,0) -> 0 | I43: =IF(AND(I$4>=$D$10,I$4<$D$10+$D$11),1,0) -> 0 | J43: =IF(AND(J$4>=$D$10,J$4<$D$10+$D$11),1,0) -> 0 | K43: =IF(AND(K$4>=$D$10,K$4<$D$10+$D$11),1,0) -> 0 | L43: =IF(AND(L$4>=$D$10,L$4<$D$10+$D$11),1,0) -> 0 | M43: =IF(AND(M$4>=$D$10,M$4<$D$10+$D$11),1,0) -> 0 | N43: =IF(AND(N$4>=$D$10,N$4<$D$10+$D$11),1,0) -> 0 | ... BX43: =IF(AND(BX$4>=$D$10,BX$4<$D$10+$D$11),1,0) -> 0
B44: Operating year k | C44: # | G44: =IF(G43=1,G$4-$D$10+1,0) -> 0 | H44: =IF(H43=1,H$4-$D$10+1,0) -> 0 | I44: =IF(I43=1,I$4-$D$10+1,0) -> 0 | J44: =IF(J43=1,J$4-$D$10+1,0) -> 0 | K44: =IF(K43=1,K$4-$D$10+1,0) -> 0 | L44: =IF(L43=1,L$4-$D$10+1,0) -> 0 | M44: =IF(M43=1,M$4-$D$10+1,0) -> 0 | N44: =IF(N43=1,N$4-$D$10+1,0) -> 0 | ... BX44: =IF(BX43=1,BX$4-$D$10+1,0) -> 0
B45: Discount period (years from FID) | C45: # | G45: =G$4-$D$12 -> -3 | H45: =H$4-$D$12 -> -2 | I45: =I$4-$D$12 -> -1 | J45: =J$4-$D$12 -> 0 | K45: =K$4-$D$12 -> 1 | L45: =L$4-$D$12 -> 2 | M45: =M$4-$D$12 -> 3 | N45: =N$4-$D$12 -> 4 | ... BX45: =BX$4-$D$12 -> 66
B46: Discount factor | C46: # | G46: =IF(G$4>=$D$12,1/(1+$D$13)^G45,0) -> 0 | H46: =IF(H$4>=$D$12,1/(1+$D$13)^H45,0) -> 0 | I46: =IF(I$4>=$D$12,1/(1+$D$13)^I45,0) -> 0 | J46: =IF(J$4>=$D$12,1/(1+$D$13)^J45,0) -> 1 | K46: =IF(K$4>=$D$12,1/(1+$D$13)^K45,0) -> 0.95238095 | L46: =IF(L$4>=$D$12,1/(1+$D$13)^L45,0) -> 0.90702948 | M46: =IF(M$4>=$D$12,1/(1+$D$13)^M45,0) -> 0.8638376 | N46: =IF(N$4>=$D$12,1/(1+$D$13)^N45,0) -> 0.82270247 | ... BX46: =IF(BX$4>=$D$12,1/(1+$D$13)^BX45,0) -> 0.039949032
B47: Capex spend share (S-curve, normalised) | C47: % | G47: =IF(G42=1,1+1.7*SIN(PI()*((G$4-$D$12+0.5)/$D$9))^2,0) -> 0 | H47: =IF(H42=1,1+1.7*SIN(PI()*((H$4-$D$12+0.5)/$D$9))^2,0) -> 0 | I47: =IF(I42=1,1+1.7*SIN(PI()*((I$4-$D$12+0.5)/$D$9))^2,0) -> 0 | J47: =IF(J42=1,1+1.7*SIN(PI()*((J$4-$D$12+0.5)/$D$9))^2,0) -> 1.1623356 | K47: =IF(K42=1,1+1.7*SIN(PI()*((K$4-$D$12+0.5)/$D$9))^2,0) -> 2.1126644 | L47: =IF(L42=1,1+1.7*SIN(PI()*((L$4-$D$12+0.5)/$D$9))^2,0) -> 2.7 | M47: =IF(M42=1,1+1.7*SIN(PI()*((M$4-$D$12+0.5)/$D$9))^2,0) -> 2.1126644 | N47: =IF(N42=1,1+1.7*SIN(PI()*((N$4-$D$12+0.5)/$D$9))^2,0) -> 1.1623356 | ... BX47: =IF(BX42=1,1+1.7*SIN(PI()*((BX$4-$D$12+0.5)/$D$9))^2,0) -> 0
B48: Capex spend share normalised | C48: % | G48: =IF(SUM($G47:$BX47)>0,G47/SUM($G47:$BX47),0) -> 0 | H48: =IF(SUM($G47:$BX47)>0,H47/SUM($G47:$BX47),0) -> 0 | I48: =IF(SUM($G47:$BX47)>0,I47/SUM($G47:$BX47),0) -> 0 | J48: =IF(SUM($G47:$BX47)>0,J47/SUM($G47:$BX47),0) -> 0.1256579 | K48: =IF(SUM($G47:$BX47)>0,K47/SUM($G47:$BX47),0) -> 0.22839616 | L48: =IF(SUM($G47:$BX47)>0,L47/SUM($G47:$BX47),0) -> 0.29189189 | M48: =IF(SUM($G47:$BX47)>0,M47/SUM($G47:$BX47),0) -> 0.22839616 | N48: =IF(SUM($G47:$BX47)>0,N47/SUM($G47:$BX47),0) -> 0.1256579 | ... BX48: =IF(SUM($G47:$BX47)>0,BX47/SUM($G47:$BX47),0) -> 0
B50: 3. Investment (m PLN)
B51: Overnight capex spend | C51: m PLN | D51: =SUM(G51:BX51) -> 11400 | G51: =$D$24*G48 -> 0 | H51: =$D$24*H48 -> 0 | I51: =$D$24*I48 -> 0 | J51: =$D$24*J48 -> 1432.5 | K51: =$D$24*K48 -> 2603.7162 | L51: =$D$24*L48 -> 3327.5676 | M51: =$D$24*M48 -> 2603.7162 | N51: =$D$24*N48 -> 1432.5 | ... BX51: =$D$24*BX48 -> 0
B52: Other capex (pre-development at FID, first core at COD−1, grid spread) | C52: m PLN | D52: =SUM(G52:BX52) -> 1175 | G52: =IF(G$4=$D$12,$D$28,0)+IF(G$4=$D$10-1,$D$29,0)+$D$30*G48 -> 0 | H52: =IF(H$4=$D$12,$D$28,0)+IF(H$4=$D$10-1,$D$29,0)+$D$30*H48 -> 0 | I52: =IF(I$4=$D$12,$D$28,0)+IF(I$4=$D$10-1,$D$29,0)+$D$30*I48 -> 0 | J52: =IF(J$4=$D$12,$D$28,0)+IF(J$4=$D$10-1,$D$29,0)+$D$30*J48 -> 515.70724 | K52: =IF(K$4=$D$12,$D$28,0)+IF(K$4=$D$10-1,$D$29,0)+$D$30*K48 -> 28.54952 | L52: =IF(L$4=$D$12,$D$28,0)+IF(L$4=$D$10-1,$D$29,0)+$D$30*L48 -> 36.486486 | M52: =IF(M$4=$D$12,$D$28,0)+IF(M$4=$D$10-1,$D$29,0)+$D$30*M48 -> 28.54952 | N52: =IF(N$4=$D$12,$D$28,0)+IF(N$4=$D$10-1,$D$29,0)+$D$30*N48 -> 565.70724 | ... BX52: =IF(BX$4=$D$12,$D$28,0)+IF(BX$4=$D$10-1,$D$29,0)+$D$30*BX48 -> 0
B53: Total capex | C53: m PLN | D53: =SUM(G53:BX53) -> 12575 | G53: =G51+G52 -> 0 | H53: =H51+H52 -> 0 | I53: =I51+I52 -> 0 | J53: =J51+J52 -> 1948.2073 | K53: =K51+K52 -> 2632.2657 | L53: =L51+L52 -> 3364.0541 | M53: =M51+M52 -> 2632.2657 | N53: =N51+N52 -> 1998.2073 | ... BX53: =BX51+BX52 -> 0
B55: 4. Market inputs (selected case, from Input)
B56: Annual mean day-ahead price | C56: PLN/MWh | G56: =Input!J36 -> 496 | H56: =Input!K36 -> 445 | I56: =Input!L36 -> 420 | J56: =Input!M36 -> 410 | K56: =Input!N36 -> 408 | L56: =Input!O36 -> 406 | M56: =Input!P36 -> 404 | N56: =Input!Q36 -> 402 | ... BX56: =Input!CA36 -> 380
B58: 5. Dispatch (from hourly twin) and revenue
B59: Capacity factor (twin) | C59: % | G59: =IF(G43=1,IFERROR(INDEX(Twin!$G$27:$BN$27,1,G44),0),0) -> 0 | H59: =IF(H43=1,IFERROR(INDEX(Twin!$G$27:$BN$27,1,H44),0),0) -> 0 | I59: =IF(I43=1,IFERROR(INDEX(Twin!$G$27:$BN$27,1,I44),0),0) -> 0 | J59: =IF(J43=1,IFERROR(INDEX(Twin!$G$27:$BN$27,1,J44),0),0) -> 0 | K59: =IF(K43=1,IFERROR(INDEX(Twin!$G$27:$BN$27,1,K44),0),0) -> 0 | L59: =IF(L43=1,IFERROR(INDEX(Twin!$G$27:$BN$27,1,L44),0),0) -> 0 | M59: =IF(M43=1,IFERROR(INDEX(Twin!$G$27:$BN$27,1,M44),0),0) -> 0 | N59: =IF(N43=1,IFERROR(INDEX(Twin!$G$27:$BN$27,1,N44),0),0) -> 0 | ... BX59: =IF(BX43=1,IFERROR(INDEX(Twin!$G$27:$BN$27,1,BX44),0),0) -> 0
B60: Net generation | C60: MWh | D60: =SUM(G60:BX60) -> 147760920 | G60: =G59*$D$7*8760 -> 0 | H60: =H59*$D$7*8760 -> 0 | I60: =I59*$D$7*8760 -> 0 | J60: =J59*$D$7*8760 -> 0 | K60: =K59*$D$7*8760 -> 0 | L60: =L59*$D$7*8760 -> 0 | M60: =M59*$D$7*8760 -> 0 | N60: =N59*$D$7*8760 -> 0 | ... BX60: =BX59*$D$7*8760 -> 0
B61: Realised price | C61: PLN/MWh | G61: =IF(G43=1,$D$37,0) -> 0 | H61: =IF(H43=1,$D$37,0) -> 0 | I61: =IF(I43=1,$D$37,0) -> 0 | J61: =IF(J43=1,$D$37,0) -> 0 | K61: =IF(K43=1,$D$37,0) -> 0 | L61: =IF(L43=1,$D$37,0) -> 0 | M61: =IF(M43=1,$D$37,0) -> 0 | N61: =IF(N43=1,$D$37,0) -> 0 | ... BX61: =IF(BX43=1,$D$37,0) -> 0
B62: Market revenue | C62: m PLN | D62: =SUM(G62:BX62) -> 71426.151 | G62: =G60*G61/1000000 -> 0 | H62: =H60*H61/1000000 -> 0 | I62: =I60*I61/1000000 -> 0 | J62: =J60*J61/1000000 -> 0 | K62: =K60*K61/1000000 -> 0 | L62: =L60*L61/1000000 -> 0 | M62: =M60*M61/1000000 -> 0 | N62: =N60*N61/1000000 -> 0 | ... BX62: =BX60*BX61/1000000 -> 0
B63: CfD difference payment | C63: m PLN | D63: =SUM(G63:BX63) -> 0 | G63: =0 -> 0 | H63: =0 -> 0 | I63: =0 -> 0 | J63: =0 -> 0 | K63: =0 -> 0 | L63: =0 -> 0 | M63: =0 -> 0 | N63: =0 -> 0 | ... BX63: =0 -> 0
B64: Capacity-market revenue | C64: m PLN | D64: =SUM(G64:BX64) -> 0 | G64: =IF(AND(G43=1,G44<=$D$39),$D$38*$D$35*$D$7*1000/1000000,0) -> 0 | H64: =IF(AND(H43=1,H44<=$D$39),$D$38*$D$35*$D$7*1000/1000000,0) -> 0 | I64: =IF(AND(I43=1,I44<=$D$39),$D$38*$D$35*$D$7*1000/1000000,0) -> 0 | J64: =IF(AND(J43=1,J44<=$D$39),$D$38*$D$35*$D$7*1000/1000000,0) -> 0 | K64: =IF(AND(K43=1,K44<=$D$39),$D$38*$D$35*$D$7*1000/1000000,0) -> 0 | L64: =IF(AND(L43=1,L44<=$D$39),$D$38*$D$35*$D$7*1000/1000000,0) -> 0 | M64: =IF(AND(M43=1,M44<=$D$39),$D$38*$D$35*$D$7*1000/1000000,0) -> 0 | N64: =IF(AND(N43=1,N44<=$D$39),$D$38*$D$35*$D$7*1000/1000000,0) -> 0 | ... BX64: =IF(AND(BX43=1,BX44<=$D$39),$D$38*$D$35*$D$7*1000/1000000,0) -> 0
B65: Balancing-services revenue | C65: m PLN | D65: =SUM(G65:BX65) -> 0 | G65: =0 -> 0 | H65: =0 -> 0 | I65: =0 -> 0 | J65: =0 -> 0 | K65: =0 -> 0 | L65: =0 -> 0 | M65: =0 -> 0 | N65: =0 -> 0 | ... BX65: =0 -> 0
B66: Total revenue | C66: m PLN | D66: =SUM(G66:BX66) -> 71426.151 | G66: =G62+G63+G64+G65 -> 0 | H66: =H62+H63+H64+H65 -> 0 | I66: =I62+I63+I64+I65 -> 0 | J66: =J62+J63+J64+J65 -> 0 | K66: =K62+K63+K64+K65 -> 0 | L66: =L62+L63+L64+L65 -> 0 | M66: =M62+M63+M64+M65 -> 0 | N66: =N62+N63+N64+N65 -> 0 | ... BX66: =BX62+BX63+BX64+BX65 -> 0
B68: 6. Operating costs (m PLN)
B69: Nuclear fuel (incl. part-load efficiency effect, twin ratio) | C69: m PLN | D69: =SUM(G69:BX69) -> 4580.5885 | G69: =G60*$D$25*IF(G43=1,IFERROR(INDEX(Twin!$G$31:$BN$31,1,G44),0),0)/1000000 -> 0 | H69: =H60*$D$25*IF(H43=1,IFERROR(INDEX(Twin!$G$31:$BN$31,1,H44),0),0)/1000000 -> 0 | I69: =I60*$D$25*IF(I43=1,IFERROR(INDEX(Twin!$G$31:$BN$31,1,I44),0),0)/1000000 -> 0 | J69: =J60*$D$25*IF(J43=1,IFERROR(INDEX(Twin!$G$31:$BN$31,1,J44),0),0)/1000000 -> 0 | K69: =K60*$D$25*IF(K43=1,IFERROR(INDEX(Twin!$G$31:$BN$31,1,K44),0),0)/1000000 -> 0 | L69: =L60*$D$25*IF(L43=1,IFERROR(INDEX(Twin!$G$31:$BN$31,1,L44),0),0)/1000000 -> 0 | M69: =M60*$D$25*IF(M43=1,IFERROR(INDEX(Twin!$G$31:$BN$31,1,M44),0),0)/1000000 -> 0 | N69: =N60*$D$25*IF(N43=1,IFERROR(INDEX(Twin!$G$31:$BN$31,1,N44),0),0)/1000000 -> 0 | ... BX69: =BX60*$D$25*IF(BX43=1,IFERROR(INDEX(Twin!$G$31:$BN$31,1,BX44),0),0)/1000000 -> 0
B70: CO2 cost | C70: m PLN | D70: =SUM(G70:BX70) -> 0 | G70: =0 -> 0 | H70: =0 -> 0 | I70: =0 -> 0 | J70: =0 -> 0 | K70: =0 -> 0 | L70: =0 -> 0 | M70: =0 -> 0 | N70: =0 -> 0 | ... BX70: =0 -> 0
B71: Variable O&M | C71: m PLN | D71: =SUM(G71:BX71) -> 1625.3701 | G71: =G60*$D$15/1000000 -> 0 | H71: =H60*$D$15/1000000 -> 0 | I71: =I60*$D$15/1000000 -> 0 | J71: =J60*$D$15/1000000 -> 0 | K71: =K60*$D$15/1000000 -> 0 | L71: =L60*$D$15/1000000 -> 0 | M71: =M60*$D$15/1000000 -> 0 | N71: =N60*$D$15/1000000 -> 0 | ... BX71: =BX60*$D$15/1000000 -> 0
B72: Start-up / cycling cost | C72: m PLN | D72: =SUM(G72:BX72) -> 0 | G72: =0 -> 0 | H72: =0 -> 0 | I72: =0 -> 0 | J72: =0 -> 0 | K72: =0 -> 0 | L72: =0 -> 0 | M72: =0 -> 0 | N72: =0 -> 0 | ... BX72: =0 -> 0
B73: Decommissioning & waste fund | C73: m PLN | D73: =SUM(G73:BX73) -> 3841.7839 | G73: =G60*$D$26/1000000 -> 0 | H73: =H60*$D$26/1000000 -> 0 | I73: =I60*$D$26/1000000 -> 0 | J73: =J60*$D$26/1000000 -> 0 | K73: =K60*$D$26/1000000 -> 0 | L73: =L60*$D$26/1000000 -> 0 | M73: =M60*$D$26/1000000 -> 0 | N73: =N60*$D$26/1000000 -> 0 | ... BX73: =BX60*$D$26/1000000 -> 0
B74: Fixed O&M (× single-unit multiplier, × load-following uplift) | C74: m PLN | D74: =SUM(G74:BX74) -> 9594 | G74: =IF(G43=1,$D$14*$D$7*1000/1000000*IF(G44<=$D$32,$D$31,1)*(1+0),0) -> 0 | H74: =IF(H43=1,$D$14*$D$7*1000/1000000*IF(H44<=$D$32,$D$31,1)*(1+0),0) -> 0 | I74: =IF(I43=1,$D$14*$D$7*1000/1000000*IF(I44<=$D$32,$D$31,1)*(1+0),0) -> 0 | J74: =IF(J43=1,$D$14*$D$7*1000/1000000*IF(J44<=$D$32,$D$31,1)*(1+0),0) -> 0 | K74: =IF(K43=1,$D$14*$D$7*1000/1000000*IF(K44<=$D$32,$D$31,1)*(1+0),0) -> 0 | L74: =IF(L43=1,$D$14*$D$7*1000/1000000*IF(L44<=$D$32,$D$31,1)*(1+0),0) -> 0 | M74: =IF(M43=1,$D$14*$D$7*1000/1000000*IF(M44<=$D$32,$D$31,1)*(1+0),0) -> 0 | N74: =IF(N43=1,$D$14*$D$7*1000/1000000*IF(N44<=$D$32,$D$31,1)*(1+0),0) -> 0 | ... BX74: =IF(BX43=1,$D$14*$D$7*1000/1000000*IF(BX44<=$D$32,$D$31,1)*(1+0),0) -> 0
B75: memo: staff cost inside fixed O&M | C75: m PLN | D75: =SUM(G75:BX75) -> 3132 | G75: =IF(G43=1,$D$19*$D$20/1000,0) -> 0 | H75: =IF(H43=1,$D$19*$D$20/1000,0) -> 0 | I75: =IF(I43=1,$D$19*$D$20/1000,0) -> 0 | J75: =IF(J43=1,$D$19*$D$20/1000,0) -> 0 | K75: =IF(K43=1,$D$19*$D$20/1000,0) -> 0 | L75: =IF(L43=1,$D$19*$D$20/1000,0) -> 0 | M75: =IF(M43=1,$D$19*$D$20/1000,0) -> 0 | N75: =IF(N43=1,$D$19*$D$20/1000,0) -> 0 | ... BX75: =IF(BX43=1,$D$19*$D$20/1000,0) -> 0
B76: Sustaining capex | C76: m PLN | D76: =SUM(G76:BX76) -> 3547.8 | G76: =IF(G43=1,$D$27*$D$7*8760*0.9/1000000,0) -> 0 | H76: =IF(H43=1,$D$27*$D$7*8760*0.9/1000000,0) -> 0 | I76: =IF(I43=1,$D$27*$D$7*8760*0.9/1000000,0) -> 0 | J76: =IF(J43=1,$D$27*$D$7*8760*0.9/1000000,0) -> 0 | K76: =IF(K43=1,$D$27*$D$7*8760*0.9/1000000,0) -> 0 | L76: =IF(L43=1,$D$27*$D$7*8760*0.9/1000000,0) -> 0 | M76: =IF(M43=1,$D$27*$D$7*8760*0.9/1000000,0) -> 0 | N76: =IF(N43=1,$D$27*$D$7*8760*0.9/1000000,0) -> 0 | ... BX76: =IF(BX43=1,$D$27*$D$7*8760*0.9/1000000,0) -> 0
B77: Gas capacity booking | C77: m PLN | D77: =SUM(G77:BX77) -> 0 | G77: =0 -> 0 | H77: =0 -> 0 | I77: =0 -> 0 | J77: =0 -> 0 | K77: =0 -> 0 | L77: =0 -> 0 | M77: =0 -> 0 | N77: =0 -> 0 | ... BX77: =0 -> 0
B78: Property tax (2 % of budowle value) | C78: m PLN | D78: =SUM(G78:BX78) -> 2736 | G78: =IF(G43=1,$D$22*$D$21*$D$24,0) -> 0 | H78: =IF(H43=1,$D$22*$D$21*$D$24,0) -> 0 | I78: =IF(I43=1,$D$22*$D$21*$D$24,0) -> 0 | J78: =IF(J43=1,$D$22*$D$21*$D$24,0) -> 0 | K78: =IF(K43=1,$D$22*$D$21*$D$24,0) -> 0 | L78: =IF(L43=1,$D$22*$D$21*$D$24,0) -> 0 | M78: =IF(M43=1,$D$22*$D$21*$D$24,0) -> 0 | N78: =IF(N43=1,$D$22*$D$21*$D$24,0) -> 0 | ... BX78: =IF(BX43=1,$D$22*$D$21*$D$24,0) -> 0
B79: URE licence fee | C79: m PLN | D79: =SUM(G79:BX79) -> 357.13076 | G79: =IF(G43=1,$D$18*MAX(G66,0),0) -> 0 | H79: =IF(H43=1,$D$18*MAX(H66,0),0) -> 0 | I79: =IF(I43=1,$D$18*MAX(I66,0),0) -> 0 | J79: =IF(J43=1,$D$18*MAX(J66,0),0) -> 0 | K79: =IF(K43=1,$D$18*MAX(K66,0),0) -> 0 | L79: =IF(L43=1,$D$18*MAX(L66,0),0) -> 0 | M79: =IF(M43=1,$D$18*MAX(M66,0),0) -> 0 | N79: =IF(N43=1,$D$18*MAX(N66,0),0) -> 0 | ... BX79: =IF(BX43=1,$D$18*MAX(BX66,0),0) -> 0
B80: Total opex | C80: m PLN | D80: =SUM(G80:BX80) -> 26282.673 | G80: =G69+G70+G71+G72+G73+G74+G76+G77+G78+G79 -> 0 | H80: =H69+H70+H71+H72+H73+H74+H76+H77+H78+H79 -> 0 | I80: =I69+I70+I71+I72+I73+I74+I76+I77+I78+I79 -> 0 | J80: =J69+J70+J71+J72+J73+J74+J76+J77+J78+J79 -> 0 | K80: =K69+K70+K71+K72+K73+K74+K76+K77+K78+K79 -> 0 | L80: =L69+L70+L71+L72+L73+L74+L76+L77+L78+L79 -> 0 | M80: =M69+M70+M71+M72+M73+M74+M76+M77+M78+M79 -> 0 | N80: =N69+N70+N71+N72+N73+N74+N76+N77+N78+N79 -> 0 | ... BX80: =BX69+BX70+BX71+BX72+BX73+BX74+BX76+BX77+BX78+BX79 -> 0
B81: EBITDA | C81: m PLN | D81: =SUM(G81:BX81) -> 45143.478 | G81: =G66-G80 -> 0 | H81: =H66-H80 -> 0 | I81: =I66-I80 -> 0 | J81: =J66-J80 -> 0 | K81: =K66-K80 -> 0 | L81: =L66-L80 -> 0 | M81: =M66-M80 -> 0 | N81: =N66-N80 -> 0 | ... BX81: =BX66-BX80 -> 0
B82: End-of-life provision (nuclear: covered by fund) | C82: m PLN | D82: =SUM(G82:BX82) -> 0 | G82: =0 -> 0 | H82: =0 -> 0 | I82: =0 -> 0 | J82: =0 -> 0 | K82: =0 -> 0 | L82: =0 -> 0 | M82: =0 -> 0 | N82: =0 -> 0 | ... BX82: =0 -> 0
B84: 7. Tax (Polish CIT, straight-line KŚT depreciation, loss carry-forward)
B85: Depreciation — KŚT group (b) | C85: m PLN | D85: =SUM(G85:BX85) -> 2515 | G85: =IF(AND(G43=1,G44<=ROUNDUP(1/Input!$H$142,0)),MIN($D$53*Input!$H$76*Input!$H$142,MAX($D$53*Input!$H$76-$D$53*Input!$H$76*Input!$H$142*(G44-1),0)),0) -> 0 | H85: =IF(AND(H43=1,H44<=ROUNDUP(1/Input!$H$142,0)),MIN($D$53*Input!$H$76*Input!$H$142,MAX($D$53*Input!$H$76-$D$53*Input!$H$76*Input!$H$142*(H44-1),0)),0) -> 0 | I85: =IF(AND(I43=1,I44<=ROUNDUP(1/Input!$H$142,0)),MIN($D$53*Input!$H$76*Input!$H$142,MAX($D$53*Input!$H$76-$D$53*Input!$H$76*Input!$H$142*(I44-1),0)),0) -> 0 | J85: =IF(AND(J43=1,J44<=ROUNDUP(1/Input!$H$142,0)),MIN($D$53*Input!$H$76*Input!$H$142,MAX($D$53*Input!$H$76-$D$53*Input!$H$76*Input!$H$142*(J44-1),0)),0) -> 0 | K85: =IF(AND(K43=1,K44<=ROUNDUP(1/Input!$H$142,0)),MIN($D$53*Input!$H$76*Input!$H$142,MAX($D$53*Input!$H$76-$D$53*Input!$H$76*Input!$H$142*(K44-1),0)),0) -> 0 | L85: =IF(AND(L43=1,L44<=ROUNDUP(1/Input!$H$142,0)),MIN($D$53*Input!$H$76*Input!$H$142,MAX($D$53*Input!$H$76-$D$53*Input!$H$76*Input!$H$142*(L44-1),0)),0) -> 0 | M85: =IF(AND(M43=1,M44<=ROUNDUP(1/Input!$H$142,0)),MIN($D$53*Input!$H$76*Input!$H$142,MAX($D$53*Input!$H$76-$D$53*Input!$H$76*Input!$H$142*(M44-1),0)),0) -> 0 | N85: =IF(AND(N43=1,N44<=ROUNDUP(1/Input!$H$142,0)),MIN($D$53*Input!$H$76*Input!$H$142,MAX($D$53*Input!$H$76-$D$53*Input!$H$76*Input!$H$142*(N44-1),0)),0) -> 0 | ... BX85: =IF(AND(BX43=1,BX44<=ROUNDUP(1/Input!$H$142,0)),MIN($D$53*Input!$H$76*Input!$H$142,MAX($D$53*Input!$H$76-$D$53*Input!$H$76*Input!$H$142*(BX44-1),0)),0) -> 0
B86: Depreciation — KŚT group (s) | C86: m PLN | D86: =SUM(G86:BX86) -> 1886.25 | G86: =IF(AND(G43=1,G44<=ROUNDUP(1/Input!$H$143,0)),MIN($D$53*Input!$H$77*Input!$H$143,MAX($D$53*Input!$H$77-$D$53*Input!$H$77*Input!$H$143*(G44-1),0)),0) -> 0 | H86: =IF(AND(H43=1,H44<=ROUNDUP(1/Input!$H$143,0)),MIN($D$53*Input!$H$77*Input!$H$143,MAX($D$53*Input!$H$77-$D$53*Input!$H$77*Input!$H$143*(H44-1),0)),0) -> 0 | I86: =IF(AND(I43=1,I44<=ROUNDUP(1/Input!$H$143,0)),MIN($D$53*Input!$H$77*Input!$H$143,MAX($D$53*Input!$H$77-$D$53*Input!$H$77*Input!$H$143*(I44-1),0)),0) -> 0 | J86: =IF(AND(J43=1,J44<=ROUNDUP(1/Input!$H$143,0)),MIN($D$53*Input!$H$77*Input!$H$143,MAX($D$53*Input!$H$77-$D$53*Input!$H$77*Input!$H$143*(J44-1),0)),0) -> 0 | K86: =IF(AND(K43=1,K44<=ROUNDUP(1/Input!$H$143,0)),MIN($D$53*Input!$H$77*Input!$H$143,MAX($D$53*Input!$H$77-$D$53*Input!$H$77*Input!$H$143*(K44-1),0)),0) -> 0 | L86: =IF(AND(L43=1,L44<=ROUNDUP(1/Input!$H$143,0)),MIN($D$53*Input!$H$77*Input!$H$143,MAX($D$53*Input!$H$77-$D$53*Input!$H$77*Input!$H$143*(L44-1),0)),0) -> 0 | M86: =IF(AND(M43=1,M44<=ROUNDUP(1/Input!$H$143,0)),MIN($D$53*Input!$H$77*Input!$H$143,MAX($D$53*Input!$H$77-$D$53*Input!$H$77*Input!$H$143*(M44-1),0)),0) -> 0 | N86: =IF(AND(N43=1,N44<=ROUNDUP(1/Input!$H$143,0)),MIN($D$53*Input!$H$77*Input!$H$143,MAX($D$53*Input!$H$77-$D$53*Input!$H$77*Input!$H$143*(N44-1),0)),0) -> 0 | ... BX86: =IF(AND(BX43=1,BX44<=ROUNDUP(1/Input!$H$143,0)),MIN($D$53*Input!$H$77*Input!$H$143,MAX($D$53*Input!$H$77-$D$53*Input!$H$77*Input!$H$143*(BX44-1),0)),0) -> 0
B87: Depreciation — KŚT group (r) | C87: m PLN | D87: =SUM(G87:BX87) -> 3143.75 | G87: =IF(AND(G43=1,G44<=ROUNDUP(1/Input!$H$144,0)),MIN($D$53*Input!$H$78*Input!$H$144,MAX($D$53*Input!$H$78-$D$53*Input!$H$78*Input!$H$144*(G44-1),0)),0) -> 0 | H87: =IF(AND(H43=1,H44<=ROUNDUP(1/Input!$H$144,0)),MIN($D$53*Input!$H$78*Input!$H$144,MAX($D$53*Input!$H$78-$D$53*Input!$H$78*Input!$H$144*(H44-1),0)),0) -> 0 | I87: =IF(AND(I43=1,I44<=ROUNDUP(1/Input!$H$144,0)),MIN($D$53*Input!$H$78*Input!$H$144,MAX($D$53*Input!$H$78-$D$53*Input!$H$78*Input!$H$144*(I44-1),0)),0) -> 0 | J87: =IF(AND(J43=1,J44<=ROUNDUP(1/Input!$H$144,0)),MIN($D$53*Input!$H$78*Input!$H$144,MAX($D$53*Input!$H$78-$D$53*Input!$H$78*Input!$H$144*(J44-1),0)),0) -> 0 | K87: =IF(AND(K43=1,K44<=ROUNDUP(1/Input!$H$144,0)),MIN($D$53*Input!$H$78*Input!$H$144,MAX($D$53*Input!$H$78-$D$53*Input!$H$78*Input!$H$144*(K44-1),0)),0) -> 0 | L87: =IF(AND(L43=1,L44<=ROUNDUP(1/Input!$H$144,0)),MIN($D$53*Input!$H$78*Input!$H$144,MAX($D$53*Input!$H$78-$D$53*Input!$H$78*Input!$H$144*(L44-1),0)),0) -> 0 | M87: =IF(AND(M43=1,M44<=ROUNDUP(1/Input!$H$144,0)),MIN($D$53*Input!$H$78*Input!$H$144,MAX($D$53*Input!$H$78-$D$53*Input!$H$78*Input!$H$144*(M44-1),0)),0) -> 0 | N87: =IF(AND(N43=1,N44<=ROUNDUP(1/Input!$H$144,0)),MIN($D$53*Input!$H$78*Input!$H$144,MAX($D$53*Input!$H$78-$D$53*Input!$H$78*Input!$H$144*(N44-1),0)),0) -> 0 | ... BX87: =IF(AND(BX43=1,BX44<=ROUNDUP(1/Input!$H$144,0)),MIN($D$53*Input!$H$78*Input!$H$144,MAX($D$53*Input!$H$78-$D$53*Input!$H$78*Input!$H$144*(BX44-1),0)),0) -> 0
B88: Depreciation — KŚT group (t) | C88: m PLN | D88: =SUM(G88:BX88) -> 3772.5 | G88: =IF(AND(G43=1,G44<=ROUNDUP(1/Input!$H$145,0)),MIN($D$53*Input!$H$79*Input!$H$145,MAX($D$53*Input!$H$79-$D$53*Input!$H$79*Input!$H$145*(G44-1),0)),0) -> 0 | H88: =IF(AND(H43=1,H44<=ROUNDUP(1/Input!$H$145,0)),MIN($D$53*Input!$H$79*Input!$H$145,MAX($D$53*Input!$H$79-$D$53*Input!$H$79*Input!$H$145*(H44-1),0)),0) -> 0 | I88: =IF(AND(I43=1,I44<=ROUNDUP(1/Input!$H$145,0)),MIN($D$53*Input!$H$79*Input!$H$145,MAX($D$53*Input!$H$79-$D$53*Input!$H$79*Input!$H$145*(I44-1),0)),0) -> 0 | J88: =IF(AND(J43=1,J44<=ROUNDUP(1/Input!$H$145,0)),MIN($D$53*Input!$H$79*Input!$H$145,MAX($D$53*Input!$H$79-$D$53*Input!$H$79*Input!$H$145*(J44-1),0)),0) -> 0 | K88: =IF(AND(K43=1,K44<=ROUNDUP(1/Input!$H$145,0)),MIN($D$53*Input!$H$79*Input!$H$145,MAX($D$53*Input!$H$79-$D$53*Input!$H$79*Input!$H$145*(K44-1),0)),0) -> 0 | L88: =IF(AND(L43=1,L44<=ROUNDUP(1/Input!$H$145,0)),MIN($D$53*Input!$H$79*Input!$H$145,MAX($D$53*Input!$H$79-$D$53*Input!$H$79*Input!$H$145*(L44-1),0)),0) -> 0 | M88: =IF(AND(M43=1,M44<=ROUNDUP(1/Input!$H$145,0)),MIN($D$53*Input!$H$79*Input!$H$145,MAX($D$53*Input!$H$79-$D$53*Input!$H$79*Input!$H$145*(M44-1),0)),0) -> 0 | N88: =IF(AND(N43=1,N44<=ROUNDUP(1/Input!$H$145,0)),MIN($D$53*Input!$H$79*Input!$H$145,MAX($D$53*Input!$H$79-$D$53*Input!$H$79*Input!$H$145*(N44-1),0)),0) -> 0 | ... BX88: =IF(AND(BX43=1,BX44<=ROUNDUP(1/Input!$H$145,0)),MIN($D$53*Input!$H$79*Input!$H$145,MAX($D$53*Input!$H$79-$D$53*Input!$H$79*Input!$H$145*(BX44-1),0)),0) -> 0
B89: Depreciation — KŚT group (d) | C89: m PLN | D89: =SUM(G89:BX89) -> 1257.5 | G89: =IF(AND(G43=1,G44<=ROUNDUP(1/Input!$H$146,0)),MIN($D$53*Input!$H$80*Input!$H$146,MAX($D$53*Input!$H$80-$D$53*Input!$H$80*Input!$H$146*(G44-1),0)),0) -> 0 | H89: =IF(AND(H43=1,H44<=ROUNDUP(1/Input!$H$146,0)),MIN($D$53*Input!$H$80*Input!$H$146,MAX($D$53*Input!$H$80-$D$53*Input!$H$80*Input!$H$146*(H44-1),0)),0) -> 0 | I89: =IF(AND(I43=1,I44<=ROUNDUP(1/Input!$H$146,0)),MIN($D$53*Input!$H$80*Input!$H$146,MAX($D$53*Input!$H$80-$D$53*Input!$H$80*Input!$H$146*(I44-1),0)),0) -> 0 | J89: =IF(AND(J43=1,J44<=ROUNDUP(1/Input!$H$146,0)),MIN($D$53*Input!$H$80*Input!$H$146,MAX($D$53*Input!$H$80-$D$53*Input!$H$80*Input!$H$146*(J44-1),0)),0) -> 0 | K89: =IF(AND(K43=1,K44<=ROUNDUP(1/Input!$H$146,0)),MIN($D$53*Input!$H$80*Input!$H$146,MAX($D$53*Input!$H$80-$D$53*Input!$H$80*Input!$H$146*(K44-1),0)),0) -> 0 | L89: =IF(AND(L43=1,L44<=ROUNDUP(1/Input!$H$146,0)),MIN($D$53*Input!$H$80*Input!$H$146,MAX($D$53*Input!$H$80-$D$53*Input!$H$80*Input!$H$146*(L44-1),0)),0) -> 0 | M89: =IF(AND(M43=1,M44<=ROUNDUP(1/Input!$H$146,0)),MIN($D$53*Input!$H$80*Input!$H$146,MAX($D$53*Input!$H$80-$D$53*Input!$H$80*Input!$H$146*(M44-1),0)),0) -> 0 | N89: =IF(AND(N43=1,N44<=ROUNDUP(1/Input!$H$146,0)),MIN($D$53*Input!$H$80*Input!$H$146,MAX($D$53*Input!$H$80-$D$53*Input!$H$80*Input!$H$146*(N44-1),0)),0) -> 0 | ... BX89: =IF(AND(BX43=1,BX44<=ROUNDUP(1/Input!$H$146,0)),MIN($D$53*Input!$H$80*Input!$H$146,MAX($D$53*Input!$H$80-$D$53*Input!$H$80*Input!$H$146*(BX44-1),0)),0) -> 0
B90: Total tax depreciation | C90: m PLN | D90: =SUM(G90:BX90) -> 12575 | G90: =G85+G86+G87+G88+G89 -> 0 | H90: =H85+H86+H87+H88+H89 -> 0 | I90: =I85+I86+I87+I88+I89 -> 0 | J90: =J85+J86+J87+J88+J89 -> 0 | K90: =K85+K86+K87+K88+K89 -> 0 | L90: =L85+L86+L87+L88+L89 -> 0 | M90: =M85+M86+M87+M88+M89 -> 0 | N90: =N85+N86+N87+N88+N89 -> 0 | ... BX90: =BX85+BX86+BX87+BX88+BX89 -> 0
B91: Taxable EBIT (EBITDA − depreciation − provisions) | C91: m PLN | D91: =SUM(G91:BX91) -> 32568.478 | G91: =G81-G90-G82 -> 0 | H91: =H81-H90-H82 -> 0 | I91: =I81-I90-I82 -> 0 | J91: =J81-J90-J82 -> 0 | K91: =K81-K90-K82 -> 0 | L91: =L81-L90-L82 -> 0 | M91: =M81-M90-M82 -> 0 | N91: =N81-N90-N82 -> 0 | ... BX91: =BX81-BX90-BX82 -> 0
B92: Loss utilisation (50 % cap per year, simplified pool) | C92: m PLN | G92: =0 -> 0 | H92: =IF(H91>0,MIN(G93,0.5*H91),0) -> 0 | I92: =IF(I91>0,MIN(H93,0.5*I91),0) -> 0 | J92: =IF(J91>0,MIN(I93,0.5*J91),0) -> 0 | K92: =IF(K91>0,MIN(J93,0.5*K91),0) -> 0 | L92: =IF(L91>0,MIN(K93,0.5*L91),0) -> 0 | M92: =IF(M91>0,MIN(L93,0.5*M91),0) -> 0 | N92: =IF(N91>0,MIN(M93,0.5*N91),0) -> 0 | O92: =IF(O91>0,MIN(N93,0.5*O91),0) -> 0 | ... BX92: =IF(BX91>0,MIN(BW93,0.5*BX91),0) -> 0
B93: Loss pool carried forward (EoY) | C93: m PLN | G93: =MAX(-G91,0) -> 0 | H93: =MAX(G93-H92+MAX(-H91,0),0) -> 0 | I93: =MAX(H93-I92+MAX(-I91,0),0) -> 0 | J93: =MAX(I93-J92+MAX(-J91,0),0) -> 0 | K93: =MAX(J93-K92+MAX(-K91,0),0) -> 0 | L93: =MAX(K93-L92+MAX(-L91,0),0) -> 0 | M93: =MAX(L93-M92+MAX(-M91,0),0) -> 0 | N93: =MAX(M93-N92+MAX(-N91,0),0) -> 0 | O93: =MAX(N93-O92+MAX(-O91,0),0) -> 296.26067 | ... BX93: =MAX(BW93-BX92+MAX(-BX91,0),0) -> 0
B94: Taxable income | C94: m PLN | D94: =SUM(G94:BX94) -> 32568.478 | G94: =MAX(G91-G92,0) -> 0 | H94: =MAX(H91-H92,0) -> 0 | I94: =MAX(I91-I92,0) -> 0 | J94: =MAX(J91-J92,0) -> 0 | K94: =MAX(K91-K92,0) -> 0 | L94: =MAX(L91-L92,0) -> 0 | M94: =MAX(M91-M92,0) -> 0 | N94: =MAX(N91-N92,0) -> 0 | ... BX94: =MAX(BX91-BX92,0) -> 0
B95: CIT | C95: m PLN | D95: =SUM(G95:BX95) -> 6188.0108 | G95: =G94*$D$17 -> 0 | H95: =H94*$D$17 -> 0 | I95: =I94*$D$17 -> 0 | J95: =J94*$D$17 -> 0 | K95: =K94*$D$17 -> 0 | L95: =L94*$D$17 -> 0 | M95: =M94*$D$17 -> 0 | N95: =N94*$D$17 -> 0 | ... BX95: =BX94*$D$17 -> 0
B97: 8. Cash flow and valuation (m PLN)
B98: Pre-tax free cash flow | C98: m PLN | D98: =SUM(G98:BX98) -> 32568.478 | G98: =G81-G53-G82 -> 0 | H98: =H81-H53-H82 -> 0 | I98: =I81-I53-I82 -> 0 | J98: =J81-J53-J82 -> -1948.2073 | K98: =K81-K53-K82 -> -2632.2657 | L98: =L81-L53-L82 -> -3364.0541 | M98: =M81-M53-M82 -> -2632.2657 | N98: =N81-N53-N82 -> -1998.2073 | ... BX98: =BX81-BX53-BX82 -> 0
B99: Post-tax free cash flow (unlevered) | C99: m PLN | D99: =SUM(G99:BX99) -> 26380.467 | G99: =G98-G95 -> 0 | H99: =H98-H95 -> 0 | I99: =I98-I95 -> 0 | J99: =J98-J95 -> -1948.2073 | K99: =K98-K95 -> -2632.2657 | L99: =L98-L95 -> -3364.0541 | M99: =M98-M95 -> -2632.2657 | N99: =N98-N95 -> -1998.2073 | ... BX99: =BX98-BX95 -> 0
B100: Cumulative post-tax FCF | C100: m PLN | G100: =G99 -> 0 | H100: =G100+H99 -> 0 | I100: =H100+I99 -> 0 | J100: =I100+J99 -> -1948.2073 | K100: =J100+K99 -> -4580.473 | L100: =K100+L99 -> -7944.527 | M100: =L100+M99 -> -10576.793 | N100: =M100+N99 -> -12575 | O100: =N100+O99 -> -11893.554 | ... BX100: =BW100+BX99 -> 26380.467
B101: Discounted post-tax FCF | C101: m PLN | D101: =SUM(G101:BX101) -> -821.15934 | G101: =G99*G46 -> 0 | H101: =H99*H46 -> 0 | I101: =I99*I46 -> 0 | J101: =J99*J46 -> -1948.2073 | K101: =K99*K46 -> -2506.9197 | L101: =L99*L46 -> -3051.2962 | M101: =M99*M46 -> -2273.8501 | N101: =N99*N46 -> -1643.9301 | ... BX101: =BX99*BX46 -> 0
B102: NPV post-tax @ WACC (m PLN) | D102: =SUMPRODUCT($G$99:$BX$99,$G$46:$BX$46) -> -821.15934
B103: NPV pre-tax @ WACC (m PLN) | D103: =SUMPRODUCT($G$98:$BX$98,$G$46:$BX$46) -> 154.44571
B104: IRR post-tax (real) | D104: =IFERROR(IRR(OFFSET(G99,0,$D$12-2027,1,$D$11+$D$9),0.05),"n/a") -> 0.045942837
B105: PV of generation (MWh) | D105: =SUMPRODUCT($G$60:$BX$60,$G$46:$BX$46) -> 38292561
B106: PV of all costs (capex + opex + provisions) | D106: =SUMPRODUCT($G$53:$BX$53,$G$46:$BX$46)+SUMPRODUCT($G$80:$BX$80,$G$46:$BX$46)+SUMPRODUCT($G$82:$BX$82,$G$46:$BX$46) -> 18355.795
B107: PV capex | D107: =SUMPRODUCT($G$53:$BX$53,$G$46:$BX$46) -> 11424.203
B108: PV fixed O&M | D108: =SUMPRODUCT($G$74:$BX$74,$G$46:$BX$46) -> 2604.168
B109: PV fuel | D109: =SUMPRODUCT($G$69:$BX$69,$G$46:$BX$46) -> 1187.0694
...

Sheet Model_SMR_Dynamic
B1: SMR · merchant, dynamic 50–100 % dispatch
B2: Annual model, real PLN m (2026). Column D = totals / KPIs. Timeline columns G→. Dispatch quantities come from the Twin sheet (hourly digital twin).
B4: Year | G4: 2027 | H4: 2028 | I4: 2029 | J4: 2030 | K4: 2031 | L4: 2032 | M4: 2033 | N4: 2034 | O4: 2035 | P4: 2036 | Q4: 2037 | R4: 2038 | S4: 2039 | T4: 2040 | U4: 2041 | V4: 2042 | W4: 2043 | X4: 2044 | Y4: 2045 | Z4: 2046 | AA4: 2047 | AB4: 2048 | AC4: 2049 | AD4: 2050 | AE4: 2051 | AF4: 2052 | AG4: 2053 | AH4: 2054 | AI4: 2055 | AJ4: 2056 | AK4: 2057 | AL4: 2058 | AM4: 2059 | AN4: 2060 | AO4: 2061 | AP4: 2062 | AQ4: 2063 | AR4: 2064 | AS4: 2065 | AT4: 2066 | AU4: 2067 | AV4: 2068 | AW4: 2069 | AX4: 2070 | AY4: 2071 | AZ4: 2072 | BA4: 2073 | BB4: 2074 | BC4: 2075 | BD4: 2076 | BE4: 2077 | BF4: 2078 | BG4: 2079 | BH4: 2080 | BI4: 2081 | BJ4: 2082 | BK4: 2083 | BL4: 2084 | BM4: 2085 | BN4: 2086 | BO4: 2087 | BP4: 2088 | BQ4: 2089 | BR4: 2090 | BS4: 2091 | BT4: 2092 | BU4: 2093 | BV4: 2094 | BW4: 2095 | BX4: 2096
B6: 1. Parameters (links to Input, selected case)
B7: Net capacity, MW | D7: =Input!$H$52 -> 300
B8: Overnight capex, PLN/kW | D8: =Input!$H$53 -> 38000
B9: Construction years | D9: =Input!$H$54 -> 5
B10: COD year | D10: =Input!$H$55 -> 2035
B11: Life years | D11: =Input!$H$56 -> 60
B12: FID year (COD − construction) | D12: =$D$10-$D$9 -> 2030
B13: Real post-tax WACC | D13: =Input!$H$16 -> 0.07
B14: Fixed O&M, PLN/kW-yr | D14: =Input!$H$60 -> 520
B15: Variable O&M, PLN/MWh | D15: =Input!$H$66 -> 11
B16: EUR/PLN | D16: =Input!$H$10 -> 4.3633
B17: CIT rate | D17: =Input!$H$141 -> 0.19
B18: Licence fee share of revenue | D18: =Input!$H$31 -> 0.005
B19: Staff FTE | D19: =Input!$H$63 -> 180
B20: Loaded cost per FTE, k PLN | D20: =Input!$H$64 -> 290
B21: Budowle share of capex | D21: =Input!$H$69 -> 0.2
B22: Property tax rate | D22: =0.02 -> 0.02
B23: Host-gmina share of property tax | D23: =Input!$H$70 -> 0.5
B24: Overnight cost, m PLN | D24: =$D$8*$D$7*1000/1000000 -> 11400
B25: Nuclear fuel, PLN/MWh | D25: =Input!$H$65 -> 31
B26: Decommissioning fund, PLN/MWh | D26: =Input!$H$67 -> 26
B27: Sustaining capex, PLN/MWh @90 % CF | D27: =Input!$H$68 -> 25
B28: Pre-development, m PLN | D28: =Input!$H$57 -> 500
B29: First core, m PLN | D29: =Input!$H$58 -> 550
B30: Grid connection, m PLN | D30: =Input!$H$59 -> 125
B31: Single-unit FOM multiplier | D31: =Input!$H$61 -> 1.5
B32: Single-unit years | D32: =Input!$H$62 -> 3
B33: Load-following capability loss | D33: =Input!$H$71 -> 0.012
B34: Load-following FOM uplift | D34: =Input!$H$72 -> 0.01
B35: Capacity-market de-rating | D35: =Input!$H$25 -> 0.9383
B36: Peak construction workforce | D36: =Input!$H$75 -> 1500
B37: Capacity-market price, PLN/kW-yr | D37: =Input!$H$23 -> 0
B38: Capacity contract years | D38: =Input!$H$24 -> 17
B40: 2. Timing
B41: Construction flag | C41: 0/1 | G41: =IF(AND(G$4>=$D$12,G$4<$D$10),1,0) -> 0 | H41: =IF(AND(H$4>=$D$12,H$4<$D$10),1,0) -> 0 | I41: =IF(AND(I$4>=$D$12,I$4<$D$10),1,0) -> 0 | J41: =IF(AND(J$4>=$D$12,J$4<$D$10),1,0) -> 1 | K41: =IF(AND(K$4>=$D$12,K$4<$D$10),1,0) -> 1 | L41: =IF(AND(L$4>=$D$12,L$4<$D$10),1,0) -> 1 | M41: =IF(AND(M$4>=$D$12,M$4<$D$10),1,0) -> 1 | N41: =IF(AND(N$4>=$D$12,N$4<$D$10),1,0) -> 1 | ... BX41: =IF(AND(BX$4>=$D$12,BX$4<$D$10),1,0) -> 0
B42: Operating flag | C42: 0/1 | G42: =IF(AND(G$4>=$D$10,G$4<$D$10+$D$11),1,0) -> 0 | H42: =IF(AND(H$4>=$D$10,H$4<$D$10+$D$11),1,0) -> 0 | I42: =IF(AND(I$4>=$D$10,I$4<$D$10+$D$11),1,0) -> 0 | J42: =IF(AND(J$4>=$D$10,J$4<$D$10+$D$11),1,0) -> 0 | K42: =IF(AND(K$4>=$D$10,K$4<$D$10+$D$11),1,0) -> 0 | L42: =IF(AND(L$4>=$D$10,L$4<$D$10+$D$11),1,0) -> 0 | M42: =IF(AND(M$4>=$D$10,M$4<$D$10+$D$11),1,0) -> 0 | N42: =IF(AND(N$4>=$D$10,N$4<$D$10+$D$11),1,0) -> 0 | ... BX42: =IF(AND(BX$4>=$D$10,BX$4<$D$10+$D$11),1,0) -> 0
B43: Operating year k | C43: # | G43: =IF(G42=1,G$4-$D$10+1,0) -> 0 | H43: =IF(H42=1,H$4-$D$10+1,0) -> 0 | I43: =IF(I42=1,I$4-$D$10+1,0) -> 0 | J43: =IF(J42=1,J$4-$D$10+1,0) -> 0 | K43: =IF(K42=1,K$4-$D$10+1,0) -> 0 | L43: =IF(L42=1,L$4-$D$10+1,0) -> 0 | M43: =IF(M42=1,M$4-$D$10+1,0) -> 0 | N43: =IF(N42=1,N$4-$D$10+1,0) -> 0 | ... BX43: =IF(BX42=1,BX$4-$D$10+1,0) -> 0
B44: Discount period (years from FID) | C44: # | G44: =G$4-$D$12 -> -3 | H44: =H$4-$D$12 -> -2 | I44: =I$4-$D$12 -> -1 | J44: =J$4-$D$12 -> 0 | K44: =K$4-$D$12 -> 1 | L44: =L$4-$D$12 -> 2 | M44: =M$4-$D$12 -> 3 | N44: =N$4-$D$12 -> 4 | ... BX44: =BX$4-$D$12 -> 66
B45: Discount factor | C45: # | G45: =IF(G$4>=$D$12,1/(1+$D$13)^G44,0) -> 0 | H45: =IF(H$4>=$D$12,1/(1+$D$13)^H44,0) -> 0 | I45: =IF(I$4>=$D$12,1/(1+$D$13)^I44,0) -> 0 | J45: =IF(J$4>=$D$12,1/(1+$D$13)^J44,0) -> 1 | K45: =IF(K$4>=$D$12,1/(1+$D$13)^K44,0) -> 0.93457944 | L45: =IF(L$4>=$D$12,1/(1+$D$13)^L44,0) -> 0.87343873 | M45: =IF(M$4>=$D$12,1/(1+$D$13)^M44,0) -> 0.81629788 | N45: =IF(N$4>=$D$12,1/(1+$D$13)^N44,0) -> 0.76289521 | ... BX45: =IF(BX$4>=$D$12,1/(1+$D$13)^BX44,0) -> 0.011499281
B46: Capex spend share (S-curve, normalised) | C46: % | G46: =IF(G41=1,1+1.7*SIN(PI()*((G$4-$D$12+0.5)/$D$9))^2,0) -> 0 | H46: =IF(H41=1,1+1.7*SIN(PI()*((H$4-$D$12+0.5)/$D$9))^2,0) -> 0 | I46: =IF(I41=1,1+1.7*SIN(PI()*((I$4-$D$12+0.5)/$D$9))^2,0) -> 0 | J46: =IF(J41=1,1+1.7*SIN(PI()*((J$4-$D$12+0.5)/$D$9))^2,0) -> 1.1623356 | K46: =IF(K41=1,1+1.7*SIN(PI()*((K$4-$D$12+0.5)/$D$9))^2,0) -> 2.1126644 | L46: =IF(L41=1,1+1.7*SIN(PI()*((L$4-$D$12+0.5)/$D$9))^2,0) -> 2.7 | M46: =IF(M41=1,1+1.7*SIN(PI()*((M$4-$D$12+0.5)/$D$9))^2,0) -> 2.1126644 | N46: =IF(N41=1,1+1.7*SIN(PI()*((N$4-$D$12+0.5)/$D$9))^2,0) -> 1.1623356 | ... BX46: =IF(BX41=1,1+1.7*SIN(PI()*((BX$4-$D$12+0.5)/$D$9))^2,0) -> 0
B47: Capex spend share normalised | C47: % | G47: =IF(SUM($G46:$BX46)>0,G46/SUM($G46:$BX46),0) -> 0 | H47: =IF(SUM($G46:$BX46)>0,H46/SUM($G46:$BX46),0) -> 0 | I47: =IF(SUM($G46:$BX46)>0,I46/SUM($G46:$BX46),0) -> 0 | J47: =IF(SUM($G46:$BX46)>0,J46/SUM($G46:$BX46),0) -> 0.1256579 | K47: =IF(SUM($G46:$BX46)>0,K46/SUM($G46:$BX46),0) -> 0.22839616 | L47: =IF(SUM($G46:$BX46)>0,L46/SUM($G46:$BX46),0) -> 0.29189189 | M47: =IF(SUM($G46:$BX46)>0,M46/SUM($G46:$BX46),0) -> 0.22839616 | N47: =IF(SUM($G46:$BX46)>0,N46/SUM($G46:$BX46),0) -> 0.1256579 | ... BX47: =IF(SUM($G46:$BX46)>0,BX46/SUM($G46:$BX46),0) -> 0
B49: 3. Investment (m PLN)
B50: Overnight capex spend | C50: m PLN | D50: =SUM(G50:BX50) -> 11400 | G50: =$D$24*G47 -> 0 | H50: =$D$24*H47 -> 0 | I50: =$D$24*I47 -> 0 | J50: =$D$24*J47 -> 1432.5 | K50: =$D$24*K47 -> 2603.7162 | L50: =$D$24*L47 -> 3327.5676 | M50: =$D$24*M47 -> 2603.7162 | N50: =$D$24*N47 -> 1432.5 | ... BX50: =$D$24*BX47 -> 0
B51: Other capex (pre-development at FID, first core at COD−1, grid spread) | C51: m PLN | D51: =SUM(G51:BX51) -> 1175 | G51: =IF(G$4=$D$12,$D$28,0)+IF(G$4=$D$10-1,$D$29,0)+$D$30*G47 -> 0 | H51: =IF(H$4=$D$12,$D$28,0)+IF(H$4=$D$10-1,$D$29,0)+$D$30*H47 -> 0 | I51: =IF(I$4=$D$12,$D$28,0)+IF(I$4=$D$10-1,$D$29,0)+$D$30*I47 -> 0 | J51: =IF(J$4=$D$12,$D$28,0)+IF(J$4=$D$10-1,$D$29,0)+$D$30*J47 -> 515.70724 | K51: =IF(K$4=$D$12,$D$28,0)+IF(K$4=$D$10-1,$D$29,0)+$D$30*K47 -> 28.54952 | L51: =IF(L$4=$D$12,$D$28,0)+IF(L$4=$D$10-1,$D$29,0)+$D$30*L47 -> 36.486486 | M51: =IF(M$4=$D$12,$D$28,0)+IF(M$4=$D$10-1,$D$29,0)+$D$30*M47 -> 28.54952 | N51: =IF(N$4=$D$12,$D$28,0)+IF(N$4=$D$10-1,$D$29,0)+$D$30*N47 -> 565.70724 | ... BX51: =IF(BX$4=$D$12,$D$28,0)+IF(BX$4=$D$10-1,$D$29,0)+$D$30*BX47 -> 0
B52: Total capex | C52: m PLN | D52: =SUM(G52:BX52) -> 12575 | G52: =G50+G51 -> 0 | H52: =H50+H51 -> 0 | I52: =I50+I51 -> 0 | J52: =J50+J51 -> 1948.2073 | K52: =K50+K51 -> 2632.2657 | L52: =L50+L51 -> 3364.0541 | M52: =M50+M51 -> 2632.2657 | N52: =N50+N51 -> 1998.2073 | ... BX52: =BX50+BX51 -> 0
B54: 4. Market inputs (selected case, from Input)
B55: Annual mean day-ahead price | C55: PLN/MWh | G55: =Input!J36 -> 496 | H55: =Input!K36 -> 445 | I55: =Input!L36 -> 420 | J55: =Input!M36 -> 410 | K55: =Input!N36 -> 408 | L55: =Input!O36 -> 406 | M55: =Input!P36 -> 404 | N55: =Input!Q36 -> 402 | ... BX55: =Input!CA36 -> 380
B57: 5. Dispatch (from hourly twin) and revenue
B58: Capacity factor (twin) | C58: % | G58: =IF(G42=1,IFERROR(INDEX(Twin!$G$37:$BN$37,1,G43),0),0) -> 0 | H58: =IF(H42=1,IFERROR(INDEX(Twin!$G$37:$BN$37,1,H43),0),0) -> 0 | I58: =IF(I42=1,IFERROR(INDEX(Twin!$G$37:$BN$37,1,I43),0),0) -> 0 | J58: =IF(J42=1,IFERROR(INDEX(Twin!$G$37:$BN$37,1,J43),0),0) -> 0 | K58: =IF(K42=1,IFERROR(INDEX(Twin!$G$37:$BN$37,1,K43),0),0) -> 0 | L58: =IF(L42=1,IFERROR(INDEX(Twin!$G$37:$BN$37,1,L43),0),0) -> 0 | M58: =IF(M42=1,IFERROR(INDEX(Twin!$G$37:$BN$37,1,M43),0),0) -> 0 | N58: =IF(N42=1,IFERROR(INDEX(Twin!$G$37:$BN$37,1,N43),0),0) -> 0 | ... BX58: =IF(BX42=1,IFERROR(INDEX(Twin!$G$37:$BN$37,1,BX43),0),0) -> 0
B59: Net generation (twin CF already net of load-following capability loss) | C59: MWh | D59: =SUM(G59:BX59) -> 1.4028671e+08 | G59: =G58*$D$7*8760 -> 0 | H59: =H58*$D$7*8760 -> 0 | I59: =I58*$D$7*8760 -> 0 | J59: =J58*$D$7*8760 -> 0 | K59: =K58*$D$7*8760 -> 0 | L59: =L58*$D$7*8760 -> 0 | M59: =M58*$D$7*8760 -> 0 | N59: =N58*$D$7*8760 -> 0 | ... BX59: =BX58*$D$7*8760 -> 0
B60: Capture price = mean × capture ratio (twin) | C60: PLN/MWh | G60: =IF(G42=1,G55*IFERROR(INDEX(Twin!$G$41:$BN$41,1,G43),0),0) -> 0 | H60: =IF(H42=1,H55*IFERROR(INDEX(Twin!$G$41:$BN$41,1,H43),0),0) -> 0 | I60: =IF(I42=1,I55*IFERROR(INDEX(Twin!$G$41:$BN$41,1,I43),0),0) -> 0 | J60: =IF(J42=1,J55*IFERROR(INDEX(Twin!$G$41:$BN$41,1,J43),0),0) -> 0 | K60: =IF(K42=1,K55*IFERROR(INDEX(Twin!$G$41:$BN$41,1,K43),0),0) -> 0 | L60: =IF(L42=1,L55*IFERROR(INDEX(Twin!$G$41:$BN$41,1,L43),0),0) -> 0 | M60: =IF(M42=1,M55*IFERROR(INDEX(Twin!$G$41:$BN$41,1,M43),0),0) -> 0 | N60: =IF(N42=1,N55*IFERROR(INDEX(Twin!$G$41:$BN$41,1,N43),0),0) -> 0 | ... BX60: =IF(BX42=1,BX55*IFERROR(INDEX(Twin!$G$41:$BN$41,1,BX43),0),0) -> 0
B61: Market revenue | C61: m PLN | D61: =SUM(G61:BX61) -> 55751.178 | G61: =G59*G60/1000000 -> 0 | H61: =H59*H60/1000000 -> 0 | I61: =I59*I60/1000000 -> 0 | J61: =J59*J60/1000000 -> 0 | K61: =K59*K60/1000000 -> 0 | L61: =L59*L60/1000000 -> 0 | M61: =M59*M60/1000000 -> 0 | N61: =N59*N60/1000000 -> 0 | ... BX61: =BX59*BX60/1000000 -> 0
B62: CfD difference payment | C62: m PLN | D62: =SUM(G62:BX62) -> 0 | G62: =0 -> 0 | H62: =0 -> 0 | I62: =0 -> 0 | J62: =0 -> 0 | K62: =0 -> 0 | L62: =0 -> 0 | M62: =0 -> 0 | N62: =0 -> 0 | ... BX62: =0 -> 0
B63: Capacity-market revenue | C63: m PLN | D63: =SUM(G63:BX63) -> 0 | G63: =IF(AND(G42=1,G43<=$D$38),$D$37*$D$35*$D$7*1000/1000000,0) -> 0 | H63: =IF(AND(H42=1,H43<=$D$38),$D$37*$D$35*$D$7*1000/1000000,0) -> 0 | I63: =IF(AND(I42=1,I43<=$D$38),$D$37*$D$35*$D$7*1000/1000000,0) -> 0 | J63: =IF(AND(J42=1,J43<=$D$38),$D$37*$D$35*$D$7*1000/1000000,0) -> 0 | K63: =IF(AND(K42=1,K43<=$D$38),$D$37*$D$35*$D$7*1000/1000000,0) -> 0 | L63: =IF(AND(L42=1,L43<=$D$38),$D$37*$D$35*$D$7*1000/1000000,0) -> 0 | M63: =IF(AND(M42=1,M43<=$D$38),$D$37*$D$35*$D$7*1000/1000000,0) -> 0 | N63: =IF(AND(N42=1,N43<=$D$38),$D$37*$D$35*$D$7*1000/1000000,0) -> 0 | ... BX63: =IF(AND(BX42=1,BX43<=$D$38),$D$37*$D$35*$D$7*1000/1000000,0) -> 0
B64: Balancing-services revenue | C64: m PLN | D64: =SUM(G64:BX64) -> 0 | G64: =0 -> 0 | H64: =0 -> 0 | I64: =0 -> 0 | J64: =0 -> 0 | K64: =0 -> 0 | L64: =0 -> 0 | M64: =0 -> 0 | N64: =0 -> 0 | ... BX64: =0 -> 0
B65: Total revenue | C65: m PLN | D65: =SUM(G65:BX65) -> 55751.178 | G65: =G61+G62+G63+G64 -> 0 | H65: =H61+H62+H63+H64 -> 0 | I65: =I61+I62+I63+I64 -> 0 | J65: =J61+J62+J63+J64 -> 0 | K65: =K61+K62+K63+K64 -> 0 | L65: =L61+L62+L63+L64 -> 0 | M65: =M61+M62+M63+M64 -> 0 | N65: =N61+N62+N63+N64 -> 0 | ... BX65: =BX61+BX62+BX63+BX64 -> 0
B67: 6. Operating costs (m PLN)
B68: Nuclear fuel (incl. part-load efficiency effect, twin ratio) | C68: m PLN | D68: =SUM(G68:BX68) -> 4357.4833 | G68: =G59*$D$25*IF(G42=1,IFERROR(INDEX(Twin!$G$45:$BN$45,1,G43),0),0)/1000000 -> 0 | H68: =H59*$D$25*IF(H42=1,IFERROR(INDEX(Twin!$G$45:$BN$45,1,H43),0),0)/1000000 -> 0 | I68: =I59*$D$25*IF(I42=1,IFERROR(INDEX(Twin!$G$45:$BN$45,1,I43),0),0)/1000000 -> 0 | J68: =J59*$D$25*IF(J42=1,IFERROR(INDEX(Twin!$G$45:$BN$45,1,J43),0),0)/1000000 -> 0 | K68: =K59*$D$25*IF(K42=1,IFERROR(INDEX(Twin!$G$45:$BN$45,1,K43),0),0)/1000000 -> 0 | L68: =L59*$D$25*IF(L42=1,IFERROR(INDEX(Twin!$G$45:$BN$45,1,L43),0),0)/1000000 -> 0 | M68: =M59*$D$25*IF(M42=1,IFERROR(INDEX(Twin!$G$45:$BN$45,1,M43),0),0)/1000000 -> 0 | N68: =N59*$D$25*IF(N42=1,IFERROR(INDEX(Twin!$G$45:$BN$45,1,N43),0),0)/1000000 -> 0 | ... BX68: =BX59*$D$25*IF(BX42=1,IFERROR(INDEX(Twin!$G$45:$BN$45,1,BX43),0),0)/1000000 -> 0
B69: CO2 cost | C69: m PLN | D69: =SUM(G69:BX69) -> 0 | G69: =0 -> 0 | H69: =0 -> 0 | I69: =0 -> 0 | J69: =0 -> 0 | K69: =0 -> 0 | L69: =0 -> 0 | M69: =0 -> 0 | N69: =0 -> 0 | ... BX69: =0 -> 0
B70: Variable O&M | C70: m PLN | D70: =SUM(G70:BX70) -> 1543.1539 | G70: =G59*$D$15/1000000 -> 0 | H70: =H59*$D$15/1000000 -> 0 | I70: =I59*$D$15/1000000 -> 0 | J70: =J59*$D$15/1000000 -> 0 | K70: =K59*$D$15/1000000 -> 0 | L70: =L59*$D$15/1000000 -> 0 | M70: =M59*$D$15/1000000 -> 0 | N70: =N59*$D$15/1000000 -> 0 | ... BX70: =BX59*$D$15/1000000 -> 0
B71: Start-up / cycling cost | C71: m PLN | D71: =SUM(G71:BX71) -> 0 | G71: =0 -> 0 | H71: =0 -> 0 | I71: =0 -> 0 | J71: =0 -> 0 | K71: =0 -> 0 | L71: =0 -> 0 | M71: =0 -> 0 | N71: =0 -> 0 | ... BX71: =0 -> 0
B72: Decommissioning & waste fund | C72: m PLN | D72: =SUM(G72:BX72) -> 3647.4546 | G72: =G59*$D$26/1000000 -> 0 | H72: =H59*$D$26/1000000 -> 0 | I72: =I59*$D$26/1000000 -> 0 | J72: =J59*$D$26/1000000 -> 0 | K72: =K59*$D$26/1000000 -> 0 | L72: =L59*$D$26/1000000 -> 0 | M72: =M59*$D$26/1000000 -> 0 | N72: =N59*$D$26/1000000 -> 0 | ... BX72: =BX59*$D$26/1000000 -> 0
B73: Fixed O&M (× single-unit multiplier, × load-following uplift) | C73: m PLN | D73: =SUM(G73:BX73) -> 9689.94 | G73: =IF(G42=1,$D$14*$D$7*1000/1000000*IF(G43<=$D$32,$D$31,1)*(1+$D$34),0) -> 0 | H73: =IF(H42=1,$D$14*$D$7*1000/1000000*IF(H43<=$D$32,$D$31,1)*(1+$D$34),0) -> 0 | I73: =IF(I42=1,$D$14*$D$7*1000/1000000*IF(I43<=$D$32,$D$31,1)*(1+$D$34),0) -> 0 | J73: =IF(J42=1,$D$14*$D$7*1000/1000000*IF(J43<=$D$32,$D$31,1)*(1+$D$34),0) -> 0 | K73: =IF(K42=1,$D$14*$D$7*1000/1000000*IF(K43<=$D$32,$D$31,1)*(1+$D$34),0) -> 0 | L73: =IF(L42=1,$D$14*$D$7*1000/1000000*IF(L43<=$D$32,$D$31,1)*(1+$D$34),0) -> 0 | M73: =IF(M42=1,$D$14*$D$7*1000/1000000*IF(M43<=$D$32,$D$31,1)*(1+$D$34),0) -> 0 | N73: =IF(N42=1,$D$14*$D$7*1000/1000000*IF(N43<=$D$32,$D$31,1)*(1+$D$34),0) -> 0 | ... BX73: =IF(BX42=1,$D$14*$D$7*1000/1000000*IF(BX43<=$D$32,$D$31,1)*(1+$D$34),0) -> 0
B74: memo: staff cost inside fixed O&M | C74: m PLN | D74: =SUM(G74:BX74) -> 3132 | G74: =IF(G42=1,$D$19*$D$20/1000,0) -> 0 | H74: =IF(H42=1,$D$19*$D$20/1000,0) -> 0 | I74: =IF(I42=1,$D$19*$D$20/1000,0) -> 0 | J74: =IF(J42=1,$D$19*$D$20/1000,0) -> 0 | K74: =IF(K42=1,$D$19*$D$20/1000,0) -> 0 | L74: =IF(L42=1,$D$19*$D$20/1000,0) -> 0 | M74: =IF(M42=1,$D$19*$D$20/1000,0) -> 0 | N74: =IF(N42=1,$D$19*$D$20/1000,0) -> 0 | ... BX74: =IF(BX42=1,$D$19*$D$20/1000,0) -> 0
B75: Sustaining capex | C75: m PLN | D75: =SUM(G75:BX75) -> 3547.8 | G75: =IF(G42=1,$D$27*$D$7*8760*0.9/1000000,0) -> 0 | H75: =IF(H42=1,$D$27*$D$7*8760*0.9/1000000,0) -> 0 | I75: =IF(I42=1,$D$27*$D$7*8760*0.9/1000000,0) -> 0 | J75: =IF(J42=1,$D$27*$D$7*8760*0.9/1000000,0) -> 0 | K75: =IF(K42=1,$D$27*$D$7*8760*0.9/1000000,0) -> 0 | L75: =IF(L42=1,$D$27*$D$7*8760*0.9/1000000,0) -> 0 | M75: =IF(M42=1,$D$27*$D$7*8760*0.9/1000000,0) -> 0 | N75: =IF(N42=1,$D$27*$D$7*8760*0.9/1000000,0) -> 0 | ... BX75: =IF(BX42=1,$D$27*$D$7*8760*0.9/1000000,0) -> 0
B76: Gas capacity booking | C76: m PLN | D76: =SUM(G76:BX76) -> 0 | G76: =0 -> 0 | H76: =0 -> 0 | I76: =0 -> 0 | J76: =0 -> 0 | K76: =0 -> 0 | L76: =0 -> 0 | M76: =0 -> 0 | N76: =0 -> 0 | ... BX76: =0 -> 0
B77: Property tax (2 % of budowle value) | C77: m PLN | D77: =SUM(G77:BX77) -> 2736 | G77: =IF(G42=1,$D$22*$D$21*$D$24,0) -> 0 | H77: =IF(H42=1,$D$22*$D$21*$D$24,0) -> 0 | I77: =IF(I42=1,$D$22*$D$21*$D$24,0) -> 0 | J77: =IF(J42=1,$D$22*$D$21*$D$24,0) -> 0 | K77: =IF(K42=1,$D$22*$D$21*$D$24,0) -> 0 | L77: =IF(L42=1,$D$22*$D$21*$D$24,0) -> 0 | M77: =IF(M42=1,$D$22*$D$21*$D$24,0) -> 0 | N77: =IF(N42=1,$D$22*$D$21*$D$24,0) -> 0 | ... BX77: =IF(BX42=1,$D$22*$D$21*$D$24,0) -> 0
B78: URE licence fee | C78: m PLN | D78: =SUM(G78:BX78) -> 278.75589 | G78: =IF(G42=1,$D$18*MAX(G65,0),0) -> 0 | H78: =IF(H42=1,$D$18*MAX(H65,0),0) -> 0 | I78: =IF(I42=1,$D$18*MAX(I65,0),0) -> 0 | J78: =IF(J42=1,$D$18*MAX(J65,0),0) -> 0 | K78: =IF(K42=1,$D$18*MAX(K65,0),0) -> 0 | L78: =IF(L42=1,$D$18*MAX(L65,0),0) -> 0 | M78: =IF(M42=1,$D$18*MAX(M65,0),0) -> 0 | N78: =IF(N42=1,$D$18*MAX(N65,0),0) -> 0 | ... BX78: =IF(BX42=1,$D$18*MAX(BX65,0),0) -> 0
B79: Total opex | C79: m PLN | D79: =SUM(G79:BX79) -> 25800.588 | G79: =G68+G69+G70+G71+G72+G73+G75+G76+G77+G78 -> 0 | H79: =H68+H69+H70+H71+H72+H73+H75+H76+H77+H78 -> 0 | I79: =I68+I69+I70+I71+I72+I73+I75+I76+I77+I78 -> 0 | J79: =J68+J69+J70+J71+J72+J73+J75+J76+J77+J78 -> 0 | K79: =K68+K69+K70+K71+K72+K73+K75+K76+K77+K78 -> 0 | L79: =L68+L69+L70+L71+L72+L73+L75+L76+L77+L78 -> 0 | M79: =M68+M69+M70+M71+M72+M73+M75+M76+M77+M78 -> 0 | N79: =N68+N69+N70+N71+N72+N73+N75+N76+N77+N78 -> 0 | ... BX79: =BX68+BX69+BX70+BX71+BX72+BX73+BX75+BX76+BX77+BX78 -> 0
B80: EBITDA | C80: m PLN | D80: =SUM(G80:BX80) -> 29950.591 | G80: =G65-G79 -> 0 | H80: =H65-H79 -> 0 | I80: =I65-I79 -> 0 | J80: =J65-J79 -> 0 | K80: =K65-K79 -> 0 | L80: =L65-L79 -> 0 | M80: =M65-M79 -> 0 | N80: =N65-N79 -> 0 | ... BX80: =BX65-BX79 -> 0
B81: End-of-life provision (nuclear: covered by fund) | C81: m PLN | D81: =SUM(G81:BX81) -> 0 | G81: =0 -> 0 | H81: =0 -> 0 | I81: =0 -> 0 | J81: =0 -> 0 | K81: =0 -> 0 | L81: =0 -> 0 | M81: =0 -> 0 | N81: =0 -> 0 | ... BX81: =0 -> 0
B83: 7. Tax (Polish CIT, straight-line KŚT depreciation, loss carry-forward)
B84: Depreciation — KŚT group (b) | C84: m PLN | D84: =SUM(G84:BX84) -> 2515 | G84: =IF(AND(G42=1,G43<=ROUNDUP(1/Input!$H$142,0)),MIN($D$52*Input!$H$76*Input!$H$142,MAX($D$52*Input!$H$76-$D$52*Input!$H$76*Input!$H$142*(G43-1),0)),0) -> 0 | H84: =IF(AND(H42=1,H43<=ROUNDUP(1/Input!$H$142,0)),MIN($D$52*Input!$H$76*Input!$H$142,MAX($D$52*Input!$H$76-$D$52*Input!$H$76*Input!$H$142*(H43-1),0)),0) -> 0 | I84: =IF(AND(I42=1,I43<=ROUNDUP(1/Input!$H$142,0)),MIN($D$52*Input!$H$76*Input!$H$142,MAX($D$52*Input!$H$76-$D$52*Input!$H$76*Input!$H$142*(I43-1),0)),0) -> 0 | J84: =IF(AND(J42=1,J43<=ROUNDUP(1/Input!$H$142,0)),MIN($D$52*Input!$H$76*Input!$H$142,MAX($D$52*Input!$H$76-$D$52*Input!$H$76*Input!$H$142*(J43-1),0)),0) -> 0 | K84: =IF(AND(K42=1,K43<=ROUNDUP(1/Input!$H$142,0)),MIN($D$52*Input!$H$76*Input!$H$142,MAX($D$52*Input!$H$76-$D$52*Input!$H$76*Input!$H$142*(K43-1),0)),0) -> 0 | L84: =IF(AND(L42=1,L43<=ROUNDUP(1/Input!$H$142,0)),MIN($D$52*Input!$H$76*Input!$H$142,MAX($D$52*Input!$H$76-$D$52*Input!$H$76*Input!$H$142*(L43-1),0)),0) -> 0 | M84: =IF(AND(M42=1,M43<=ROUNDUP(1/Input!$H$142,0)),MIN($D$52*Input!$H$76*Input!$H$142,MAX($D$52*Input!$H$76-$D$52*Input!$H$76*Input!$H$142*(M43-1),0)),0) -> 0 | N84: =IF(AND(N42=1,N43<=ROUNDUP(1/Input!$H$142,0)),MIN($D$52*Input!$H$76*Input!$H$142,MAX($D$52*Input!$H$76-$D$52*Input!$H$76*Input!$H$142*(N43-1),0)),0) -> 0 | ... BX84: =IF(AND(BX42=1,BX43<=ROUNDUP(1/Input!$H$142,0)),MIN($D$52*Input!$H$76*Input!$H$142,MAX($D$52*Input!$H$76-$D$52*Input!$H$76*Input!$H$142*(BX43-1),0)),0) -> 0
B85: Depreciation — KŚT group (s) | C85: m PLN | D85: =SUM(G85:BX85) -> 1886.25 | G85: =IF(AND(G42=1,G43<=ROUNDUP(1/Input!$H$143,0)),MIN($D$52*Input!$H$77*Input!$H$143,MAX($D$52*Input!$H$77-$D$52*Input!$H$77*Input!$H$143*(G43-1),0)),0) -> 0 | H85: =IF(AND(H42=1,H43<=ROUNDUP(1/Input!$H$143,0)),MIN($D$52*Input!$H$77*Input!$H$143,MAX($D$52*Input!$H$77-$D$52*Input!$H$77*Input!$H$143*(H43-1),0)),0) -> 0 | I85: =IF(AND(I42=1,I43<=ROUNDUP(1/Input!$H$143,0)),MIN($D$52*Input!$H$77*Input!$H$143,MAX($D$52*Input!$H$77-$D$52*Input!$H$77*Input!$H$143*(I43-1),0)),0) -> 0 | J85: =IF(AND(J42=1,J43<=ROUNDUP(1/Input!$H$143,0)),MIN($D$52*Input!$H$77*Input!$H$143,MAX($D$52*Input!$H$77-$D$52*Input!$H$77*Input!$H$143*(J43-1),0)),0) -> 0 | K85: =IF(AND(K42=1,K43<=ROUNDUP(1/Input!$H$143,0)),MIN($D$52*Input!$H$77*Input!$H$143,MAX($D$52*Input!$H$77-$D$52*Input!$H$77*Input!$H$143*(K43-1),0)),0) -> 0 | L85: =IF(AND(L42=1,L43<=ROUNDUP(1/Input!$H$143,0)),MIN($D$52*Input!$H$77*Input!$H$143,MAX($D$52*Input!$H$77-$D$52*Input!$H$77*Input!$H$143*(L43-1),0)),0) -> 0 | M85: =IF(AND(M42=1,M43<=ROUNDUP(1/Input!$H$143,0)),MIN($D$52*Input!$H$77*Input!$H$143,MAX($D$52*Input!$H$77-$D$52*Input!$H$77*Input!$H$143*(M43-1),0)),0) -> 0 | N85: =IF(AND(N42=1,N43<=ROUNDUP(1/Input!$H$143,0)),MIN($D$52*Input!$H$77*Input!$H$143,MAX($D$52*Input!$H$77-$D$52*Input!$H$77*Input!$H$143*(N43-1),0)),0) -> 0 | ... BX85: =IF(AND(BX42=1,BX43<=ROUNDUP(1/Input!$H$143,0)),MIN($D$52*Input!$H$77*Input!$H$143,MAX($D$52*Input!$H$77-$D$52*Input!$H$77*Input!$H$143*(BX43-1),0)),0) -> 0
B86: Depreciation — KŚT group (r) | C86: m PLN | D86: =SUM(G86:BX86) -> 3143.75 | G86: =IF(AND(G42=1,G43<=ROUNDUP(1/Input!$H$144,0)),MIN($D$52*Input!$H$78*Input!$H$144,MAX($D$52*Input!$H$78-$D$52*Input!$H$78*Input!$H$144*(G43-1),0)),0) -> 0 | H86: =IF(AND(H42=1,H43<=ROUNDUP(1/Input!$H$144,0)),MIN($D$52*Input!$H$78*Input!$H$144,MAX($D$52*Input!$H$78-$D$52*Input!$H$78*Input!$H$144*(H43-1),0)),0) -> 0 | I86: =IF(AND(I42=1,I43<=ROUNDUP(1/Input!$H$144,0)),MIN($D$52*Input!$H$78*Input!$H$144,MAX($D$52*Input!$H$78-$D$52*Input!$H$78*Input!$H$144*(I43-1),0)),0) -> 0 | J86: =IF(AND(J42=1,J43<=ROUNDUP(1/Input!$H$144,0)),MIN($D$52*Input!$H$78*Input!$H$144,MAX($D$52*Input!$H$78-$D$52*Input!$H$78*Input!$H$144*(J43-1),0)),0) -> 0 | K86: =IF(AND(K42=1,K43<=ROUNDUP(1/Input!$H$144,0)),MIN($D$52*Input!$H$78*Input!$H$144,MAX($D$52*Input!$H$78-$D$52*Input!$H$78*Input!$H$144*(K43-1),0)),0) -> 0 | L86: =IF(AND(L42=1,L43<=ROUNDUP(1/Input!$H$144,0)),MIN($D$52*Input!$H$78*Input!$H$144,MAX($D$52*Input!$H$78-$D$52*Input!$H$78*Input!$H$144*(L43-1),0)),0) -> 0 | M86: =IF(AND(M42=1,M43<=ROUNDUP(1/Input!$H$144,0)),MIN($D$52*Input!$H$78*Input!$H$144,MAX($D$52*Input!$H$78-$D$52*Input!$H$78*Input!$H$144*(M43-1),0)),0) -> 0 | N86: =IF(AND(N42=1,N43<=ROUNDUP(1/Input!$H$144,0)),MIN($D$52*Input!$H$78*Input!$H$144,MAX($D$52*Input!$H$78-$D$52*Input!$H$78*Input!$H$144*(N43-1),0)),0) -> 0 | ... BX86: =IF(AND(BX42=1,BX43<=ROUNDUP(1/Input!$H$144,0)),MIN($D$52*Input!$H$78*Input!$H$144,MAX($D$52*Input!$H$78-$D$52*Input!$H$78*Input!$H$144*(BX43-1),0)),0) -> 0
B87: Depreciation — KŚT group (t) | C87: m PLN | D87: =SUM(G87:BX87) -> 3772.5 | G87: =IF(AND(G42=1,G43<=ROUNDUP(1/Input!$H$145,0)),MIN($D$52*Input!$H$79*Input!$H$145,MAX($D$52*Input!$H$79-$D$52*Input!$H$79*Input!$H$145*(G43-1),0)),0) -> 0 | H87: =IF(AND(H42=1,H43<=ROUNDUP(1/Input!$H$145,0)),MIN($D$52*Input!$H$79*Input!$H$145,MAX($D$52*Input!$H$79-$D$52*Input!$H$79*Input!$H$145*(H43-1),0)),0) -> 0 | I87: =IF(AND(I42=1,I43<=ROUNDUP(1/Input!$H$145,0)),MIN($D$52*Input!$H$79*Input!$H$145,MAX($D$52*Input!$H$79-$D$52*Input!$H$79*Input!$H$145*(I43-1),0)),0) -> 0 | J87: =IF(AND(J42=1,J43<=ROUNDUP(1/Input!$H$145,0)),MIN($D$52*Input!$H$79*Input!$H$145,MAX($D$52*Input!$H$79-$D$52*Input!$H$79*Input!$H$145*(J43-1),0)),0) -> 0 | K87: =IF(AND(K42=1,K43<=ROUNDUP(1/Input!$H$145,0)),MIN($D$52*Input!$H$79*Input!$H$145,MAX($D$52*Input!$H$79-$D$52*Input!$H$79*Input!$H$145*(K43-1),0)),0) -> 0 | L87: =IF(AND(L42=1,L43<=ROUNDUP(1/Input!$H$145,0)),MIN($D$52*Input!$H$79*Input!$H$145,MAX($D$52*Input!$H$79-$D$52*Input!$H$79*Input!$H$145*(L43-1),0)),0) -> 0 | M87: =IF(AND(M42=1,M43<=ROUNDUP(1/Input!$H$145,0)),MIN($D$52*Input!$H$79*Input!$H$145,MAX($D$52*Input!$H$79-$D$52*Input!$H$79*Input!$H$145*(M43-1),0)),0) -> 0 | N87: =IF(AND(N42=1,N43<=ROUNDUP(1/Input!$H$145,0)),MIN($D$52*Input!$H$79*Input!$H$145,MAX($D$52*Input!$H$79-$D$52*Input!$H$79*Input!$H$145*(N43-1),0)),0) -> 0 | ... BX87: =IF(AND(BX42=1,BX43<=ROUNDUP(1/Input!$H$145,0)),MIN($D$52*Input!$H$79*Input!$H$145,MAX($D$52*Input!$H$79-$D$52*Input!$H$79*Input!$H$145*(BX43-1),0)),0) -> 0
B88: Depreciation — KŚT group (d) | C88: m PLN | D88: =SUM(G88:BX88) -> 1257.5 | G88: =IF(AND(G42=1,G43<=ROUNDUP(1/Input!$H$146,0)),MIN($D$52*Input!$H$80*Input!$H$146,MAX($D$52*Input!$H$80-$D$52*Input!$H$80*Input!$H$146*(G43-1),0)),0) -> 0 | H88: =IF(AND(H42=1,H43<=ROUNDUP(1/Input!$H$146,0)),MIN($D$52*Input!$H$80*Input!$H$146,MAX($D$52*Input!$H$80-$D$52*Input!$H$80*Input!$H$146*(H43-1),0)),0) -> 0 | I88: =IF(AND(I42=1,I43<=ROUNDUP(1/Input!$H$146,0)),MIN($D$52*Input!$H$80*Input!$H$146,MAX($D$52*Input!$H$80-$D$52*Input!$H$80*Input!$H$146*(I43-1),0)),0) -> 0 | J88: =IF(AND(J42=1,J43<=ROUNDUP(1/Input!$H$146,0)),MIN($D$52*Input!$H$80*Input!$H$146,MAX($D$52*Input!$H$80-$D$52*Input!$H$80*Input!$H$146*(J43-1),0)),0) -> 0 | K88: =IF(AND(K42=1,K43<=ROUNDUP(1/Input!$H$146,0)),MIN($D$52*Input!$H$80*Input!$H$146,MAX($D$52*Input!$H$80-$D$52*Input!$H$80*Input!$H$146*(K43-1),0)),0) -> 0 | L88: =IF(AND(L42=1,L43<=ROUNDUP(1/Input!$H$146,0)),MIN($D$52*Input!$H$80*Input!$H$146,MAX($D$52*Input!$H$80-$D$52*Input!$H$80*Input!$H$146*(L43-1),0)),0) -> 0 | M88: =IF(AND(M42=1,M43<=ROUNDUP(1/Input!$H$146,0)),MIN($D$52*Input!$H$80*Input!$H$146,MAX($D$52*Input!$H$80-$D$52*Input!$H$80*Input!$H$146*(M43-1),0)),0) -> 0 | N88: =IF(AND(N42=1,N43<=ROUNDUP(1/Input!$H$146,0)),MIN($D$52*Input!$H$80*Input!$H$146,MAX($D$52*Input!$H$80-$D$52*Input!$H$80*Input!$H$146*(N43-1),0)),0) -> 0 | ... BX88: =IF(AND(BX42=1,BX43<=ROUNDUP(1/Input!$H$146,0)),MIN($D$52*Input!$H$80*Input!$H$146,MAX($D$52*Input!$H$80-$D$52*Input!$H$80*Input!$H$146*(BX43-1),0)),0) -> 0
B89: Total tax depreciation | C89: m PLN | D89: =SUM(G89:BX89) -> 12575 | G89: =G84+G85+G86+G87+G88 -> 0 | H89: =H84+H85+H86+H87+H88 -> 0 | I89: =I84+I85+I86+I87+I88 -> 0 | J89: =J84+J85+J86+J87+J88 -> 0 | K89: =K84+K85+K86+K87+K88 -> 0 | L89: =L84+L85+L86+L87+L88 -> 0 | M89: =M84+M85+M86+M87+M88 -> 0 | N89: =N84+N85+N86+N87+N88 -> 0 | ... BX89: =BX84+BX85+BX86+BX87+BX88 -> 0
B90: Taxable EBIT (EBITDA − depreciation − provisions) | C90: m PLN | D90: =SUM(G90:BX90) -> 17375.591 | G90: =G80-G89-G81 -> 0 | H90: =H80-H89-H81 -> 0 | I90: =I80-I89-I81 -> 0 | J90: =J80-J89-J81 -> 0 | K90: =K80-K89-K81 -> 0 | L90: =L80-L89-L81 -> 0 | M90: =M80-M89-M81 -> 0 | N90: =N80-N89-N81 -> 0 | ... BX90: =BX80-BX89-BX81 -> 0
B91: Loss utilisation (50 % cap per year, simplified pool) | C91: m PLN | G91: =0 -> 0 | H91: =IF(H90>0,MIN(G92,0.5*H90),0) -> 0 | I91: =IF(I90>0,MIN(H92,0.5*I90),0) -> 0 | J91: =IF(J90>0,MIN(I92,0.5*J90),0) -> 0 | K91: =IF(K90>0,MIN(J92,0.5*K90),0) -> 0 | L91: =IF(L90>0,MIN(K92,0.5*L90),0) -> 0 | M91: =IF(M90>0,MIN(L92,0.5*M90),0) -> 0 | N91: =IF(N90>0,MIN(M92,0.5*N90),0) -> 0 | O91: =IF(O90>0,MIN(N92,0.5*O90),0) -> 0 | ... BX91: =IF(BX90>0,MIN(BW92,0.5*BX90),0) -> 0
B92: Loss pool carried forward (EoY) | C92: m PLN | G92: =MAX(-G90,0) -> 0 | H92: =MAX(G92-H91+MAX(-H90,0),0) -> 0 | I92: =MAX(H92-I91+MAX(-I90,0),0) -> 0 | J92: =MAX(I92-J91+MAX(-J90,0),0) -> 0 | K92: =MAX(J92-K91+MAX(-K90,0),0) -> 0 | L92: =MAX(K92-L91+MAX(-L90,0),0) -> 0 | M92: =MAX(L92-M91+MAX(-M90,0),0) -> 0 | N92: =MAX(M92-N91+MAX(-N90,0),0) -> 0 | O92: =MAX(N92-O91+MAX(-O90,0),0) -> 504.64125 | ... BX92: =MAX(BW92-BX91+MAX(-BX90,0),0) -> 0
B93: Taxable income | C93: m PLN | D93: =SUM(G93:BX93) -> 17375.591 | G93: =MAX(G90-G91,0) -> 0 | H93: =MAX(H90-H91,0) -> 0 | I93: =MAX(I90-I91,0) -> 0 | J93: =MAX(J90-J91,0) -> 0 | K93: =MAX(K90-K91,0) -> 0 | L93: =MAX(L90-L91,0) -> 0 | M93: =MAX(M90-M91,0) -> 0 | N93: =MAX(N90-N91,0) -> 0 | ... BX93: =MAX(BX90-BX91,0) -> 0
B94: CIT | C94: m PLN | D94: =SUM(G94:BX94) -> 3301.3622 | G94: =G93*$D$17 -> 0 | H94: =H93*$D$17 -> 0 | I94: =I93*$D$17 -> 0 | J94: =J93*$D$17 -> 0 | K94: =K93*$D$17 -> 0 | L94: =L93*$D$17 -> 0 | M94: =M93*$D$17 -> 0 | N94: =N93*$D$17 -> 0 | ... BX94: =BX93*$D$17 -> 0
B96: 8. Cash flow and valuation (m PLN)
B97: Pre-tax free cash flow | C97: m PLN | D97: =SUM(G97:BX97) -> 17375.591 | G97: =G80-G52-G81 -> 0 | H97: =H80-H52-H81 -> 0 | I97: =I80-I52-I81 -> 0 | J97: =J80-J52-J81 -> -1948.2073 | K97: =K80-K52-K81 -> -2632.2657 | L97: =L80-L52-L81 -> -3364.0541 | M97: =M80-M52-M81 -> -2632.2657 | N97: =N80-N52-N81 -> -1998.2073 | ... BX97: =BX80-BX52-BX81 -> 0
B98: Post-tax free cash flow (unlevered) | C98: m PLN | D98: =SUM(G98:BX98) -> 14074.228 | G98: =G97-G94 -> 0 | H98: =H97-H94 -> 0 | I98: =I97-I94 -> 0 | J98: =J97-J94 -> -1948.2073 | K98: =K97-K94 -> -2632.2657 | L98: =L97-L94 -> -3364.0541 | M98: =M97-M94 -> -2632.2657 | N98: =N97-N94 -> -1998.2073 | ... BX98: =BX97-BX94 -> 0
B99: Cumulative post-tax FCF | C99: m PLN | G99: =G98 -> 0 | H99: =G99+H98 -> 0 | I99: =H99+I98 -> 0 | J99: =I99+J98 -> -1948.2073 | K99: =J99+K98 -> -4580.473 | L99: =K99+L98 -> -7944.527 | M99: =L99+M98 -> -10576.793 | N99: =M99+N98 -> -12575 | O99: =N99+O98 -> -12101.935 | ... BX99: =BW99+BX98 -> 14074.228
B100: Discounted post-tax FCF | C100: m PLN | D100: =SUM(G100:BX100) -> -5904.5069 | G100: =G98*G45 -> 0 | H100: =H98*H45 -> 0 | I100: =I98*I45 -> 0 | J100: =J98*J45 -> -1948.2073 | K100: =K98*K45 -> -2460.0614 | L100: =L98*L45 -> -2938.2951 | M100: =M98*M45 -> -2148.7129 | N100: =N98*N45 -> -1524.4228 | ... BX100: =BX98*BX45 -> 0
B101: NPV post-tax @ WACC (m PLN) | D101: =SUMPRODUCT($G$98:$BX$98,$G$45:$BX$45) -> -5904.5069
B102: NPV pre-tax @ WACC (m PLN) | D102: =SUMPRODUCT($G$97:$BX$97,$G$45:$BX$45) -> -5687.7416
B103: IRR post-tax (real) | D103: =IFERROR(IRR(OFFSET(G98,0,$D$12-2027,1,$D$11+$D$9),0.05),"n/a") -> 0.028078146
B104: PV of generation (MWh) | D104: =SUMPRODUCT($G$59:$BX$59,$G$45:$BX$45) -> 25005740
B105: PV of all costs (capex + opex + provisions) | D105: =SUMPRODUCT($G$52:$BX$52,$G$45:$BX$45)+SUMPRODUCT($G$79:$BX$79,$G$45:$BX$45)+SUMPRODUCT($G$81:$BX$81,$G$45:$BX$45) -> 15738.801
B106: PV capex | D106: =SUMPRODUCT($G$52:$BX$52,$G$45:$BX$45) -> 11019.699
B107: PV fixed O&M | D107: =SUMPRODUCT($G$73:$BX$73,$G$45:$BX$45) -> 1845.2581
B108: PV fuel | D108: =SUMPRODUCT($G$68:$BX$68,$G$45:$BX$45) -> 776.6732
B109: PV CO2 | D109: =SUMPRODUCT($G$69:$BX$69,$G$45:$BX$45) -> 0
...

Sheet Model_CCGT
B1: CCGT 1+1 ~300 MW · merchant dynamic
B2: Annual model, real PLN m (2026). Column D = totals / KPIs. Timeline columns G→. Dispatch quantities come from the Twin sheet (hourly digital twin).
B4: Year | G4: 2027 | H4: 2028 | I4: 2029 | J4: 2030 | K4: 2031 | L4: 2032 | M4: 2033 | N4: 2034 | O4: 2035 | P4: 2036 | Q4: 2037 | R4: 2038 | S4: 2039 | T4: 2040 | U4: 2041 | V4: 2042 | W4: 2043 | X4: 2044 | Y4: 2045 | Z4: 2046 | AA4: 2047 | AB4: 2048 | AC4: 2049 | AD4: 2050 | AE4: 2051 | AF4: 2052 | AG4: 2053 | AH4: 2054 | AI4: 2055 | AJ4: 2056 | AK4: 2057 | AL4: 2058 | AM4: 2059 | AN4: 2060 | AO4: 2061 | AP4: 2062 | AQ4: 2063 | AR4: 2064 | AS4: 2065 | AT4: 2066 | AU4: 2067 | AV4: 2068 | AW4: 2069 | AX4: 2070 | AY4: 2071 | AZ4: 2072 | BA4: 2073 | BB4: 2074 | BC4: 2075 | BD4: 2076 | BE4: 2077 | BF4: 2078 | BG4: 2079 | BH4: 2080 | BI4: 2081 | BJ4: 2082 | BK4: 2083 | BL4: 2084 | BM4: 2085 | BN4: 2086 | BO4: 2087 | BP4: 2088 | BQ4: 2089 | BR4: 2090 | BS4: 2091 | BT4: 2092 | BU4: 2093 | BV4: 2094 | BW4: 2095 | BX4: 2096
B6: 1. Parameters (links to Input, selected case)
B7: Net capacity, MW | D7: =Input!$H$90 -> 300
B8: Overnight capex, PLN/kW | D8: =Input!$H$91 -> 6200
B9: Construction years | D9: =Input!$H$92 -> 4
B10: COD year | D10: =Input!$H$83 -> 2031
B11: Life years | D11: =Input!$H$93 -> 30
B12: FID year (COD − construction) | D12: =$D$10-$D$9 -> 2027
B13: Real post-tax WACC | D13: =Input!$H$17 -> 0.07
B14: Fixed O&M, PLN/kW-yr | D14: =Input!$H$95 -> 100
B15: Variable O&M, PLN/MWh | D15: =Input!$H$96 -> 16
B16: EUR/PLN | D16: =Input!$H$10 -> 4.3633
B17: CIT rate | D17: =Input!$H$141 -> 0.19
B18: Licence fee share of revenue | D18: =Input!$H$31 -> 0.005
B19: Staff FTE | D19: =Input!$H$98 -> 60
B20: Loaded cost per FTE, k PLN | D20: =Input!$H$99 -> 200
B21: Budowle share of capex | D21: =Input!$H$100 -> 0.15
B22: Property tax rate | D22: =Input!$H$84 -> 0.02
B23: Host-gmina share of property tax | D23: =1 -> 1
B24: Overnight cost, m PLN | D24: =$D$8*$D$7*1000/1000000 -> 1860
B25: Net efficiency full load | D25: =Input!$H$94 -> 0.57
B26: CO2 factor, t/MWh_th | D26: =Input!$H$30 -> 0.2006
B27: Gas exit-capacity booking, PLN/kW-yr | D27: =Input!$H$97 -> 58
B28: Grid connection, PLN/kW | D28: =Input!$H$85 -> 350
B29: Demolition provision share | D29: =Input!$H$86 -> 0.05
B30: Capacity-market de-rating | D30: =Input!$H$26 -> 0.9315
B31: Balancing revenue, PLN/kW-yr | D31: =Input!$H$28 -> 15
B32: Peak construction workforce | D32: =Input!$H$87*$D$7/300 -> 300
B33: Capacity-market price, PLN/kW-yr | D33: =Input!$H$23 -> 0
B34: Capacity contract years | D34: =Input!$H$24 -> 17
B36: 2. Timing
B37: Construction flag | C37: 0/1 | G37: =IF(AND(G$4>=$D$12,G$4<$D$10),1,0) -> 1 | H37: =IF(AND(H$4>=$D$12,H$4<$D$10),1,0) -> 1 | I37: =IF(AND(I$4>=$D$12,I$4<$D$10),1,0) -> 1 | J37: =IF(AND(J$4>=$D$12,J$4<$D$10),1,0) -> 1 | K37: =IF(AND(K$4>=$D$12,K$4<$D$10),1,0) -> 0 | L37: =IF(AND(L$4>=$D$12,L$4<$D$10),1,0) -> 0 | M37: =IF(AND(M$4>=$D$12,M$4<$D$10),1,0) -> 0 | N37: =IF(AND(N$4>=$D$12,N$4<$D$10),1,0) -> 0 | ... BX37: =IF(AND(BX$4>=$D$12,BX$4<$D$10),1,0) -> 0
B38: Operating flag | C38: 0/1 | G38: =IF(AND(G$4>=$D$10,G$4<$D$10+$D$11),1,0) -> 0 | H38: =IF(AND(H$4>=$D$10,H$4<$D$10+$D$11),1,0) -> 0 | I38: =IF(AND(I$4>=$D$10,I$4<$D$10+$D$11),1,0) -> 0 | J38: =IF(AND(J$4>=$D$10,J$4<$D$10+$D$11),1,0) -> 0 | K38: =IF(AND(K$4>=$D$10,K$4<$D$10+$D$11),1,0) -> 1 | L38: =IF(AND(L$4>=$D$10,L$4<$D$10+$D$11),1,0) -> 1 | M38: =IF(AND(M$4>=$D$10,M$4<$D$10+$D$11),1,0) -> 1 | N38: =IF(AND(N$4>=$D$10,N$4<$D$10+$D$11),1,0) -> 1 | ... BX38: =IF(AND(BX$4>=$D$10,BX$4<$D$10+$D$11),1,0) -> 0
B39: Operating year k | C39: # | G39: =IF(G38=1,G$4-$D$10+1,0) -> 0 | H39: =IF(H38=1,H$4-$D$10+1,0) -> 0 | I39: =IF(I38=1,I$4-$D$10+1,0) -> 0 | J39: =IF(J38=1,J$4-$D$10+1,0) -> 0 | K39: =IF(K38=1,K$4-$D$10+1,0) -> 1 | L39: =IF(L38=1,L$4-$D$10+1,0) -> 2 | M39: =IF(M38=1,M$4-$D$10+1,0) -> 3 | N39: =IF(N38=1,N$4-$D$10+1,0) -> 4 | ... BX39: =IF(BX38=1,BX$4-$D$10+1,0) -> 0
B40: Discount period (years from FID) | C40: # | G40: =G$4-$D$12 -> 0 | H40: =H$4-$D$12 -> 1 | I40: =I$4-$D$12 -> 2 | J40: =J$4-$D$12 -> 3 | K40: =K$4-$D$12 -> 4 | L40: =L$4-$D$12 -> 5 | M40: =M$4-$D$12 -> 6 | N40: =N$4-$D$12 -> 7 | ... BX40: =BX$4-$D$12 -> 69
B41: Discount factor | C41: # | G41: =IF(G$4>=$D$12,1/(1+$D$13)^G40,0) -> 1 | H41: =IF(H$4>=$D$12,1/(1+$D$13)^H40,0) -> 0.93457944 | I41: =IF(I$4>=$D$12,1/(1+$D$13)^I40,0) -> 0.87343873 | J41: =IF(J$4>=$D$12,1/(1+$D$13)^J40,0) -> 0.81629788 | K41: =IF(K$4>=$D$12,1/(1+$D$13)^K40,0) -> 0.76289521 | L41: =IF(L$4>=$D$12,1/(1+$D$13)^L40,0) -> 0.71298618 | M41: =IF(M$4>=$D$12,1/(1+$D$13)^M40,0) -> 0.66634222 | N41: =IF(N$4>=$D$12,1/(1+$D$13)^N40,0) -> 0.62274974 | ... BX41: =IF(BX$4>=$D$12,1/(1+$D$13)^BX40,0) -> 0.0093868384
B42: Capex spend share (S-curve, normalised) | C42: % | G42: =IF(G37=1,IF(G$4-$D$12=0,0.3,IF(G$4-$D$12=1,0.45,0.25/MAX($D$9-2,1))),0) -> 0.3 | H42: =IF(H37=1,IF(H$4-$D$12=0,0.3,IF(H$4-$D$12=1,0.45,0.25/MAX($D$9-2,1))),0) -> 0.45 | I42: =IF(I37=1,IF(I$4-$D$12=0,0.3,IF(I$4-$D$12=1,0.45,0.25/MAX($D$9-2,1))),0) -> 0.125 | J42: =IF(J37=1,IF(J$4-$D$12=0,0.3,IF(J$4-$D$12=1,0.45,0.25/MAX($D$9-2,1))),0) -> 0.125 | K42: =IF(K37=1,IF(K$4-$D$12=0,0.3,IF(K$4-$D$12=1,0.45,0.25/MAX($D$9-2,1))),0) -> 0 | L42: =IF(L37=1,IF(L$4-$D$12=0,0.3,IF(L$4-$D$12=1,0.45,0.25/MAX($D$9-2,1))),0) -> 0 | M42: =IF(M37=1,IF(M$4-$D$12=0,0.3,IF(M$4-$D$12=1,0.45,0.25/MAX($D$9-2,1))),0) -> 0 | N42: =IF(N37=1,IF(N$4-$D$12=0,0.3,IF(N$4-$D$12=1,0.45,0.25/MAX($D$9-2,1))),0) -> 0 | ... BX42: =IF(BX37=1,IF(BX$4-$D$12=0,0.3,IF(BX$4-$D$12=1,0.45,0.25/MAX($D$9-2,1))),0) -> 0
B43: Capex spend share normalised | C43: % | G43: =IF(SUM($G42:$BX42)>0,G42/SUM($G42:$BX42),0) -> 0.3 | H43: =IF(SUM($G42:$BX42)>0,H42/SUM($G42:$BX42),0) -> 0.45 | I43: =IF(SUM($G42:$BX42)>0,I42/SUM($G42:$BX42),0) -> 0.125 | J43: =IF(SUM($G42:$BX42)>0,J42/SUM($G42:$BX42),0) -> 0.125 | K43: =IF(SUM($G42:$BX42)>0,K42/SUM($G42:$BX42),0) -> 0 | L43: =IF(SUM($G42:$BX42)>0,L42/SUM($G42:$BX42),0) -> 0 | M43: =IF(SUM($G42:$BX42)>0,M42/SUM($G42:$BX42),0) -> 0 | N43: =IF(SUM($G42:$BX42)>0,N42/SUM($G42:$BX42),0) -> 0 | ... BX43: =IF(SUM($G42:$BX42)>0,BX42/SUM($G42:$BX42),0) -> 0
B45: 3. Investment (m PLN)
B46: Overnight capex spend | C46: m PLN | D46: =SUM(G46:BX46) -> 1860 | G46: =$D$24*G43 -> 558 | H46: =$D$24*H43 -> 837 | I46: =$D$24*I43 -> 232.5 | J46: =$D$24*J43 -> 232.5 | K46: =$D$24*K43 -> 0 | L46: =$D$24*L43 -> 0 | M46: =$D$24*M43 -> 0 | N46: =$D$24*N43 -> 0 | ... BX46: =$D$24*BX43 -> 0
B47: Other capex (grid connection, spread) | C47: m PLN | D47: =SUM(G47:BX47) -> 105 | G47: =$D$28*$D$7/1000*G43 -> 31.5 | H47: =$D$28*$D$7/1000*H43 -> 47.25 | I47: =$D$28*$D$7/1000*I43 -> 13.125 | J47: =$D$28*$D$7/1000*J43 -> 13.125 | K47: =$D$28*$D$7/1000*K43 -> 0 | L47: =$D$28*$D$7/1000*L43 -> 0 | M47: =$D$28*$D$7/1000*M43 -> 0 | N47: =$D$28*$D$7/1000*N43 -> 0 | ... BX47: =$D$28*$D$7/1000*BX43 -> 0
B48: Total capex | C48: m PLN | D48: =SUM(G48:BX48) -> 1965 | G48: =G46+G47 -> 589.5 | H48: =H46+H47 -> 884.25 | I48: =I46+I47 -> 245.625 | J48: =J46+J47 -> 245.625 | K48: =K46+K47 -> 0 | L48: =L46+L47 -> 0 | M48: =M46+M47 -> 0 | N48: =N46+N47 -> 0 | ... BX48: =BX46+BX47 -> 0
B50: 4. Market inputs (selected case, from Input)
B51: Annual mean day-ahead price | C51: PLN/MWh | G51: =Input!J36 -> 496 | H51: =Input!K36 -> 445 | I51: =Input!L36 -> 420 | J51: =Input!M36 -> 410 | K51: =Input!N36 -> 408 | L51: =Input!O36 -> 406 | M51: =Input!P36 -> 404 | N51: =Input!Q36 -> 402 | ... BX51: =Input!CA36 -> 380
B52: Gas price (PL virtual point) | C52: PLN/MWh_th | G52: =Input!J42 -> 214 | H52: =Input!K42 -> 165 | I52: =Input!L42 -> 145 | J52: =Input!M42 -> 135 | K52: =Input!N42 -> 135 | L52: =Input!O42 -> 135 | M52: =Input!P42 -> 135 | N52: =Input!Q42 -> 135 | ... BX52: =Input!CA42 -> 135
B53: EUA price | C53: PLN/t | G53: =Input!J48*$D$16 -> 392.697 | H53: =Input!K48*$D$16 -> 429.05783 | I53: =Input!L48*$D$16 -> 465.41867 | J53: =Input!M48*$D$16 -> 501.7795 | K53: =Input!N48*$D$16 -> 523.596 | L53: =Input!O48*$D$16 -> 545.4125 | M53: =Input!P48*$D$16 -> 567.229 | N53: =Input!Q48*$D$16 -> 589.0455 | ... BX53: =Input!CA48*$D$16 -> 654.495
B55: 5. Dispatch (from hourly twin) and revenue
B56: Capacity factor (twin) | C56: % | G56: =IF(G38=1,IFERROR(INDEX(Twin!$G$51:$BN$51,1,G39),0),0) -> 0 | H56: =IF(H38=1,IFERROR(INDEX(Twin!$G$51:$BN$51,1,H39),0),0) -> 0 | I56: =IF(I38=1,IFERROR(INDEX(Twin!$G$51:$BN$51,1,I39),0),0) -> 0 | J56: =IF(J38=1,IFERROR(INDEX(Twin!$G$51:$BN$51,1,J39),0),0) -> 0 | K56: =IF(K38=1,IFERROR(INDEX(Twin!$G$51:$BN$51,1,K39),0),0) -> 0.32748801 | L56: =IF(L38=1,IFERROR(INDEX(Twin!$G$51:$BN$51,1,L39),0),0) -> 0.30922032 | M56: =IF(M38=1,IFERROR(INDEX(Twin!$G$51:$BN$51,1,M39),0),0) -> 0.28138584 | N56: =IF(N38=1,IFERROR(INDEX(Twin!$G$51:$BN$51,1,N39),0),0) -> 0.25154509 | ... BX56: =IF(BX38=1,IFERROR(INDEX(Twin!$G$51:$BN$51,1,BX39),0),0) -> 0
B57: Net generation | C57: MWh | D57: =SUM(G57:BX57) -> 13554154 | G57: =G56*$D$7*8760 -> 0 | H57: =H56*$D$7*8760 -> 0 | I57: =I56*$D$7*8760 -> 0 | J57: =J56*$D$7*8760 -> 0 | K57: =K56*$D$7*8760 -> 860638.5 | L57: =L56*$D$7*8760 -> 812631 | M57: =M56*$D$7*8760 -> 739482 | N57: =N56*$D$7*8760 -> 661060.5 | ... BX57: =BX56*$D$7*8760 -> 0
B58: Capture price = mean × capture ratio (twin) | C58: PLN/MWh | G58: =IF(G38=1,G51*IFERROR(INDEX(Twin!$G$55:$BN$55,1,G39),0),0) -> 0 | H58: =IF(H38=1,H51*IFERROR(INDEX(Twin!$G$55:$BN$55,1,H39),0),0) -> 0 | I58: =IF(I38=1,I51*IFERROR(INDEX(Twin!$G$55:$BN$55,1,I39),0),0) -> 0 | J58: =IF(J38=1,J51*IFERROR(INDEX(Twin!$G$55:$BN$55,1,J39),0),0) -> 0 | K58: =IF(K38=1,K51*IFERROR(INDEX(Twin!$G$55:$BN$55,1,K39),0),0) -> 576.81317 | L58: =IF(L38=1,L51*IFERROR(INDEX(Twin!$G$55:$BN$55,1,L39),0),0) -> 581.83231 | M58: =IF(M38=1,M51*IFERROR(INDEX(Twin!$G$55:$BN$55,1,M39),0),0) -> 592.65278 | N58: =IF(N38=1,N51*IFERROR(INDEX(Twin!$G$55:$BN$55,1,N39),0),0) -> 605.99403 | ... BX58: =IF(BX38=1,BX51*IFERROR(INDEX(Twin!$G$55:$BN$55,1,BX39),0),0) -> 0
B59: Market revenue | C59: m PLN | D59: =SUM(G59:BX59) -> 8664.8085 | G59: =G57*G58/1000000 -> 0 | H59: =H57*H58/1000000 -> 0 | I59: =I57*I58/1000000 -> 0 | J59: =J57*J58/1000000 -> 0 | K59: =K57*K58/1000000 -> 496.42762 | L59: =L57*L58/1000000 -> 472.81497 | M59: =M57*M58/1000000 -> 438.25606 | N59: =N57*N58/1000000 -> 400.59872 | ... BX59: =BX57*BX58/1000000 -> 0
B60: CfD difference payment | C60: m PLN | D60: =SUM(G60:BX60) -> 0 | G60: =0 -> 0 | H60: =0 -> 0 | I60: =0 -> 0 | J60: =0 -> 0 | K60: =0 -> 0 | L60: =0 -> 0 | M60: =0 -> 0 | N60: =0 -> 0 | ... BX60: =0 -> 0
B61: Capacity-market revenue | C61: m PLN | D61: =SUM(G61:BX61) -> 0 | G61: =IF(AND(G38=1,G39<=$D$34),$D$33*$D$30*$D$7*1000/1000000,0) -> 0 | H61: =IF(AND(H38=1,H39<=$D$34),$D$33*$D$30*$D$7*1000/1000000,0) -> 0 | I61: =IF(AND(I38=1,I39<=$D$34),$D$33*$D$30*$D$7*1000/1000000,0) -> 0 | J61: =IF(AND(J38=1,J39<=$D$34),$D$33*$D$30*$D$7*1000/1000000,0) -> 0 | K61: =IF(AND(K38=1,K39<=$D$34),$D$33*$D$30*$D$7*1000/1000000,0) -> 0 | L61: =IF(AND(L38=1,L39<=$D$34),$D$33*$D$30*$D$7*1000/1000000,0) -> 0 | M61: =IF(AND(M38=1,M39<=$D$34),$D$33*$D$30*$D$7*1000/1000000,0) -> 0 | N61: =IF(AND(N38=1,N39<=$D$34),$D$33*$D$30*$D$7*1000/1000000,0) -> 0 | ... BX61: =IF(AND(BX38=1,BX39<=$D$34),$D$33*$D$30*$D$7*1000/1000000,0) -> 0
B62: Balancing-services revenue | C62: m PLN | D62: =SUM(G62:BX62) -> 135 | G62: =IF(G38=1,$D$31*$D$7*1000/1000000,0) -> 0 | H62: =IF(H38=1,$D$31*$D$7*1000/1000000,0) -> 0 | I62: =IF(I38=1,$D$31*$D$7*1000/1000000,0) -> 0 | J62: =IF(J38=1,$D$31*$D$7*1000/1000000,0) -> 0 | K62: =IF(K38=1,$D$31*$D$7*1000/1000000,0) -> 4.5 | L62: =IF(L38=1,$D$31*$D$7*1000/1000000,0) -> 4.5 | M62: =IF(M38=1,$D$31*$D$7*1000/1000000,0) -> 4.5 | N62: =IF(N38=1,$D$31*$D$7*1000/1000000,0) -> 4.5 | ... BX62: =IF(BX38=1,$D$31*$D$7*1000/1000000,0) -> 0
B63: Total revenue | C63: m PLN | D63: =SUM(G63:BX63) -> 8799.8085 | G63: =G59+G60+G61+G62 -> 0 | H63: =H59+H60+H61+H62 -> 0 | I63: =I59+I60+I61+I62 -> 0 | J63: =J59+J60+J61+J62 -> 0 | K63: =K59+K60+K61+K62 -> 500.92762 | L63: =L59+L60+L61+L62 -> 477.31497 | M63: =M59+M60+M61+M62 -> 442.75606 | N63: =N59+N60+N61+N62 -> 405.09872 | ... BX63: =BX59+BX60+BX61+BX62 -> 0
B65: 6. Operating costs (m PLN)
B66: Heat input (twin heat rate incl. no-load & start fuel) | C66: MWh_th | D66: =SUM(G66:BX66) -> 23752276 | G66: =IF(G38=1,G57*IFERROR(INDEX(Twin!$G$59:$BN$59,1,G39),0),0) -> 0 | H66: =IF(H38=1,H57*IFERROR(INDEX(Twin!$G$59:$BN$59,1,H39),0),0) -> 0 | I66: =IF(I38=1,I57*IFERROR(INDEX(Twin!$G$59:$BN$59,1,I39),0),0) -> 0 | J66: =IF(J38=1,J57*IFERROR(INDEX(Twin!$G$59:$BN$59,1,J39),0),0) -> 0 | K66: =IF(K38=1,K57*IFERROR(INDEX(Twin!$G$59:$BN$59,1,K39),0),0) -> 1495816.6 | L66: =IF(L38=1,L57*IFERROR(INDEX(Twin!$G$59:$BN$59,1,L39),0),0) -> 1412044.5 | M66: =IF(M38=1,M57*IFERROR(INDEX(Twin!$G$59:$BN$59,1,M39),0),0) -> 1288055 | N66: =IF(N38=1,N57*IFERROR(INDEX(Twin!$G$59:$BN$59,1,N39),0),0) -> 1153733.6 | ... BX66: =IF(BX38=1,BX57*IFERROR(INDEX(Twin!$G$59:$BN$59,1,BX39),0),0) -> 0
B67: Gas cost | C67: m PLN | D67: =SUM(G67:BX67) -> 3206.5573 | G67: =G66*G52/1000000 -> 0 | H67: =H66*H52/1000000 -> 0 | I67: =I66*I52/1000000 -> 0 | J67: =J66*J52/1000000 -> 0 | K67: =K66*K52/1000000 -> 201.93524 | L67: =L66*L52/1000000 -> 190.626 | M67: =M66*M52/1000000 -> 173.88743 | N67: =N66*N52/1000000 -> 155.75404 | ... BX67: =BX66*BX52/1000000 -> 0
B68: CO2 emissions | C68: t | D68: =SUM(G68:BX68) -> 4764706.6 | G68: =G66*$D$26 -> 0 | H68: =H66*$D$26 -> 0 | I68: =I66*$D$26 -> 0 | J68: =J66*$D$26 -> 0 | K68: =K66*$D$26 -> 300060.8 | L68: =L66*$D$26 -> 283256.12 | M68: =M66*$D$26 -> 258383.84 | N68: =N66*$D$26 -> 231438.96 | ... BX68: =BX66*$D$26 -> 0
